Workbook

Sheet Dashboard
B2: FEC Corporate Deals and Aggregators: Weekly Management Review
B3: E3 Events and Entertainments | Prepared by Rajan Pathak, Head of Operations (FEC & IT) | Tuesday management meeting
B4: Reporting week (ISO) | C4: 2026-W37 | D4: Previous week | E4: =IF(VALUE(RIGHT(C4,2))=1,LEFT(C4,4)-1&"-W52",LEFT(C4,6)&TEXT(VALUE(RIGHT(C4,2))-1,"00")) -> 2026-W36 | H4: Meeting date | J4: Reviewed by | K4: Mr. Adil
B5: Type the ISO week into C4 after pasting the new export into Weekly Log. Everything below recalculates. | C5: =E4 -> 2026-W36
B7: Partner redemptions | D7: Tickets under deals | F7: Discount given (QAR) | H7: Active partners | J7: Aggregator share of discount
B8: =Summary!B9 -> 194 | D8: =Summary!C9 -> 576 | F8: =Summary!D9 -> 12750.5 | H8: =Summary!E9&" of 21" -> 12 of 21 | J8: =IF(K16=0,0,K15/K16) -> 0.67981648
B10: =IF(COUNTIF('Weekly Log'!$G$5:$G$636,$E$4)=0,"No previous week in log yet",IF(Summary!B9-SUMPRODUCT(Summary!K25:K45)>=0,"+","")&TEXT(Summary!B9-SUMPRODUCT(Summary!K25:K45),"#,##0")&" vs previous week") -> No previous week in log yet
B12: Top partners this week | H12: Corporate discounts vs aggregator BOGO, this week
B13: Partner | C13: This week | D13: Prev week | E13: Change | F13: Month to date | H13: Category | I13: Redemptions | J13: Tickets | K13: Discount QAR | L13: QAR per redempt.
B14: =IFERROR(INDEX(Summary!$A$25:$A$45,MATCH(LARGE(Summary!$M$25:$M$45,1),Summary!$M$25:$M$45,0)),"") -> Imtyazat | C14: =IFERROR(INDEX(Summary!$C$25:$C$45,MATCH($B14,Summary!$A$25:$A$45,0)),0) -> 40 | D14: =IFERROR(INDEX(Summary!$K$25:$K$45,MATCH($B14,Summary!$A$25:$A$45,0)),0) -> 0 | E14: =C14-D14 -> 40 | F14: =IFERROR(INDEX(Summary!$D$25:$D$45,MATCH($B14,Summary!$A$25:$A$45,0)),0) -> 72 | H14: Corporate discount | I14: =SUMPRODUCT((Summary!$B$25:$B$45="Corporate discount")*Summary!$C$25:$C$45) -> 139 | J14: =SUMIFS('Weekly Log'!$J$5:$J$636,'Weekly Log'!$G$5:$G$636,$C$4,'Weekly Log'!$M$5:$M$636,"Corporate discount") -> 521 | K14: =SUMIFS('Weekly Log'!$K$5:$K$636,'Weekly Log'!$G$5:$G$636,$C$4,'Weekly Log'!$M$5:$M$636,"Corporate discount") -> 4082.5 | L14: =IF(I14=0,0,K14/I14) -> 29.370504
B15: =IFERROR(INDEX(Summary!$A$25:$A$45,MATCH(LARGE(Summary!$M$25:$M$45,2),Summary!$M$25:$M$45,0)),"") -> Qatar Airways | C15: =IFERROR(INDEX(Summary!$C$25:$C$45,MATCH($B15,Summary!$A$25:$A$45,0)),0) -> 37 | D15: =IFERROR(INDEX(Summary!$K$25:$K$45,MATCH($B15,Summary!$A$25:$A$45,0)),0) -> 0 | E15: =C15-D15 -> 37 | F15: =IFERROR(INDEX(Summary!$D$25:$D$45,MATCH($B15,Summary!$A$25:$A$45,0)),0) -> 66 | H15: Aggregator BOGO | I15: =SUMPRODUCT((Summary!$B$25:$B$45="Aggregator BOGO")*Summary!$C$25:$C$45) -> 55 | J15: =SUMIFS('Weekly Log'!$J$5:$J$636,'Weekly Log'!$G$5:$G$636,$C$4,'Weekly Log'!$M$5:$M$636,"Aggregator BOGO") -> 55 | K15: =SUMIFS('Weekly Log'!$K$5:$K$636,'Weekly Log'!$G$5:$G$636,$C$4,'Weekly Log'!$M$5:$M$636,"Aggregator BOGO") -> 8668 | L15: =IF(I15=0,0,K15/I15) -> 157.6
B16: =IFERROR(INDEX(Summary!$A$25:$A$45,MATCH(LARGE(Summary!$M$25:$M$45,3),Summary!$M$25:$M$45,0)),"") -> Urban Point | C16: =IFERROR(INDEX(Summary!$C$25:$C$45,MATCH($B16,Summary!$A$25:$A$45,0)),0) -> 27 | D16: =IFERROR(INDEX(Summary!$K$25:$K$45,MATCH($B16,Summary!$A$25:$A$45,0)),0) -> 0 | E16: =C16-D16 -> 27 | F16: =IFERROR(INDEX(Summary!$D$25:$D$45,MATCH($B16,Summary!$A$25:$A$45,0)),0) -> 40 | H16: Total | I16: =SUM(I14:I15) -> 194 | J16: =SUM(J14:J15) -> 576 | K16: =SUM(K14:K15) -> 12750.5
B17: =IFERROR(INDEX(Summary!$A$25:$A$45,MATCH(LARGE(Summary!$M$25:$M$45,4),Summary!$M$25:$M$45,0)),"") -> Public Health Sector (Sogha) | C17: =IFERROR(INDEX(Summary!$C$25:$C$45,MATCH($B17,Summary!$A$25:$A$45,0)),0) -> 25 | D17: =IFERROR(INDEX(Summary!$K$25:$K$45,MATCH($B17,Summary!$A$25:$A$45,0)),0) -> 0 | E17: =C17-D17 -> 25 | F17: =IFERROR(INDEX(Summary!$D$25:$D$45,MATCH($B17,Summary!$A$25:$A$45,0)),0) -> 51
B18: =IFERROR(INDEX(Summary!$A$25:$A$45,MATCH(LARGE(Summary!$M$25:$M$45,5),Summary!$M$25:$M$45,0)),"") -> My Book | C18: =IFERROR(INDEX(Summary!$C$25:$C$45,MATCH($B18,Summary!$A$25:$A$45,0)),0) -> 14 | D18: =IFERROR(INDEX(Summary!$K$25:$K$45,MATCH($B18,Summary!$A$25:$A$45,0)),0) -> 0 | E18: =C18-D18 -> 14 | F18: =IFERROR(INDEX(Summary!$D$25:$D$45,MATCH($B18,Summary!$A$25:$A$45,0)),0) -> 25 | H18: Partners with no usage this month
B19: =IFERROR(INDEX(Summary!$A$25:$A$45,MATCH(LARGE(Summary!$M$25:$M$45,6),Summary!$M$25:$M$45,0)),"") -> Entertainer | C19: =IFERROR(INDEX(Summary!$C$25:$C$45,MATCH($B19,Summary!$A$25:$A$45,0)),0) -> 14 | D19: =IFERROR(INDEX(Summary!$K$25:$K$45,MATCH($B19,Summary!$A$25:$A$45,0)),0) -> 0 | E19: =C19-D19 -> 14 | F19: =IFERROR(INDEX(Summary!$D$25:$D$45,MATCH($B19,Summary!$A$25:$A$45,0)),0) -> 19 | H19: Partner | I19: Mechanism | J19: Last used (month)
B20: =IFERROR(INDEX(Summary!$A$25:$A$45,MATCH(LARGE(Summary!$M$25:$M$45,7),Summary!$M$25:$M$45,0)),"") -> Qatar Foundation | C20: =IFERROR(INDEX(Summary!$C$25:$C$45,MATCH($B20,Summary!$A$25:$A$45,0)),0) -> 13 | D20: =IFERROR(INDEX(Summary!$K$25:$K$45,MATCH($B20,Summary!$A$25:$A$45,0)),0) -> 0 | E20: =C20-D20 -> 13 | F20: =IFERROR(INDEX(Summary!$D$25:$D$45,MATCH($B20,Summary!$A$25:$A$45,0)),0) -> 34 | H20: =IFERROR(INDEX(Summary!$A$25:$A$45,SMALL(Summary!$N$25:$N$45,1)),"") -> Dar App | I20: =IF(H20="","",INDEX('Partner Master'!$C$5:$C$25,MATCH(H20,'Partner Master'!$A$5:$A$25,0))) -> Dar community app | J20: =IF(H20="","",IFERROR(INDEX('Trend Data'!$G$5:$G$2085,MATCH(H20,'Trend Data'!$L$5:$L$2085,0)),"Never")) -> 2026-07
B21: =IFERROR(INDEX(Summary!$A$25:$A$45,MATCH(LARGE(Summary!$M$25:$M$45,8),Summary!$M$25:$M$45,0)),"") -> Qatar Investment Authority | C21: =IFERROR(INDEX(Summary!$C$25:$C$45,MATCH($B21,Summary!$A$25:$A$45,0)),0) -> 12 | D21: =IFERROR(INDEX(Summary!$K$25:$K$45,MATCH($B21,Summary!$A$25:$A$45,0)),0) -> 0 | E21: =C21-D21 -> 12 | F21: =IFERROR(INDEX(Summary!$D$25:$D$45,MATCH($B21,Summary!$A$25:$A$45,0)),0) -> 20 | H21: =IFERROR(INDEX(Summary!$A$25:$A$45,SMALL(Summary!$N$25:$N$45,2)),"") -> Classmate | I21: =IF(H21="","",INDEX('Partner Master'!$C$5:$C$25,MATCH(H21,'Partner Master'!$A$5:$A$25,0))) -> App 9171 | J21: =IF(H21="","",IFERROR(INDEX('Trend Data'!$G$5:$G$2085,MATCH(H21,'Trend Data'!$L$5:$L$2085,0)),"Never")) -> 2026-07
B22: =IFERROR(INDEX(Summary!$A$25:$A$45,MATCH(LARGE(Summary!$M$25:$M$45,9),Summary!$M$25:$M$45,0)),"") -> Aspire | C22: =IFERROR(INDEX(Summary!$C$25:$C$45,MATCH($B22,Summary!$A$25:$A$45,0)),0) -> 4 | D22: =IFERROR(INDEX(Summary!$K$25:$K$45,MATCH($B22,Summary!$A$25:$A$45,0)),0) -> 0 | E22: =C22-D22 -> 4 | F22: =IFERROR(INDEX(Summary!$D$25:$D$45,MATCH($B22,Summary!$A$25:$A$45,0)),0) -> 5 | H22: =IFERROR(INDEX(Summary!$A$25:$A$45,SMALL(Summary!$N$25:$N$45,3)),"") -> MyBenefit | I22: =IF(H22="","",INDEX('Partner Master'!$C$5:$C$25,MATCH(H22,'Partner Master'!$A$5:$A$25,0))) -> Codes mbfua15 / mbfip15 / mbfcb15 / mbfkd15 | J22: =IF(H22="","",IFERROR(INDEX('Trend Data'!$G$5:$G$2085,MATCH(H22,'Trend Data'!$L$5:$L$2085,0)),"Never")) -> Never
B23: =IFERROR(INDEX(Summary!$A$25:$A$45,MATCH(LARGE(Summary!$M$25:$M$45,10),Summary!$M$25:$M$45,0)),"") -> Al Jazeera Imtiyazat | C23: =IFERROR(INDEX(Summary!$C$25:$C$45,MATCH($B23,Summary!$A$25:$A$45,0)),0) -> 3 | D23: =IFERROR(INDEX(Summary!$K$25:$K$45,MATCH($B23,Summary!$A$25:$A$45,0)),0) -> 0 | E23: =C23-D23 -> 3 | F23: =IFERROR(INDEX(Summary!$D$25:$D$45,MATCH($B23,Summary!$A$25:$A$45,0)),0) -> 6 | H23: =IFERROR(INDEX(Summary!$A$25:$A$45,SMALL(Summary!$N$25:$N$45,4)),"") -> DHL | I23: =IF(H23="","",INDEX('Partner Master'!$C$5:$C$25,MATCH(H23,'Partner Master'!$A$5:$A$25,0))) -> Staff ID | J23: =IF(H23="","",IFERROR(INDEX('Trend Data'!$G$5:$G$2085,MATCH(H23,'Trend Data'!$L$5:$L$2085,0)),"Never")) -> Never
H24: =IFERROR(INDEX(Summary!$A$25:$A$45,SMALL(Summary!$N$25:$N$45,5)),"") -> Huawei | I24: =IF(H24="","",INDEX('Partner Master'!$C$5:$C$25,MATCH(H24,'Partner Master'!$A$5:$A$25,0))) -> Staff ID | J24: =IF(H24="","",IFERROR(INDEX('Trend Data'!$G$5:$G$2085,MATCH(H24,'Trend Data'!$L$5:$L$2085,0)),"Never")) -> Never
B25: By venue this week | H25: =IFERROR(INDEX(Summary!$A$25:$A$45,SMALL(Summary!$N$25:$N$45,6)),"") -> Qatar Media Corporation | I25: =IF(H25="","",INDEX('Partner Master'!$C$5:$C$25,MATCH(H25,'Partner Master'!$A$5:$A$25,0))) -> Staff ID | J25: =IF(H25="","",IFERROR(INDEX('Trend Data'!$G$5:$G$2085,MATCH(H25,'Trend Data'!$L$5:$L$2085,0)),"Never")) -> 2026-08
B26: Venue | C26: Redemptions | D26: Tickets | E26: Discount QAR | F26: Share | H26: =IFERROR(INDEX(Summary!$A$25:$A$45,SMALL(Summary!$N$25:$N$45,7)),"") -> Snoonu Employees | I26: =IF(H26="","",INDEX('Partner Master'!$C$5:$C$25,MATCH(H26,'Partner Master'!$A$5:$A$25,0))) -> Scity app | J26: =IF(H26="","",IFERROR(INDEX('Trend Data'!$G$5:$G$2085,MATCH(H26,'Trend Data'!$L$5:$L$2085,0)),"Never")) -> 2026-04
B27: Urban Arena | C27: =Summary!I15 -> 67 | D27: =Summary!J15 -> 241 | E27: =Summary!K15 -> 3914.75 | F27: =IF($C$31=0,0,C27/$C$31) -> 0.34536082 | H27: =IFERROR(INDEX(Summary!$A$25:$A$45,SMALL(Summary!$N$25:$N$45,8)),"") | I27: =IF(H27="","",INDEX('Partner Master'!$C$5:$C$25,MATCH(H27,'Partner Master'!$A$5:$A$25,0))) | J27: =IF(H27="","",IFERROR(INDEX('Trend Data'!$G$5:$G$2085,MATCH(H27,'Trend Data'!$L$5:$L$2085,0)),"Never"))
B28: InflataPark | C28: =Summary!I16 -> 58 | D28: =Summary!J16 -> 148 | E28: =Summary!K16 -> 3273.5 | F28: =IF($C$31=0,0,C28/$C$31) -> 0.29896907
B29: Kids City Driving School | C29: =Summary!I17 -> 45 | D29: =Summary!J17 -> 158 | E29: =Summary!K17 -> 3230.75 | F29: =IF($C$31=0,0,C29/$C$31) -> 0.23195876
B30: Crayons & Bricks Vendome | C30: =Summary!I18 -> 24 | D30: =Summary!J18 -> 29 | E30: =Summary!K18 -> 2331.5 | F30: =IF($C$31=0,0,C30/$C$31) -> 0.12371134
B31: Total | C31: =SUM(C27:C30) -> 194 | D31: =SUM(D27:D30) -> 576 | E31: =SUM(E27:E30) -> 12750.5 | F31: 1
B33: Weekly trend (partner redemptions)
B34: Week | C34: Redemptions | D34: Tickets | E34: Discount QAR | F34: Aggregator BOGO
B35: =IF(36<=VALUE(RIGHT($C$4,2)),LEFT($C$4,6)&TEXT(36,"00"),"") -> 2026-W36 | C35: =IF(B35="","",SUMIFS('Weekly Log'!$H$5:$H$636,'Weekly Log'!$G$5:$G$636,B35,'Weekly Log'!$M$5:$M$636,"Corporate discount")+SUMIFS('Weekly Log'!$H$5:$H$636,'Weekly Log'!$G$5:$G$636,B35,'Weekly Log'!$M$5:$M$636,"Aggregator BOGO")) -> 0 | D35: =IF(B35="","",SUMIFS('Weekly Log'!$J$5:$J$636,'Weekly Log'!$G$5:$G$636,B35,'Weekly Log'!$M$5:$M$636,"Corporate discount")+SUMIFS('Weekly Log'!$J$5:$J$636,'Weekly Log'!$G$5:$G$636,B35,'Weekly Log'!$M$5:$M$636,"Aggregator BOGO")) -> 0 | E35: =IF(B35="","",SUMIFS('Weekly Log'!$K$5:$K$636,'Weekly Log'!$G$5:$G$636,B35,'Weekly Log'!$M$5:$M$636,"Corporate discount")+SUMIFS('Weekly Log'!$K$5:$K$636,'Weekly Log'!$G$5:$G$636,B35,'Weekly Log'!$M$5:$M$636,"Aggregator BOGO")) -> 0 | F35: =IF(B35="","",SUMIFS('Weekly Log'!$H$5:$H$636,'Weekly Log'!$G$5:$G$636,B35,'Weekly Log'!$M$5:$M$636,"Aggregator BOGO")) -> 0
B36: =IF(37<=VALUE(RIGHT($C$4,2)),LEFT($C$4,6)&TEXT(37,"00"),"") -> 2026-W37 | C36: =IF(B36="","",SUMIFS('Weekly Log'!$H$5:$H$636,'Weekly Log'!$G$5:$G$636,B36,'Weekly Log'!$M$5:$M$636,"Corporate discount")+SUMIFS('Weekly Log'!$H$5:$H$636,'Weekly Log'!$G$5:$G$636,B36,'Weekly Log'!$M$5:$M$636,"Aggregator BOGO")) -> 194 | D36: =IF(B36="","",SUMIFS('Weekly Log'!$J$5:$J$636,'Weekly Log'!$G$5:$G$636,B36,'Weekly Log'!$M$5:$M$636,"Corporate discount")+SUMIFS('Weekly Log'!$J$5:$J$636,'Weekly Log'!$G$5:$G$636,B36,'Weekly Log'!$M$5:$M$636,"Aggregator BOGO")) -> 576 | E36: =IF(B36="","",SUMIFS('Weekly Log'!$K$5:$K$636,'Weekly Log'!$G$5:$G$636,B36,'Weekly Log'!$M$5:$M$636,"Corporate discount")+SUMIFS('Weekly Log'!$K$5:$K$636,'Weekly Log'!$G$5:$G$636,B36,'Weekly Log'!$M$5:$M$636,"Aggregator BOGO")) -> 12750.5 | F36: =IF(B36="","",SUMIFS('Weekly Log'!$H$5:$H$636,'Weekly Log'!$G$5:$G$636,B36,'Weekly Log'!$M$5:$M$636,"Aggregator BOGO")) -> 55
B37: =IF(38<=VALUE(RIGHT($C$4,2)),LEFT($C$4,6)&TEXT(38,"00"),"") | C37: =IF(B37="","",SUMIFS('Weekly Log'!$H$5:$H$636,'Weekly Log'!$G$5:$G$636,B37,'Weekly Log'!$M$5:$M$636,"Corporate discount")+SUMIFS('Weekly Log'!$H$5:$H$636,'Weekly Log'!$G$5:$G$636,B37,'Weekly Log'!$M$5:$M$636,"Aggregator BOGO")) | D37: =IF(B37="","",SUMIFS('Weekly Log'!$J$5:$J$636,'Weekly Log'!$G$5:$G$636,B37,'Weekly Log'!$M$5:$M$636,"Corporate discount")+SUMIFS('Weekly Log'!$J$5:$J$636,'Weekly Log'!$G$5:$G$636,B37,'Weekly Log'!$M$5:$M$636,"Aggregator BOGO")) | E37: =IF(B37="","",SUMIFS('Weekly Log'!$K$5:$K$636,'Weekly Log'!$G$5:$G$636,B37,'Weekly Log'!$M$5:$M$636,"Corporate discount")+SUMIFS('Weekly Log'!$K$5:$K$636,'Weekly Log'!$G$5:$G$636,B37,'Weekly Log'!$M$5:$M$636,"Aggregator BOGO")) | F37: =IF(B37="","",SUMIFS('Weekly Log'!$H$5:$H$636,'Weekly Log'!$G$5:$G$636,B37,'Weekly Log'!$M$5:$M$636,"Aggregator BOGO"))
B38: =IF(39<=VALUE(RIGHT($C$4,2)),LEFT($C$4,6)&TEXT(39,"00"),"") | C38: =IF(B38="","",SUMIFS('Weekly Log'!$H$5:$H$636,'Weekly Log'!$G$5:$G$636,B38,'Weekly Log'!$M$5:$M$636,"Corporate discount")+SUMIFS('Weekly Log'!$H$5:$H$636,'Weekly Log'!$G$5:$G$636,B38,'Weekly Log'!$M$5:$M$636,"Aggregator BOGO")) | D38: =IF(B38="","",SUMIFS('Weekly Log'!$J$5:$J$636,'Weekly Log'!$G$5:$G$636,B38,'Weekly Log'!$M$5:$M$636,"Corporate discount")+SUMIFS('Weekly Log'!$J$5:$J$636,'Weekly Log'!$G$5:$G$636,B38,'Weekly Log'!$M$5:$M$636,"Aggregator BOGO")) | E38: =IF(B38="","",SUMIFS('Weekly Log'!$K$5:$K$636,'Weekly Log'!$G$5:$G$636,B38,'Weekly Log'!$M$5:$M$636,"Corporate discount")+SUMIFS('Weekly Log'!$K$5:$K$636,'Weekly Log'!$G$5:$G$636,B38,'Weekly Log'!$M$5:$M$636,"Aggregator BOGO")) | F38: =IF(B38="","",SUMIFS('Weekly Log'!$H$5:$H$636,'Weekly Log'!$G$5:$G$636,B38,'Weekly Log'!$M$5:$M$636,"Aggregator BOGO"))
B39: =IF(40<=VALUE(RIGHT($C$4,2)),LEFT($C$4,6)&TEXT(40,"00"),"") | C39: =IF(B39="","",SUMIFS('Weekly Log'!$H$5:$H$636,'Weekly Log'!$G$5:$G$636,B39,'Weekly Log'!$M$5:$M$636,"Corporate discount")+SUMIFS('Weekly Log'!$H$5:$H$636,'Weekly Log'!$G$5:$G$636,B39,'Weekly Log'!$M$5:$M$636,"Aggregator BOGO")) | D39: =IF(B39="","",SUMIFS('Weekly Log'!$J$5:$J$636,'Weekly Log'!$G$5:$G$636,B39,'Weekly Log'!$M$5:$M$636,"Corporate discount")+SUMIFS('Weekly Log'!$J$5:$J$636,'Weekly Log'!$G$5:$G$636,B39,'Weekly Log'!$M$5:$M$636,"Aggregator BOGO")) | E39: =IF(B39="","",SUMIFS('Weekly Log'!$K$5:$K$636,'Weekly Log'!$G$5:$G$636,B39,'Weekly Log'!$M$5:$M$636,"Corporate discount")+SUMIFS('Weekly Log'!$K$5:$K$636,'Weekly Log'!$G$5:$G$636,B39,'Weekly Log'!$M$5:$M$636,"Aggregator BOGO")) | F39: =IF(B39="","",SUMIFS('Weekly Log'!$H$5:$H$636,'Weekly Log'!$G$5:$G$636,B39,'Weekly Log'!$M$5:$M$636,"Aggregator BOGO"))
B40: =IF(41<=VALUE(RIGHT($C$4,2)),LEFT($C$4,6)&TEXT(41,"00"),"") | C40: =IF(B40="","",SUMIFS('Weekly Log'!$H$5:$H$636,'Weekly Log'!$G$5:$G$636,B40,'Weekly Log'!$M$5:$M$636,"Corporate discount")+SUMIFS('Weekly Log'!$H$5:$H$636,'Weekly Log'!$G$5:$G$636,B40,'Weekly Log'!$M$5:$M$636,"Aggregator BOGO")) | D40: =IF(B40="","",SUMIFS('Weekly Log'!$J$5:$J$636,'Weekly Log'!$G$5:$G$636,B40,'Weekly Log'!$M$5:$M$636,"Corporate discount")+SUMIFS('Weekly Log'!$J$5:$J$636,'Weekly Log'!$G$5:$G$636,B40,'Weekly Log'!$M$5:$M$636,"Aggregator BOGO")) | E40: =IF(B40="","",SUMIFS('Weekly Log'!$K$5:$K$636,'Weekly Log'!$G$5:$G$636,B40,'Weekly Log'!$M$5:$M$636,"Corporate discount")+SUMIFS('Weekly Log'!$K$5:$K$636,'Weekly Log'!$G$5:$G$636,B40,'Weekly Log'!$M$5:$M$636,"Aggregator BOGO")) | F40: =IF(B40="","",SUMIFS('Weekly Log'!$H$5:$H$636,'Weekly Log'!$G$5:$G$636,B40,'Weekly Log'!$M$5:$M$636,"Aggregator BOGO"))
B41: =IF(42<=VALUE(RIGHT($C$4,2)),LEFT($C$4,6)&TEXT(42,"00"),"") | C41: =IF(B41="","",SUMIFS('Weekly Log'!$H$5:$H$636,'Weekly Log'!$G$5:$G$636,B41,'Weekly Log'!$M$5:$M$636,"Corporate discount")+SUMIFS('Weekly Log'!$H$5:$H$636,'Weekly Log'!$G$5:$G$636,B41,'Weekly Log'!$M$5:$M$636,"Aggregator BOGO")) | D41: =IF(B41="","",SUMIFS('Weekly Log'!$J$5:$J$636,'Weekly Log'!$G$5:$G$636,B41,'Weekly Log'!$M$5:$M$636,"Corporate discount")+SUMIFS('Weekly Log'!$J$5:$J$636,'Weekly Log'!$G$5:$G$636,B41,'Weekly Log'!$M$5:$M$636,"Aggregator BOGO")) | E41: =IF(B41="","",SUMIFS('Weekly Log'!$K$5:$K$636,'Weekly Log'!$G$5:$G$636,B41,'Weekly Log'!$M$5:$M$636,"Corporate discount")+SUMIFS('Weekly Log'!$K$5:$K$636,'Weekly Log'!$G$5:$G$636,B41,'Weekly Log'!$M$5:$M$636,"Aggregator BOGO")) | F41: =IF(B41="","",SUMIFS('Weekly Log'!$H$5:$H$636,'Weekly Log'!$G$5:$G$636,B41,'Weekly Log'!$M$5:$M$636,"Aggregator BOGO"))
B42: =IF(43<=VALUE(RIGHT($C$4,2)),LEFT($C$4,6)&TEXT(43,"00"),"") | C42: =IF(B42="","",SUMIFS('Weekly Log'!$H$5:$H$636,'Weekly Log'!$G$5:$G$636,B42,'Weekly Log'!$M$5:$M$636,"Corporate discount")+SUMIFS('Weekly Log'!$H$5:$H$636,'Weekly Log'!$G$5:$G$636,B42,'Weekly Log'!$M$5:$M$636,"Aggregator BOGO")) | D42: =IF(B42="","",SUMIFS('Weekly Log'!$J$5:$J$636,'Weekly Log'!$G$5:$G$636,B42,'Weekly Log'!$M$5:$M$636,"Corporate discount")+SUMIFS('Weekly Log'!$J$5:$J$636,'Weekly Log'!$G$5:$G$636,B42,'Weekly Log'!$M$5:$M$636,"Aggregator BOGO")) | E42: =IF(B42="","",SUMIFS('Weekly Log'!$K$5:$K$636,'Weekly Log'!$G$5:$G$636,B42,'Weekly Log'!$M$5:$M$636,"Corporate discount")+SUMIFS('Weekly Log'!$K$5:$K$636,'Weekly Log'!$G$5:$G$636,B42,'Weekly Log'!$M$5:$M$636,"Aggregator BOGO")) | F42: =IF(B42="","",SUMIFS('Weekly Log'!$H$5:$H$636,'Weekly Log'!$G$5:$G$636,B42,'Weekly Log'!$M$5:$M$636,"Aggregator BOGO"))
B43: =IF(44<=VALUE(RIGHT($C$4,2)),LEFT($C$4,6)&TEXT(44,"00"),"") | C43: =IF(B43="","",SUMIFS('Weekly Log'!$H$5:$H$636,'Weekly Log'!$G$5:$G$636,B43,'Weekly Log'!$M$5:$M$636,"Corporate discount")+SUMIFS('Weekly Log'!$H$5:$H$636,'Weekly Log'!$G$5:$G$636,B43,'Weekly Log'!$M$5:$M$636,"Aggregator BOGO")) | D43: =IF(B43="","",SUMIFS('Weekly Log'!$J$5:$J$636,'Weekly Log'!$G$5:$G$636,B43,'Weekly Log'!$M$5:$M$636,"Corporate discount")+SUMIFS('Weekly Log'!$J$5:$J$636,'Weekly Log'!$G$5:$G$636,B43,'Weekly Log'!$M$5:$M$636,"Aggregator BOGO")) | E43: =IF(B43="","",SUMIFS('Weekly Log'!$K$5:$K$636,'Weekly Log'!$G$5:$G$636,B43,'Weekly Log'!$M$5:$M$636,"Corporate discount")+SUMIFS('Weekly Log'!$K$5:$K$636,'Weekly Log'!$G$5:$G$636,B43,'Weekly Log'!$M$5:$M$636,"Aggregator BOGO")) | F43: =IF(B43="","",SUMIFS('Weekly Log'!$H$5:$H$636,'Weekly Log'!$G$5:$G$636,B43,'Weekly Log'!$M$5:$M$636,"Aggregator BOGO"))
B44: =IF(45<=VALUE(RIGHT($C$4,2)),LEFT($C$4,6)&TEXT(45,"00"),"") | C44: =IF(B44="","",SUMIFS('Weekly Log'!$H$5:$H$636,'Weekly Log'!$G$5:$G$636,B44,'Weekly Log'!$M$5:$M$636,"Corporate discount")+SUMIFS('Weekly Log'!$H$5:$H$636,'Weekly Log'!$G$5:$G$636,B44,'Weekly Log'!$M$5:$M$636,"Aggregator BOGO")) | D44: =IF(B44="","",SUMIFS('Weekly Log'!$J$5:$J$636,'Weekly Log'!$G$5:$G$636,B44,'Weekly Log'!$M$5:$M$636,"Corporate discount")+SUMIFS('Weekly Log'!$J$5:$J$636,'Weekly Log'!$G$5:$G$636,B44,'Weekly Log'!$M$5:$M$636,"Aggregator BOGO")) | E44: =IF(B44="","",SUMIFS('Weekly Log'!$K$5:$K$636,'Weekly Log'!$G$5:$G$636,B44,'Weekly Log'!$M$5:$M$636,"Corporate discount")+SUMIFS('Weekly Log'!$K$5:$K$636,'Weekly Log'!$G$5:$G$636,B44,'Weekly Log'!$M$5:$M$636,"Aggregator BOGO")) | F44: =IF(B44="","",SUMIFS('Weekly Log'!$H$5:$H$636,'Weekly Log'!$G$5:$G$636,B44,'Weekly Log'!$M$5:$M$636,"Aggregator BOGO"))
B45: Weeks with no export pasted show as blank; weeks before W36 are not listed.
B46: Loyalty and in-house codes by venue
B47: Code | C47: Venue | D47: Week: uses | E47: Week: tickets | F47: Month: uses
B48: =Summary!A68 -> loyaltyinf | C48: =Summary!B68 -> InflataPark | D48: =Summary!D68 -> 1 | E48: =Summary!E68 -> 1 | F48: =Summary!F68 -> 1
B49: =Summary!A69 -> loyaltykds | C49: =Summary!B69 -> Kids City Driving School | D49: =Summary!D69 -> 7 | E49: =Summary!E69 -> 7 | F49: =Summary!F69 -> 13
B50: =Summary!A70 -> cafe50 | C50: =Summary!B70 -> Urban Arena | D50: =Summary!D70 -> 31 | E50: =Summary!E70 -> 36 | F50: =Summary!F70 -> 63
B51: =Summary!A71 -> karak100 | C51: =Summary!B71 -> Urban Arena | D51: =Summary!D71 -> 1 | E51: =Summary!E71 -> 3 | F51: =Summary!F71 -> 1
B52: =Summary!A72 -> loyalty | C52: =Summary!B72 -> Urban Arena | D52: =Summary!D72 -> 0 | E52: =Summary!E72 -> 0 | F52: =Summary!F72 -> 1
B53: Total | D53: =SUM(D48:D52) -> 40 | E53: =SUM(E48:E52) -> 47 | F53: =SUM(F48:F52) -> 79
B55: Loyalty, cafe and karak codes are our own promotions and are never counted in the partner figures above.

Sheet Read Me
B2: How to update this report every week (10 minutes)
B4: 1. In BookingQube, export the event-wise promo-code report for the ISO week just ended (Monday to Sunday). It must include event_id and event_title, which give the venue. Save as CSV.
B5: 2. Open the Weekly Log tab. Paste the export rows (columns A to K, event-wise export including event_id and event_title) directly below the last filled row. Do not touch columns L to N; they fill themselves.
B6: 3. Once a week also refresh the Month Data tab (current calendar month export, replace from row 5) and, on the first Tuesday of each month, the Trend Data tab (all-months export).
B7: 4. On the Dashboard, type the week you are reporting in C4 (format 2026-W38) and the meeting date in I4.
B8: 5. Check the Dashboard. If a partner shows as Unmapped or Not on master, open Code Mapping and set its Partner, Category and Venue in the yellow cells. New codes appear automatically at the bottom of the list only if you add them there; add one row per new code.
B9: 6. Open MoM Follow-up and update the Status and Update columns for each open point.
B10: 7. Present the Dashboard tab on screen (it is set to print on one landscape page). The Summary tab has the full partner table if management asks for detail.
B12: Definitions
B13: Partner redemptions: number of bookings where a corporate or aggregator promo code was applied. Tickets: entries issued under those bookings. Discount: value given, QAR.
B14: Corporate discount: staff-ID and card partners (15% to 20% on the bill). Aggregator BOGO: Urban Point, My Book, Entertainer, Qatar Living, Classmate free-pass offers.
B15: Internal / promotion codes (loyalty, cafe, Inflatarun, driving licence, media pass) are excluded from all partner totals.
... B19: Yellow cells are inputs. Everything else is a formula; do not overwrite.

Sheet Summary
A1: Corporate Deals and Aggregator Redemptions: Weekly Management Review
A2: All figures are formulas over the data sheets. Partner totals count Corporate discount, Aggregator BOGO and Not on master codes; Internal/promotion codes (loyalty, cafe, Inflatarun, driving licence) and Unmapped codes are excluded and shown separately.
A4: Reporting week | B4: =Dashboard!C4 -> 2026-W37
A5: Current month | B5: 2026-09
A6: Prepared by | B6: Rajan Pathak, Head of Operations (FEC & IT)
A8: Key figures | B8: Redemptions | C8: Tickets | D8: Discount QAR | E8: Active partners
A9: Reporting week (Dashboard!C4) | B9: =(SUMIFS('Weekly Log'!$H$5:$H$636,'Weekly Log'!$G$5:$G$636,Dashboard!$C$4,'Weekly Log'!$M$5:$M$636,"Corporate discount")+SUMIFS('Weekly Log'!$H$5:$H$636,'Weekly Log'!$G$5:$G$636,Dashboard!$C$4,'Weekly Log'!$M$5:$M$636,"Aggregator BOGO")+SUMIFS('Weekly Log'!$H$5:$H$636,'Weekly Log'!$G$5:$G$636,Dashboard!$C$4,'Weekly Log'!$M$5:$M$636,"Not on master")) -> 194 | C9: =(SUMIFS('Weekly Log'!$J$5:$J$636,'Weekly Log'!$G$5:$G$636,Dashboard!$C$4,'Weekly Log'!$M$5:$M$636,"Corporate discount")+SUMIFS('Weekly Log'!$J$5:$J$636,'Weekly Log'!$G$5:$G$636,Dashboard!$C$4,'Weekly Log'!$M$5:$M$636,"Aggregator BOGO")+SUMIFS('Weekly Log'!$J$5:$J$636,'Weekly Log'!$G$5:$G$636,Dashboard!$C$4,'Weekly Log'!$M$5:$M$636,"Not on master")) -> 576 | D9: =(SUMIFS('Weekly Log'!$K$5:$K$636,'Weekly Log'!$G$5:$G$636,Dashboard!$C$4,'Weekly Log'!$M$5:$M$636,"Corporate discount")+SUMIFS('Weekly Log'!$K$5:$K$636,'Weekly Log'!$G$5:$G$636,Dashboard!$C$4,'Weekly Log'!$M$5:$M$636,"Aggregator BOGO")+SUMIFS('Weekly Log'!$K$5:$K$636,'Weekly Log'!$G$5:$G$636,Dashboard!$C$4,'Weekly Log'!$M$5:$M$636,"Not on master")) -> 12750.5 | E9: =SUMPRODUCT((C25:C45>0)*1) -> 12
A10: This month to date | B10: =(SUMIFS('Month Data'!$H$5:$H$42,'Month Data'!$M$5:$M$42,"Corporate discount")+SUMIFS('Month Data'!$H$5:$H$42,'Month Data'!$M$5:$M$42,"Aggregator BOGO")+SUMIFS('Month Data'!$H$5:$H$42,'Month Data'!$M$5:$M$42,"Not on master")) -> 351 | C10: =(SUMIFS('Month Data'!$J$5:$J$42,'Month Data'!$M$5:$M$42,"Corporate discount")+SUMIFS('Month Data'!$J$5:$J$42,'Month Data'!$M$5:$M$42,"Aggregator BOGO")+SUMIFS('Month Data'!$J$5:$J$42,'Month Data'!$M$5:$M$42,"Not on master")) -> 1042 | D10: =(SUMIFS('Month Data'!$K$5:$K$42,'Month Data'!$M$5:$M$42,"Corporate discount")+SUMIFS('Month Data'!$K$5:$K$42,'Month Data'!$M$5:$M$42,"Aggregator BOGO")+SUMIFS('Month Data'!$K$5:$K$42,'Month Data'!$M$5:$M$42,"Not on master")) -> 21132.95 | E10: =SUMPRODUCT((D25:D45>0)*1) -> 14
A11: Previous full month | B11: =(SUMIFS('Trend Data'!$H$5:$H$2085,'Trend Data'!$G$5:$G$2085,$B$21,'Trend Data'!$M$5:$M$2085,"Corporate discount")+SUMIFS('Trend Data'!$H$5:$H$2085,'Trend Data'!$G$5:$G$2085,$B$21,'Trend Data'!$M$5:$M$2085,"Aggregator BOGO")+SUMIFS('Trend Data'!$H$5:$H$2085,'Trend Data'!$G$5:$G$2085,$B$21,'Trend Data'!$M$5:$M$2085,"Not on master")) -> 873 | C11: =(SUMIFS('Trend Data'!$J$5:$J$2085,'Trend Data'!$G$5:$G$2085,$B$21,'Trend Data'!$M$5:$M$2085,"Corporate discount")+SUMIFS('Trend Data'!$J$5:$J$2085,'Trend Data'!$G$5:$G$2085,$B$21,'Trend Data'!$M$5:$M$2085,"Aggregator BOGO")+SUMIFS('Trend Data'!$J$5:$J$2085,'Trend Data'!$G$5:$G$2085,$B$21,'Trend Data'!$M$5:$M$2085,"Not on master")) -> 2645 | D11: =(SUMIFS('Trend Data'!$K$5:$K$2085,'Trend Data'!$G$5:$G$2085,$B$21,'Trend Data'!$M$5:$M$2085,"Corporate discount")+SUMIFS('Trend Data'!$K$5:$K$2085,'Trend Data'!$G$5:$G$2085,$B$21,'Trend Data'!$M$5:$M$2085,"Aggregator BOGO")+SUMIFS('Trend Data'!$K$5:$K$2085,'Trend Data'!$G$5:$G$2085,$B$21,'Trend Data'!$M$5:$M$2085,"Not on master")) -> 55769.7 | E11: =SUMPRODUCT((H25:H45>0)*1) -> 14
A13: Category split, month to date | H13: Venue split (event title from the export)
A14: Category | B14: Redemptions | C14: Tickets | D14: Discount QAR | E14: Share of redemptions | F14: Share of discount | G14: Discount per redemption | H14: Venue | I14: Week: redemptions | J14: Week: tickets | K14: Week: discount QAR | L14: Month: redemptions | M14: Month: discount QAR
A15: Corporate discount | B15: =SUMIFS('Month Data'!$H$5:$H$42,'Month Data'!$M$5:$M$42,$A15) -> 266 | C15: =SUMIFS('Month Data'!$J$5:$J$42,'Month Data'!$M$5:$M$42,$A15) -> 957 | D15: =SUMIFS('Month Data'!$K$5:$K$42,'Month Data'!$M$5:$M$42,$A15) -> 7583.95 | E15: =IF($B$10=0,0,B15/$B$10) -> 0.75783476 | F15: =IF($D$10=0,0,D15/$D$10) -> 0.3588685 | G15: =IF(B15=0,0,D15/B15) -> 28.51109 | H15: Urban Arena | I15: =(SUMIFS('Weekly Log'!$H$5:$H$636,'Weekly Log'!$G$5:$G$636,Dashboard!$C$4,'Weekly Log'!$N$5:$N$636,$H15,'Weekly Log'!$M$5:$M$636,"Corporate discount")+SUMIFS('Weekly Log'!$H$5:$H$636,'Weekly Log'!$G$5:$G$636,Dashboard!$C$4,'Weekly Log'!$N$5:$N$636,$H15,'Weekly Log'!$M$5:$M$636,"Aggregator BOGO")) -> 67 | J15: =(SUMIFS('Weekly Log'!$J$5:$J$636,'Weekly Log'!$G$5:$G$636,Dashboard!$C$4,'Weekly Log'!$N$5:$N$636,$H15,'Weekly Log'!$M$5:$M$636,"Corporate discount")+SUMIFS('Weekly Log'!$J$5:$J$636,'Weekly Log'!$G$5:$G$636,Dashboard!$C$4,'Weekly Log'!$N$5:$N$636,$H15,'Weekly Log'!$M$5:$M$636,"Aggregator BOGO")) -> 241 | K15: =(SUMIFS('Weekly Log'!$K$5:$K$636,'Weekly Log'!$G$5:$G$636,Dashboard!$C$4,'Weekly Log'!$N$5:$N$636,$H15,'Weekly Log'!$M$5:$M$636,"Corporate discount")+SUMIFS('Weekly Log'!$K$5:$K$636,'Weekly Log'!$G$5:$G$636,Dashboard!$C$4,'Weekly Log'!$N$5:$N$636,$H15,'Weekly Log'!$M$5:$M$636,"Aggregator BOGO")) -> 3914.75 | L15: =(SUMIFS('Month Data'!$H$5:$H$42,'Month Data'!$N$5:$N$42,$H15,'Month Data'!$M$5:$M$42,"Corporate discount")+SUMIFS('Month Data'!$H$5:$H$42,'Month Data'!$N$5:$N$42,$H15,'Month Data'!$M$5:$M$42,"Aggregator BOGO")) -> 134 | M15: =(SUMIFS('Month Data'!$K$5:$K$42,'Month Data'!$N$5:$N$42,$H15,'Month Data'!$M$5:$M$42,"Corporate discount")+SUMIFS('Month Data'!$K$5:$K$42,'Month Data'!$N$5:$N$42,$H15,'Month Data'!$M$5:$M$42,"Aggregator BOGO")) -> 7547.95
A16: Aggregator BOGO | B16: =SUMIFS('Month Data'!$H$5:$H$42,'Month Data'!$M$5:$M$42,$A16) -> 85 | C16: =SUMIFS('Month Data'!$J$5:$J$42,'Month Data'!$M$5:$M$42,$A16) -> 85 | D16: =SUMIFS('Month Data'!$K$5:$K$42,'Month Data'!$M$5:$M$42,$A16) -> 13549 | E16: =IF($B$10=0,0,B16/$B$10) -> 0.24216524 | F16: =IF($D$10=0,0,D16/$D$10) -> 0.6411315 | G16: =IF(B16=0,0,D16/B16) -> 159.4 | H16: InflataPark | I16: =(SUMIFS('Weekly Log'!$H$5:$H$636,'Weekly Log'!$G$5:$G$636,Dashboard!$C$4,'Weekly Log'!$N$5:$N$636,$H16,'Weekly Log'!$M$5:$M$636,"Corporate discount")+SUMIFS('Weekly Log'!$H$5:$H$636,'Weekly Log'!$G$5:$G$636,Dashboard!$C$4,'Weekly Log'!$N$5:$N$636,$H16,'Weekly Log'!$M$5:$M$636,"Aggregator BOGO")) -> 58 | J16: =(SUMIFS('Weekly Log'!$J$5:$J$636,'Weekly Log'!$G$5:$G$636,Dashboard!$C$4,'Weekly Log'!$N$5:$N$636,$H16,'Weekly Log'!$M$5:$M$636,"Corporate discount")+SUMIFS('Weekly Log'!$J$5:$J$636,'Weekly Log'!$G$5:$G$636,Dashboard!$C$4,'Weekly Log'!$N$5:$N$636,$H16,'Weekly Log'!$M$5:$M$636,"Aggregator BOGO")) -> 148 | K16: =(SUMIFS('Weekly Log'!$K$5:$K$636,'Weekly Log'!$G$5:$G$636,Dashboard!$C$4,'Weekly Log'!$N$5:$N$636,$H16,'Weekly Log'!$M$5:$M$636,"Corporate discount")+SUMIFS('Weekly Log'!$K$5:$K$636,'Weekly Log'!$G$5:$G$636,Dashboard!$C$4,'Weekly Log'!$N$5:$N$636,$H16,'Weekly Log'!$M$5:$M$636,"Aggregator BOGO")) -> 3273.5 | L16: =(SUMIFS('Month Data'!$H$5:$H$42,'Month Data'!$N$5:$N$42,$H16,'Month Data'!$M$5:$M$42,"Corporate discount")+SUMIFS('Month Data'!$H$5:$H$42,'Month Data'!$N$5:$N$42,$H16,'Month Data'!$M$5:$M$42,"Aggregator BOGO")) -> 112 | M16: =(SUMIFS('Month Data'!$K$5:$K$42,'Month Data'!$N$5:$N$42,$H16,'Month Data'!$M$5:$M$42,"Corporate discount")+SUMIFS('Month Data'!$K$5:$K$42,'Month Data'!$N$5:$N$42,$H16,'Month Data'!$M$5:$M$42,"Aggregator BOGO")) -> 5879.75
A17: Not on master | B17: =SUMIFS('Month Data'!$H$5:$H$42,'Month Data'!$M$5:$M$42,$A17) -> 0 | C17: =SUMIFS('Month Data'!$J$5:$J$42,'Month Data'!$M$5:$M$42,$A17) -> 0 | D17: =SUMIFS('Month Data'!$K$5:$K$42,'Month Data'!$M$5:$M$42,$A17) -> 0 | E17: =IF($B$10=0,0,B17/$B$10) -> 0 | F17: =IF($D$10=0,0,D17/$D$10) -> 0 | G17: =IF(B17=0,0,D17/B17) -> 0 | H17: Kids City Driving School | I17: =(SUMIFS('Weekly Log'!$H$5:$H$636,'Weekly Log'!$G$5:$G$636,Dashboard!$C$4,'Weekly Log'!$N$5:$N$636,$H17,'Weekly Log'!$M$5:$M$636,"Corporate discount")+SUMIFS('Weekly Log'!$H$5:$H$636,'Weekly Log'!$G$5:$G$636,Dashboard!$C$4,'Weekly Log'!$N$5:$N$636,$H17,'Weekly Log'!$M$5:$M$636,"Aggregator BOGO")) -> 45 | J17: =(SUMIFS('Weekly Log'!$J$5:$J$636,'Weekly Log'!$G$5:$G$636,Dashboard!$C$4,'Weekly Log'!$N$5:$N$636,$H17,'Weekly Log'!$M$5:$M$636,"Corporate discount")+SUMIFS('Weekly Log'!$J$5:$J$636,'Weekly Log'!$G$5:$G$636,Dashboard!$C$4,'Weekly Log'!$N$5:$N$636,$H17,'Weekly Log'!$M$5:$M$636,"Aggregator BOGO")) -> 158 | K17: =(SUMIFS('Weekly Log'!$K$5:$K$636,'Weekly Log'!$G$5:$G$636,Dashboard!$C$4,'Weekly Log'!$N$5:$N$636,$H17,'Weekly Log'!$M$5:$M$636,"Corporate discount")+SUMIFS('Weekly Log'!$K$5:$K$636,'Weekly Log'!$G$5:$G$636,Dashboard!$C$4,'Weekly Log'!$N$5:$N$636,$H17,'Weekly Log'!$M$5:$M$636,"Aggregator BOGO")) -> 3230.75 | L17: =(SUMIFS('Month Data'!$H$5:$H$42,'Month Data'!$N$5:$N$42,$H17,'Month Data'!$M$5:$M$42,"Corporate discount")+SUMIFS('Month Data'!$H$5:$H$42,'Month Data'!$N$5:$N$42,$H17,'Month Data'!$M$5:$M$42,"Aggregator BOGO")) -> 68 | M17: =(SUMIFS('Month Data'!$K$5:$K$42,'Month Data'!$N$5:$N$42,$H17,'Month Data'!$M$5:$M$42,"Corporate discount")+SUMIFS('Month Data'!$K$5:$K$42,'Month Data'!$N$5:$N$42,$H17,'Month Data'!$M$5:$M$42,"Aggregator BOGO")) -> 4247.5
A18: Unmapped | B18: =SUMIFS('Month Data'!$H$5:$H$42,'Month Data'!$M$5:$M$42,$A18) -> 0 | C18: =SUMIFS('Month Data'!$J$5:$J$42,'Month Data'!$M$5:$M$42,$A18) -> 0 | D18: =SUMIFS('Month Data'!$K$5:$K$42,'Month Data'!$M$5:$M$42,$A18) -> 0 | E18: =IF($B$10=0,0,B18/$B$10) -> 0 | F18: =IF($D$10=0,0,D18/$D$10) -> 0 | G18: =IF(B18=0,0,D18/B18) -> 0 | H18: Crayons & Bricks Vendome | I18: =(SUMIFS('Weekly Log'!$H$5:$H$636,'Weekly Log'!$G$5:$G$636,Dashboard!$C$4,'Weekly Log'!$N$5:$N$636,$H18,'Weekly Log'!$M$5:$M$636,"Corporate discount")+SUMIFS('Weekly Log'!$H$5:$H$636,'Weekly Log'!$G$5:$G$636,Dashboard!$C$4,'Weekly Log'!$N$5:$N$636,$H18,'Weekly Log'!$M$5:$M$636,"Aggregator BOGO")) -> 24 | J18: =(SUMIFS('Weekly Log'!$J$5:$J$636,'Weekly Log'!$G$5:$G$636,Dashboard!$C$4,'Weekly Log'!$N$5:$N$636,$H18,'Weekly Log'!$M$5:$M$636,"Corporate discount")+SUMIFS('Weekly Log'!$J$5:$J$636,'Weekly Log'!$G$5:$G$636,Dashboard!$C$4,'Weekly Log'!$N$5:$N$636,$H18,'Weekly Log'!$M$5:$M$636,"Aggregator BOGO")) -> 29 | K18: =(SUMIFS('Weekly Log'!$K$5:$K$636,'Weekly Log'!$G$5:$G$636,Dashboard!$C$4,'Weekly Log'!$N$5:$N$636,$H18,'Weekly Log'!$M$5:$M$636,"Corporate discount")+SUMIFS('Weekly Log'!$K$5:$K$636,'Weekly Log'!$G$5:$G$636,Dashboard!$C$4,'Weekly Log'!$N$5:$N$636,$H18,'Weekly Log'!$M$5:$M$636,"Aggregator BOGO")) -> 2331.5 | L18: =(SUMIFS('Month Data'!$H$5:$H$42,'Month Data'!$N$5:$N$42,$H18,'Month Data'!$M$5:$M$42,"Corporate discount")+SUMIFS('Month Data'!$H$5:$H$42,'Month Data'!$N$5:$N$42,$H18,'Month Data'!$M$5:$M$42,"Aggregator BOGO")) -> 37 | M18: =(SUMIFS('Month Data'!$K$5:$K$42,'Month Data'!$N$5:$N$42,$H18,'Month Data'!$M$5:$M$42,"Corporate discount")+SUMIFS('Month Data'!$K$5:$K$42,'Month Data'!$N$5:$N$42,$H18,'Month Data'!$M$5:$M$42,"Aggregator BOGO")) -> 3457.75
H19: Total | I19: =SUM(I15:I18) -> 194 | J19: =SUM(J15:J18) -> 576 | K19: =SUM(K15:K18) -> 12750.5 | L19: =SUM(L15:L18) -> 351 | M19: =SUM(M15:M18) -> 21132.95
A20: Previous full month for comparison
A21: Previous month | B21: 2026-08
A23: Partner performance
A24: Partner | B24: Category | C24: This week: redemptions | D24: Month: redemptions | E24: Month: tickets | F24: Month: discount QAR | G24: Month: discount per redemption | H24: Previous month: redemptions | I24: Change vs previous month | J24: Status this month | K24: Previous week: redemptions | L24: Change vs previous week | M24: Rank helper | N24: No-usage helper
A25: ='Partner Master'!A5 -> Al Jazeera Imtiyazat | B25: ='Partner Master'!B5 -> Corporate discount | C25: =SUMIFS('Weekly Log'!$H$5:$H$636,'Weekly Log'!$G$5:$G$636,Dashboard!$C$4,'Weekly Log'!$L$5:$L$636,$A25) -> 3 | D25: =SUMIFS('Month Data'!$H$5:$H$42,'Month Data'!$L$5:$L$42,$A25) -> 6 | E25: =SUMIFS('Month Data'!$J$5:$J$42,'Month Data'!$L$5:$L$42,$A25) -> 11 | F25: =SUMIFS('Month Data'!$K$5:$K$42,'Month Data'!$L$5:$L$42,$A25) -> 219.75 | G25: =IF(D25=0,0,F25/D25) -> 36.625 | H25: =SUMIFS('Trend Data'!$H$5:$H$2085,'Trend Data'!$L$5:$L$2085,$A25,'Trend Data'!$G$5:$G$2085,$B$21) -> 16 | I25: =D25-H25 -> -10 | J25: =IF(D25=0,"No usage","Active") -> Active | K25: =SUMIFS('Weekly Log'!$H$5:$H$636,'Weekly Log'!$G$5:$G$636,Dashboard!$C$5,'Weekly Log'!$L$5:$L$636,$A25) -> 0 | L25: =C25-K25 -> 3 | M25: =C25+(45-ROW())/1000 -> 3.02 | N25: =IF(D25=0,ROW()-24,"")
A26: ='Partner Master'!A6 -> My Book | B26: ='Partner Master'!B6 -> Aggregator BOGO | C26: =SUMIFS('Weekly Log'!$H$5:$H$636,'Weekly Log'!$G$5:$G$636,Dashboard!$C$4,'Weekly Log'!$L$5:$L$636,$A26) -> 14 | D26: =SUMIFS('Month Data'!$H$5:$H$42,'Month Data'!$L$5:$L$42,$A26) -> 25 | E26: =SUMIFS('Month Data'!$J$5:$J$42,'Month Data'!$L$5:$L$42,$A26) -> 25 | F26: =SUMIFS('Month Data'!$K$5:$K$42,'Month Data'!$L$5:$L$42,$A26) -> 4579 | G26: =IF(D26=0,0,F26/D26) -> 183.16 | H26: =SUMIFS('Trend Data'!$H$5:$H$2085,'Trend Data'!$L$5:$L$2085,$A26,'Trend Data'!$G$5:$G$2085,$B$21) -> 116 | I26: =D26-H26 -> -91 | J26: =IF(D26=0,"No usage","Active") -> Active | K26: =SUMIFS('Weekly Log'!$H$5:$H$636,'Weekly Log'!$G$5:$G$636,Dashboard!$C$5,'Weekly Log'!$L$5:$L$636,$A26) -> 0 | L26: =C26-K26 -> 14 | M26: =C26+(45-ROW())/1000 -> 14.019 | N26: =IF(D26=0,ROW()-24,"")
A27: ='Partner Master'!A7 -> QIB | B27: ='Partner Master'!B7 -> Corporate discount | C27: =SUMIFS('Weekly Log'!$H$5:$H$636,'Weekly Log'!$G$5:$G$636,Dashboard!$C$4,'Weekly Log'!$L$5:$L$636,$A27) -> 2 | D27: =SUMIFS('Month Data'!$H$5:$H$42,'Month Data'!$L$5:$L$42,$A27) -> 5 | E27: =SUMIFS('Month Data'!$J$5:$J$42,'Month Data'!$L$5:$L$42,$A27) -> 21 | F27: =SUMIFS('Month Data'!$K$5:$K$42,'Month Data'!$L$5:$L$42,$A27) -> 174 | G27: =IF(D27=0,0,F27/D27) -> 34.8 | H27: =SUMIFS('Trend Data'!$H$5:$H$2085,'Trend Data'!$L$5:$L$2085,$A27,'Trend Data'!$G$5:$G$2085,$B$21) -> 5 | I27: =D27-H27 -> 0 | J27: =IF(D27=0,"No usage","Active") -> Active | K27: =SUMIFS('Weekly Log'!$H$5:$H$636,'Weekly Log'!$G$5:$G$636,Dashboard!$C$5,'Weekly Log'!$L$5:$L$636,$A27) -> 0 | L27: =C27-K27 -> 2 | M27: =C27+(45-ROW())/1000 -> 2.018 | N27: =IF(D27=0,ROW()-24,"")
A28: ='Partner Master'!A8 -> Dar App | B28: ='Partner Master'!B8 -> Corporate discount | C28: =SUMIFS('Weekly Log'!$H$5:$H$636,'Weekly Log'!$G$5:$G$636,Dashboard!$C$4,'Weekly Log'!$L$5:$L$636,$A28) -> 0 | D28: =SUMIFS('Month Data'!$H$5:$H$42,'Month Data'!$L$5:$L$42,$A28) -> 0 | E28: =SUMIFS('Month Data'!$J$5:$J$42,'Month Data'!$L$5:$L$42,$A28) -> 0 | F28: =SUMIFS('Month Data'!$K$5:$K$42,'Month Data'!$L$5:$L$42,$A28) -> 0 | G28: =IF(D28=0,0,F28/D28) -> 0 | H28: =SUMIFS('Trend Data'!$H$5:$H$2085,'Trend Data'!$L$5:$L$2085,$A28,'Trend Data'!$G$5:$G$2085,$B$21) -> 0 | I28: =D28-H28 -> 0 | J28: =IF(D28=0,"No usage","Active") -> No usage | K28: =SUMIFS('Weekly Log'!$H$5:$H$636,'Weekly Log'!$G$5:$G$636,Dashboard!$C$5,'Weekly Log'!$L$5:$L$636,$A28) -> 0 | L28: =C28-K28 -> 0 | M28: =C28+(45-ROW())/1000 -> 0.017 | N28: =IF(D28=0,ROW()-24,"") -> 4
A29: ='Partner Master'!A9 -> Qatar Airways | B29: ='Partner Master'!B9 -> Corporate discount | C29: =SUMIFS('Weekly Log'!$H$5:$H$636,'Weekly Log'!$G$5:$G$636,Dashboard!$C$4,'Weekly Log'!$L$5:$L$636,$A29) -> 37 | D29: =SUMIFS('Month Data'!$H$5:$H$42,'Month Data'!$L$5:$L$42,$A29) -> 66 | E29: =SUMIFS('Month Data'!$J$5:$J$42,'Month Data'!$L$5:$L$42,$A29) -> 205 | F29: =SUMIFS('Month Data'!$K$5:$K$42,'Month Data'!$L$5:$L$42,$A29) -> 1455 | G29: =IF(D29=0,0,F29/D29) -> 22.045455 | H29: =SUMIFS('Trend Data'!$H$5:$H$2085,'Trend Data'!$L$5:$L$2085,$A29,'Trend Data'!$G$5:$G$2085,$B$21) -> 140 | I29: =D29-H29 -> -74 | J29: =IF(D29=0,"No usage","Active") -> Active | K29: =SUMIFS('Weekly Log'!$H$5:$H$636,'Weekly Log'!$G$5:$G$636,Dashboard!$C$5,'Weekly Log'!$L$5:$L$636,$A29) -> 0 | L29: =C29-K29 -> 37 | M29: =C29+(45-ROW())/1000 -> 37.016 | N29: =IF(D29=0,ROW()-24,"")
A30: ='Partner Master'!A10 -> Entertainer | B30: ='Partner Master'!B10 -> Aggregator BOGO | C30: =SUMIFS('Weekly Log'!$H$5:$H$636,'Weekly Log'!$G$5:$G$636,Dashboard!$C$4,'Weekly Log'!$L$5:$L$636,$A30) -> 14 | D30: =SUMIFS('Month Data'!$H$5:$H$42,'Month Data'!$L$5:$L$42,$A30) -> 19 | E30: =SUMIFS('Month Data'!$J$5:$J$42,'Month Data'!$L$5:$L$42,$A30) -> 19 | F30: =SUMIFS('Month Data'!$K$5:$K$42,'Month Data'!$L$5:$L$42,$A30) -> 2593 | G30: =IF(D30=0,0,F30/D30) -> 136.47368 | H30: =SUMIFS('Trend Data'!$H$5:$H$2085,'Trend Data'!$L$5:$L$2085,$A30,'Trend Data'!$G$5:$G$2085,$B$21) -> 19 | I30: =D30-H30 -> 0 | J30: =IF(D30=0,"No usage","Active") -> Active | K30: =SUMIFS('Weekly Log'!$H$5:$H$636,'Weekly Log'!$G$5:$G$636,Dashboard!$C$5,'Weekly Log'!$L$5:$L$636,$A30) -> 0 | L30: =C30-K30 -> 14 | M30: =C30+(45-ROW())/1000 -> 14.015 | N30: =IF(D30=0,ROW()-24,"")
A31: ='Partner Master'!A11 -> Public Health Sector (Sogha) | B31: ='Partner Master'!B11 -> Corporate discount | C31: =SUMIFS('Weekly Log'!$H$5:$H$636,'Weekly Log'!$G$5:$G$636,Dashboard!$C$4,'Weekly Log'!$L$5:$L$636,$A31) -> 25 | D31: =SUMIFS('Month Data'!$H$5:$H$42,'Month Data'!$L$5:$L$42,$A31) -> 51 | E31: =SUMIFS('Month Data'!$J$5:$J$42,'Month Data'!$L$5:$L$42,$A31) -> 157 | F31: =SUMIFS('Month Data'!$K$5:$K$42,'Month Data'!$L$5:$L$42,$A31) -> 1534 | G31: =IF(D31=0,0,F31/D31) -> 30.078431 | H31: =SUMIFS('Trend Data'!$H$5:$H$2085,'Trend Data'!$L$5:$L$2085,$A31,'Trend Data'!$G$5:$G$2085,$B$21) -> 119 | I31: =D31-H31 -> -68 | J31: =IF(D31=0,"No usage","Active") -> Active | K31: =SUMIFS('Weekly Log'!$H$5:$H$636,'Weekly Log'!$G$5:$G$636,Dashboard!$C$5,'Weekly Log'!$L$5:$L$636,$A31) -> 0 | L31: =C31-K31 -> 25 | M31: =C31+(45-ROW())/1000 -> 25.014 | N31: =IF(D31=0,ROW()-24,"")
A32: ='Partner Master'!A12 -> Urban Point | B32: ='Partner Master'!B12 -> Aggregator BOGO | C32: =SUMIFS('Weekly Log'!$H$5:$H$636,'Weekly Log'!$G$5:$G$636,Dashboard!$C$4,'Weekly Log'!$L$5:$L$636,$A32) -> 27 | D32: =SUMIFS('Month Data'!$H$5:$H$42,'Month Data'!$L$5:$L$42,$A32) -> 40 | E32: =SUMIFS('Month Data'!$J$5:$J$42,'Month Data'!$L$5:$L$42,$A32) -> 40 | F32: =SUMIFS('Month Data'!$K$5:$K$42,'Month Data'!$L$5:$L$42,$A32) -> 6277 | G32: =IF(D32=0,0,F32/D32) -> 156.925 | H32: =SUMIFS('Trend Data'!$H$5:$H$2085,'Trend Data'!$L$5:$L$2085,$A32,'Trend Data'!$G$5:$G$2085,$B$21) -> 69 | I32: =D32-H32 -> -29 | J32: =IF(D32=0,"No usage","Active") -> Active | K32: =SUMIFS('Weekly Log'!$H$5:$H$636,'Weekly Log'!$G$5:$G$636,Dashboard!$C$5,'Weekly Log'!$L$5:$L$636,$A32) -> 0 | L32: =C32-K32 -> 27 | M32: =C32+(45-ROW())/1000 -> 27.013 | N32: =IF(D32=0,ROW()-24,"")
A33: ='Partner Master'!A13 -> Qatar Living Deals | B33: ='Partner Master'!B13 -> Aggregator BOGO | C33: =SUMIFS('Weekly Log'!$H$5:$H$636,'Weekly Log'!$G$5:$G$636,Dashboard!$C$4,'Weekly Log'!$L$5:$L$636,$A33) -> 0 | D33: =SUMIFS('Month Data'!$H$5:$H$42,'Month Data'!$L$5:$L$42,$A33) -> 1 | E33: =SUMIFS('Month Data'!$J$5:$J$42,'Month Data'!$L$5:$L$42,$A33) -> 1 | F33: =SUMIFS('Month Data'!$K$5:$K$42,'Month Data'!$L$5:$L$42,$A33) -> 100 | G33: =IF(D33=0,0,F33/D33) -> 100 | H33: =SUMIFS('Trend Data'!$H$5:$H$2085,'Trend Data'!$L$5:$L$2085,$A33,'Trend Data'!$G$5:$G$2085,$B$21) -> 0 | I33: =D33-H33 -> 1 | J33: =IF(D33=0,"No usage","Active") -> Active | K33: =SUMIFS('Weekly Log'!$H$5:$H$636,'Weekly Log'!$G$5:$G$636,Dashboard!$C$5,'Weekly Log'!$L$5:$L$636,$A33) -> 0 | L33: =C33-K33 -> 0 | M33: =C33+(45-ROW())/1000 -> 0.012 | N33: =IF(D33=0,ROW()-24,"")
A34: ='Partner Master'!A14 -> Imtyazat | B34: ='Partner Master'!B14 -> Corporate discount | C34: =SUMIFS('Weekly Log'!$H$5:$H$636,'Weekly Log'!$G$5:$G$636,Dashboard!$C$4,'Weekly Log'!$L$5:$L$636,$A34) -> 40 | D34: =SUMIFS('Month Data'!$H$5:$H$42,'Month Data'!$L$5:$L$42,$A34) -> 72 | E34: =SUMIFS('Month Data'!$J$5:$J$42,'Month Data'!$L$5:$L$42,$A34) -> 305 | F34: =SUMIFS('Month Data'!$K$5:$K$42,'Month Data'!$L$5:$L$42,$A34) -> 2221.5 | G34: =IF(D34=0,0,F34/D34) -> 30.854167 | H34: =SUMIFS('Trend Data'!$H$5:$H$2085,'Trend Data'!$L$5:$L$2085,$A34,'Trend Data'!$G$5:$G$2085,$B$21) -> 261 | I34: =D34-H34 -> -189 | J34: =IF(D34=0,"No usage","Active") -> Active | K34: =SUMIFS('Weekly Log'!$H$5:$H$636,'Weekly Log'!$G$5:$G$636,Dashboard!$C$5,'Weekly Log'!$L$5:$L$636,$A34) -> 0 | L34: =C34-K34 -> 40 | M34: =C34+(45-ROW())/1000 -> 40.011 | N34: =IF(D34=0,ROW()-24,"")
A35: ='Partner Master'!A15 -> Classmate | B35: ='Partner Master'!B15 -> Aggregator BOGO | C35: =SUMIFS('Weekly Log'!$H$5:$H$636,'Weekly Log'!$G$5:$G$636,Dashboard!$C$4,'Weekly Log'!$L$5:$L$636,$A35) -> 0 | D35: =SUMIFS('Month Data'!$H$5:$H$42,'Month Data'!$L$5:$L$42,$A35) -> 0 | E35: =SUMIFS('Month Data'!$J$5:$J$42,'Month Data'!$L$5:$L$42,$A35) -> 0 | F35: =SUMIFS('Month Data'!$K$5:$K$42,'Month Data'!$L$5:$L$42,$A35) -> 0 | G35: =IF(D35=0,0,F35/D35) -> 0 | H35: =SUMIFS('Trend Data'!$H$5:$H$2085,'Trend Data'!$L$5:$L$2085,$A35,'Trend Data'!$G$5:$G$2085,$B$21) -> 0 | I35: =D35-H35 -> 0 | J35: =IF(D35=0,"No usage","Active") -> No usage | K35: =SUMIFS('Weekly Log'!$H$5:$H$636,'Weekly Log'!$G$5:$G$636,Dashboard!$C$5,'Weekly Log'!$L$5:$L$636,$A35) -> 0 | L35: =C35-K35 -> 0 | M35: =C35+(45-ROW())/1000 -> 0.01 | N35: =IF(D35=0,ROW()-24,"") -> 11
A36: ='Partner Master'!A16 -> MyBenefit | B36: ='Partner Master'!B16 -> Corporate discount | C36: =SUMIFS('Weekly Log'!$H$5:$H$636,'Weekly Log'!$G$5:$G$636,Dashboard!$C$4,'Weekly Log'!$L$5:$L$636,$A36) -> 0 | D36: =SUMIFS('Month Data'!$H$5:$H$42,'Month Data'!$L$5:$L$42,$A36) -> 0 | E36: =SUMIFS('Month Data'!$J$5:$J$42,'Month Data'!$L$5:$L$42,$A36) -> 0 | F36: =SUMIFS('Month Data'!$K$5:$K$42,'Month Data'!$L$5:$L$42,$A36) -> 0 | G36: =IF(D36=0,0,F36/D36) -> 0 | H36: =SUMIFS('Trend Data'!$H$5:$H$2085,'Trend Data'!$L$5:$L$2085,$A36,'Trend Data'!$G$5:$G$2085,$B$21) -> 0 | I36: =D36-H36 -> 0 | J36: =IF(D36=0,"No usage","Active") -> No usage | K36: =SUMIFS('Weekly Log'!$H$5:$H$636,'Weekly Log'!$G$5:$G$636,Dashboard!$C$5,'Weekly Log'!$L$5:$L$636,$A36) -> 0 | L36: =C36-K36 -> 0 | M36: =C36+(45-ROW())/1000 -> 0.009 | N36: =IF(D36=0,ROW()-24,"") -> 12
... A45: ='Partner Master'!A25 -> Snoonu Employees | B45: ='Partner Master'!B25 -> Corporate discount | C45: =SUMIFS('Weekly Log'!$H$5:$H$636,'Weekly Log'!$G$5:$G$636,Dashboard!$C$4,'Weekly Log'!$L$5:$L$636,$A45) -> 0 | D45: =SUMIFS('Month Data'!$H$5:$H$42,'Month Data'!$L$5:$L$42,$A45) -> 0 | E45: =SUMIFS('Month Data'!$J$5:$J$42,'Month Data'!$L$5:$L$42,$A45) -> 0 | F45: =SUMIFS('Month Data'!$K$5:$K$42,'Month Data'!$L$5:$L$42,$A45) -> 0 | G45: =IF(D45=0,0,F45/D45) -> 0 | H45: =SUMIFS('Trend Data'!$H$5:$H$2085,'Trend Data'!$L$5:$L$2085,$A45,'Trend Data'!$G$5:$G$2085,$B$21) -> 0 | I45: =D45-H45 -> 0 | J45: =IF(D45=0,"No usage","Active") -> No usage | K45: =SUMIFS('Weekly Log'!$H$5:$H$636,'Weekly Log'!$G$5:$G$636,Dashboard!$C$5,'Weekly Log'!$L$5:$L$636,$A45) -> 0 | L45: =C45-K45 -> 0 | M45: =C45+(45-ROW())/1000 -> 0 | N45: =IF(D45=0,ROW()-24,"") -> 21
A46: Total (partners on master) | C46: =SUM(C25:C45) -> 194 | D46: =SUM(D25:D45) -> 351 | E46: =SUM(E25:E45) -> 1042 | F46: =SUM(F25:F45) -> 21132.95 | H46: =SUM(H25:H45) -> 873 | I46: =SUM(I25:I45) -> -522
A47: Codes not on master or unmapped (month, excluded from partner totals above) | D47: =SUMIFS('Month Data'!$H$5:$H$42,'Month Data'!$M$5:$M$42,"Not on master")+SUMIFS('Month Data'!$H$5:$H$42,'Month Data'!$M$5:$M$42,"Unmapped") -> 0
A49: Monthly trend, last 13 months (partners only, internal codes excluded)
A50: Month | B50: Redemptions | C50: Tickets | D50: Discount QAR | E50: Corporate discount redemptions | F50: Aggregator BOGO redemptions
A51: 2025-09 | B51: =SUMIFS('Trend Data'!$H$5:$H$2085,'Trend Data'!$G$5:$G$2085,$A51,'Trend Data'!$M$5:$M$2085,"<>Internal / promotion") -> 309 | C51: =SUMIFS('Trend Data'!$J$5:$J$2085,'Trend Data'!$G$5:$G$2085,$A51,'Trend Data'!$M$5:$M$2085,"<>Internal / promotion") -> 340 | D51: =SUMIFS('Trend Data'!$K$5:$K$2085,'Trend Data'!$G$5:$G$2085,$A51,'Trend Data'!$M$5:$M$2085,"<>Internal / promotion") -> 47609.5 | E51: =SUMIFS('Trend Data'!$H$5:$H$2085,'Trend Data'!$G$5:$G$2085,$A51,'Trend Data'!$M$5:$M$2085,"Corporate discount") -> 30 | F51: =SUMIFS('Trend Data'!$H$5:$H$2085,'Trend Data'!$G$5:$G$2085,$A51,'Trend Data'!$M$5:$M$2085,"Aggregator BOGO") -> 259
A52: 2025-10 | B52: =SUMIFS('Trend Data'!$H$5:$H$2085,'Trend Data'!$G$5:$G$2085,$A52,'Trend Data'!$M$5:$M$2085,"<>Internal / promotion") -> 428 | C52: =SUMIFS('Trend Data'!$J$5:$J$2085,'Trend Data'!$G$5:$G$2085,$A52,'Trend Data'!$M$5:$M$2085,"<>Internal / promotion") -> 456 | D52: =SUMIFS('Trend Data'!$K$5:$K$2085,'Trend Data'!$G$5:$G$2085,$A52,'Trend Data'!$M$5:$M$2085,"<>Internal / promotion") -> 70015 | E52: =SUMIFS('Trend Data'!$H$5:$H$2085,'Trend Data'!$G$5:$G$2085,$A52,'Trend Data'!$M$5:$M$2085,"Corporate discount") -> 20 | F52: =SUMIFS('Trend Data'!$H$5:$H$2085,'Trend Data'!$G$5:$G$2085,$A52,'Trend Data'!$M$5:$M$2085,"Aggregator BOGO") -> 388
A53: 2025-11 | B53: =SUMIFS('Trend Data'!$H$5:$H$2085,'Trend Data'!$G$5:$G$2085,$A53,'Trend Data'!$M$5:$M$2085,"<>Internal / promotion") -> 201 | C53: =SUMIFS('Trend Data'!$J$5:$J$2085,'Trend Data'!$G$5:$G$2085,$A53,'Trend Data'!$M$5:$M$2085,"<>Internal / promotion") -> 222 | D53: =SUMIFS('Trend Data'!$K$5:$K$2085,'Trend Data'!$G$5:$G$2085,$A53,'Trend Data'!$M$5:$M$2085,"<>Internal / promotion") -> 29360.5 | E53: =SUMIFS('Trend Data'!$H$5:$H$2085,'Trend Data'!$G$5:$G$2085,$A53,'Trend Data'!$M$5:$M$2085,"Corporate discount") -> 16 | F53: =SUMIFS('Trend Data'!$H$5:$H$2085,'Trend Data'!$G$5:$G$2085,$A53,'Trend Data'!$M$5:$M$2085,"Aggregator BOGO") -> 164
A54: 2025-12 | B54: =SUMIFS('Trend Data'!$H$5:$H$2085,'Trend Data'!$G$5:$G$2085,$A54,'Trend Data'!$M$5:$M$2085,"<>Internal / promotion") -> 374 | C54: =SUMIFS('Trend Data'!$J$5:$J$2085,'Trend Data'!$G$5:$G$2085,$A54,'Trend Data'!$M$5:$M$2085,"<>Internal / promotion") -> 392 | D54: =SUMIFS('Trend Data'!$K$5:$K$2085,'Trend Data'!$G$5:$G$2085,$A54,'Trend Data'!$M$5:$M$2085,"<>Internal / promotion") -> 61061.75 | E54: =SUMIFS('Trend Data'!$H$5:$H$2085,'Trend Data'!$G$5:$G$2085,$A54,'Trend Data'!$M$5:$M$2085,"Corporate discount") -> 13 | F54: =SUMIFS('Trend Data'!$H$5:$H$2085,'Trend Data'!$G$5:$G$2085,$A54,'Trend Data'!$M$5:$M$2085,"Aggregator BOGO") -> 345
A55: 2026-01 | B55: =SUMIFS('Trend Data'!$H$5:$H$2085,'Trend Data'!$G$5:$G$2085,$A55,'Trend Data'!$M$5:$M$2085,"<>Internal / promotion") -> 301 | C55: =SUMIFS('Trend Data'!$J$5:$J$2085,'Trend Data'!$G$5:$G$2085,$A55,'Trend Data'!$M$5:$M$2085,"<>Internal / promotion") -> 312 | D55: =SUMIFS('Trend Data'!$K$5:$K$2085,'Trend Data'!$G$5:$G$2085,$A55,'Trend Data'!$M$5:$M$2085,"<>Internal / promotion") -> 50022.25 | E55: =SUMIFS('Trend Data'!$H$5:$H$2085,'Trend Data'!$G$5:$G$2085,$A55,'Trend Data'!$M$5:$M$2085,"Corporate discount") -> 11 | F55: =SUMIFS('Trend Data'!$H$5:$H$2085,'Trend Data'!$G$5:$G$2085,$A55,'Trend Data'!$M$5:$M$2085,"Aggregator BOGO") -> 285
A56: 2026-02 | B56: =SUMIFS('Trend Data'!$H$5:$H$2085,'Trend Data'!$G$5:$G$2085,$A56,'Trend Data'!$M$5:$M$2085,"<>Internal / promotion") -> 221 | C56: =SUMIFS('Trend Data'!$J$5:$J$2085,'Trend Data'!$G$5:$G$2085,$A56,'Trend Data'!$M$5:$M$2085,"<>Internal / promotion") -> 227 | D56: =SUMIFS('Trend Data'!$K$5:$K$2085,'Trend Data'!$G$5:$G$2085,$A56,'Trend Data'!$M$5:$M$2085,"<>Internal / promotion") -> 36656.75 | E56: =SUMIFS('Trend Data'!$H$5:$H$2085,'Trend Data'!$G$5:$G$2085,$A56,'Trend Data'!$M$5:$M$2085,"Corporate discount") -> 13 | F56: =SUMIFS('Trend Data'!$H$5:$H$2085,'Trend Data'!$G$5:$G$2085,$A56,'Trend Data'!$M$5:$M$2085,"Aggregator BOGO") -> 205
A57: 2026-03 | B57: =SUMIFS('Trend Data'!$H$5:$H$2085,'Trend Data'!$G$5:$G$2085,$A57,'Trend Data'!$M$5:$M$2085,"<>Internal / promotion") -> 350 | C57: =SUMIFS('Trend Data'!$J$5:$J$2085,'Trend Data'!$G$5:$G$2085,$A57,'Trend Data'!$M$5:$M$2085,"<>Internal / promotion") -> 362 | D57: =SUMIFS('Trend Data'!$K$5:$K$2085,'Trend Data'!$G$5:$G$2085,$A57,'Trend Data'!$M$5:$M$2085,"<>Internal / promotion") -> 57869.5 | E57: =SUMIFS('Trend Data'!$H$5:$H$2085,'Trend Data'!$G$5:$G$2085,$A57,'Trend Data'!$M$5:$M$2085,"Corporate discount") -> 29 | F57: =SUMIFS('Trend Data'!$H$5:$H$2085,'Trend Data'!$G$5:$G$2085,$A57,'Trend Data'!$M$5:$M$2085,"Aggregator BOGO") -> 311
A58: 2026-04 | B58: =SUMIFS('Trend Data'!$H$5:$H$2085,'Trend Data'!$G$5:$G$2085,$A58,'Trend Data'!$M$5:$M$2085,"<>Internal / promotion") -> 419 | C58: =SUMIFS('Trend Data'!$J$5:$J$2085,'Trend Data'!$G$5:$G$2085,$A58,'Trend Data'!$M$5:$M$2085,"<>Internal / promotion") -> 985 | D58: =SUMIFS('Trend Data'!$K$5:$K$2085,'Trend Data'!$G$5:$G$2085,$A58,'Trend Data'!$M$5:$M$2085,"<>Internal / promotion") -> 43002.05 | E58: =SUMIFS('Trend Data'!$H$5:$H$2085,'Trend Data'!$G$5:$G$2085,$A58,'Trend Data'!$M$5:$M$2085,"Corporate discount") -> 200 | F58: =SUMIFS('Trend Data'!$H$5:$H$2085,'Trend Data'!$G$5:$G$2085,$A58,'Trend Data'!$M$5:$M$2085,"Aggregator BOGO") -> 216
A59: 2026-05 | B59: =SUMIFS('Trend Data'!$H$5:$H$2085,'Trend Data'!$G$5:$G$2085,$A59,'Trend Data'!$M$5:$M$2085,"<>Internal / promotion") -> 706 | C59: =SUMIFS('Trend Data'!$J$5:$J$2085,'Trend Data'!$G$5:$G$2085,$A59,'Trend Data'!$M$5:$M$2085,"<>Internal / promotion") -> 1954 | D59: =SUMIFS('Trend Data'!$K$5:$K$2085,'Trend Data'!$G$5:$G$2085,$A59,'Trend Data'!$M$5:$M$2085,"<>Internal / promotion") -> 48519.2 | E59: =SUMIFS('Trend Data'!$H$5:$H$2085,'Trend Data'!$G$5:$G$2085,$A59,'Trend Data'!$M$5:$M$2085,"Corporate discount") -> 482 | F59: =SUMIFS('Trend Data'!$H$5:$H$2085,'Trend Data'!$G$5:$G$2085,$A59,'Trend Data'!$M$5:$M$2085,"Aggregator BOGO") -> 220
A60: 2026-06 | B60: =SUMIFS('Trend Data'!$H$5:$H$2085,'Trend Data'!$G$5:$G$2085,$A60,'Trend Data'!$M$5:$M$2085,"<>Internal / promotion") -> 797 | C60: =SUMIFS('Trend Data'!$J$5:$J$2085,'Trend Data'!$G$5:$G$2085,$A60,'Trend Data'!$M$5:$M$2085,"<>Internal / promotion") -> 2419 | D60: =SUMIFS('Trend Data'!$K$5:$K$2085,'Trend Data'!$G$5:$G$2085,$A60,'Trend Data'!$M$5:$M$2085,"<>Internal / promotion") -> 50611.6 | E60: =SUMIFS('Trend Data'!$H$5:$H$2085,'Trend Data'!$G$5:$G$2085,$A60,'Trend Data'!$M$5:$M$2085,"Corporate discount") -> 605 | F60: =SUMIFS('Trend Data'!$H$5:$H$2085,'Trend Data'!$G$5:$G$2085,$A60,'Trend Data'!$M$5:$M$2085,"Aggregator BOGO") -> 191
A61: 2026-07 | B61: =SUMIFS('Trend Data'!$H$5:$H$2085,'Trend Data'!$G$5:$G$2085,$A61,'Trend Data'!$M$5:$M$2085,"<>Internal / promotion") -> 892 | C61: =SUMIFS('Trend Data'!$J$5:$J$2085,'Trend Data'!$G$5:$G$2085,$A61,'Trend Data'!$M$5:$M$2085,"<>Internal / promotion") -> 2915 | D61: =SUMIFS('Trend Data'!$K$5:$K$2085,'Trend Data'!$G$5:$G$2085,$A61,'Trend Data'!$M$5:$M$2085,"<>Internal / promotion") -> 56794.95 | E61: =SUMIFS('Trend Data'!$H$5:$H$2085,'Trend Data'!$G$5:$G$2085,$A61,'Trend Data'!$M$5:$M$2085,"Corporate discount") -> 701 | F61: =SUMIFS('Trend Data'!$H$5:$H$2085,'Trend Data'!$G$5:$G$2085,$A61,'Trend Data'!$M$5:$M$2085,"Aggregator BOGO") -> 185
A62: 2026-08 | B62: =SUMIFS('Trend Data'!$H$5:$H$2085,'Trend Data'!$G$5:$G$2085,$A62,'Trend Data'!$M$5:$M$2085,"<>Internal / promotion") -> 876 | C62: =SUMIFS('Trend Data'!$J$5:$J$2085,'Trend Data'!$G$5:$G$2085,$A62,'Trend Data'!$M$5:$M$2085,"<>Internal / promotion") -> 2648 | D62: =SUMIFS('Trend Data'!$K$5:$K$2085,'Trend Data'!$G$5:$G$2085,$A62,'Trend Data'!$M$5:$M$2085,"<>Internal / promotion") -> 56366.7 | E62: =SUMIFS('Trend Data'!$H$5:$H$2085,'Trend Data'!$G$5:$G$2085,$A62,'Trend Data'!$M$5:$M$2085,"Corporate discount") -> 669 | F62: =SUMIFS('Trend Data'!$H$5:$H$2085,'Trend Data'!$G$5:$G$2085,$A62,'Trend Data'!$M$5:$M$2085,"Aggregator BOGO") -> 204
A63: 2026-09 | B63: =SUMIFS('Trend Data'!$H$5:$H$2085,'Trend Data'!$G$5:$G$2085,$A63,'Trend Data'!$M$5:$M$2085,"<>Internal / promotion") -> 351 | C63: =SUMIFS('Trend Data'!$J$5:$J$2085,'Trend Data'!$G$5:$G$2085,$A63,'Trend Data'!$M$5:$M$2085,"<>Internal / promotion") -> 1042 | D63: =SUMIFS('Trend Data'!$K$5:$K$2085,'Trend Data'!$G$5:$G$2085,$A63,'Trend Data'!$M$5:$M$2085,"<>Internal / promotion") -> 21132.95 | E63: =SUMIFS('Trend Data'!$H$5:$H$2085,'Trend Data'!$G$5:$G$2085,$A63,'Trend Data'!$M$5:$M$2085,"Corporate discount") -> 266 | F63: =SUMIFS('Trend Data'!$H$5:$H$2085,'Trend Data'!$G$5:$G$2085,$A63,'Trend Data'!$M$5:$M$2085,"Aggregator BOGO") -> 85
A64: Note: the current month is month to date. Months before May 2026 used single-use 100% codes for aggregator free passes; from May the BOGO codes replaced them, which changes the ticket count per redemption.
A66: Loyalty and in-house codes (excluded from partner totals)
A67: Code | B67: Venue | C67: Description | D67: Week: uses | E67: Week: tickets | F67: Month: uses
A68: loyaltyinf | B68: InflataPark | C68: In-house offer | D68: =SUMIFS('Weekly Log'!$H$5:$H$636,'Weekly Log'!$G$5:$G$636,Dashboard!$C$4,'Weekly Log'!$B$5:$B$636,$A68,'Weekly Log'!$N$5:$N$636,$B68) -> 1 | E68: =SUMIFS('Weekly Log'!$J$5:$J$636,'Weekly Log'!$G$5:$G$636,Dashboard!$C$4,'Weekly Log'!$B$5:$B$636,$A68,'Weekly Log'!$N$5:$N$636,$B68) -> 1 | F68: =SUMIFS('Month Data'!$H$5:$H$42,'Month Data'!$B$5:$B$42,$A68,'Month Data'!$N$5:$N$42,$B68) -> 1
A69: loyaltykds | B69: Kids City Driving School | C69: loyalty pass free city pass | D69: =SUMIFS('Weekly Log'!$H$5:$H$636,'Weekly Log'!$G$5:$G$636,Dashboard!$C$4,'Weekly Log'!$B$5:$B$636,$A69,'Weekly Log'!$N$5:$N$636,$B69) -> 7 | E69: =SUMIFS('Weekly Log'!$J$5:$J$636,'Weekly Log'!$G$5:$G$636,Dashboard!$C$4,'Weekly Log'!$B$5:$B$636,$A69,'Weekly Log'!$N$5:$N$636,$B69) -> 7 | F69: =SUMIFS('Month Data'!$H$5:$H$42,'Month Data'!$B$5:$B$42,$A69,'Month Data'!$N$5:$N$42,$B69) -> 13
A70: cafe50 | B70: Urban Arena | C70: 50% off on cafe | D70: =SUMIFS('Weekly Log'!$H$5:$H$636,'Weekly Log'!$G$5:$G$636,Dashboard!$C$4,'Weekly Log'!$B$5:$B$636,$A70,'Weekly Log'!$N$5:$N$636,$B70) -> 31 | E70: =SUMIFS('Weekly Log'!$J$5:$J$636,'Weekly Log'!$G$5:$G$636,Dashboard!$C$4,'Weekly Log'!$B$5:$B$636,$A70,'Weekly Log'!$N$5:$N$636,$B70) -> 36 | F70: =SUMIFS('Month Data'!$H$5:$H$42,'Month Data'!$B$5:$B$42,$A70,'Month Data'!$N$5:$N$42,$B70) -> 63
A71: karak100 | B71: Urban Arena | C71: In-house offer | D71: =SUMIFS('Weekly Log'!$H$5:$H$636,'Weekly Log'!$G$5:$G$636,Dashboard!$C$4,'Weekly Log'!$B$5:$B$636,$A71,'Weekly Log'!$N$5:$N$636,$B71) -> 1 | E71: =SUMIFS('Weekly Log'!$J$5:$J$636,'Weekly Log'!$G$5:$G$636,Dashboard!$C$4,'Weekly Log'!$B$5:$B$636,$A71,'Weekly Log'!$N$5:$N$636,$B71) -> 3 | F71: =SUMIFS('Month Data'!$H$5:$H$42,'Month Data'!$B$5:$B$42,$A71,'Month Data'!$N$5:$N$42,$B71) -> 1
A72: loyalty | B72: Urban Arena | C72: Loyalty customer free rookie pass | D72: =SUMIFS('Weekly Log'!$H$5:$H$636,'Weekly Log'!$G$5:$G$636,Dashboard!$C$4,'Weekly Log'!$B$5:$B$636,$A72,'Weekly Log'!$N$5:$N$636,$B72) -> 0 | E72: =SUMIFS('Weekly Log'!$J$5:$J$636,'Weekly Log'!$G$5:$G$636,Dashboard!$C$4,'Weekly Log'!$B$5:$B$636,$A72,'Weekly Log'!$N$5:$N$636,$B72) -> 0 | F72: =SUMIFS('Month Data'!$H$5:$H$42,'Month Data'!$B$5:$B$42,$A72,'Month Data'!$N$5:$N$42,$B72) -> 1
A73: Total | D73: =SUM(D68:D72) -> 40 | E73: =SUM(E68:E72) -> 47 | F73: =SUM(F68:F72) -> 79

Sheet Code Mapping
A1: Promo code mapping (edit the blue cells; every other sheet recalculates)
A2: Partner, Category and Venue were assigned from the code and its description. Yellow cells are editable inputs. "Not specified" means the code carries no venue; add the venue in BookingQube and here.
A4: Promo code | B4: Description (from system) | C4: Company field | D4: Partner | E4: Category | F4: Venue | G4: Last used (month) | H4: Uses, last 12 months | I4: Mapping source
A5: cafe50 | B5: 50% off on cafe | D5: Internal / promotion | E5: Internal / promotion | F5: Cafe | G5: 2026-09 | H5: 591 | I5: Derived from code and description
A6: KCDSIMTYD | B6: Imtyazat 15% Discount | C6: E3 | D6: Imtyazat | E6: Corporate discount | F6: KDS | G6: 2026-08 | H6: 519 | I6: Derived from code and description
A7: UPIP100 | B7: InflataPark urban point 100% | D7: Urban Point | E7: Aggregator BOGO | F7: InflataPark | G7: 2026-04 | H7: 516 | I7: Derived from code and description
A8: MBIP100 | B8: InflataPark mybook 100% | D8: My Book | E8: Aggregator BOGO | F8: InflataPark | G8: 2026-04 | H8: 454 | I8: Derived from code and description
A9: INFIMTYD | B9: Imtyazat 15% Discount | C9: E3 | D9: Imtyazat | E9: Corporate discount | F9: InflataPark | G9: 2026-09 | H9: 433 | I9: Derived from code and description
A10: UENA | B10: Qatar Airways 15% Discount | D10: Qatar Airways | E10: Corporate discount | F10: Not specified | G10: 2026-09 | H10: 282 | I10: Derived from code and description
A11: ARNB | B11: Qatar Foundation 15% Discount | C11: E3 | D11: Qatar Foundation | E11: Corporate discount | F11: Not specified | G11: 2026-09 | H11: 270 | I11: Derived from code and description
A12: UNAR | B12: Public Health Sector Employees 20% Discount | D12: Public Health Sector (Sogha) | E12: Corporate discount | F12: Not specified | G12: 2026-09 | H12: 257 | I12: Derived from code and description
A13: INFPHSED | B13: Public Health Sector Employees 20% Discount | D13: Public Health Sector (Sogha) | E13: Corporate discount | F13: InflataPark | G13: 2026-09 | H13: 254 | I13: Derived from code and description
A14: INFQAD | B14: Qatar Airways 15% Discount | D14: Qatar Airways | E14: Corporate discount | F14: InflataPark | G14: 2026-09 | H14: 248 | I14: Derived from code and description
A15: EIP100 | B15: InflataPark entertainer 100% | D15: Entertainer | E15: Aggregator BOGO | F15: InflataPark | G15: 2026-04 | H15: 210 | I15: Derived from code and description
A16: KCDIMTIYAZAT15 | B16: Imtiyazat 15% Discount | C16: E3 | D16: Imtyazat | E16: Corporate discount | F16: KDS | G16: 2026-09 | H16: 198 | I16: Derived from code and description
A17: UBOFFM | B17: My Book BOGO | D17: My Book | E17: Aggregator BOGO | F17: Not specified | G17: 2026-09 | H17: 177 | I17: Derived from code and description
A18: UGBOGU | B18: Urban Point BOGO | D18: Urban Point | E18: Aggregator BOGO | F18: Not specified | G18: 2026-09 | H18: 157 | I18: Derived from code and description
A19: CGBOGU | B19: Urban Point BOGO | D19: Urban Point | E19: Aggregator BOGO | F19: C&B (unspecified mall) | G19: 2026-09 | H19: 152 | I19: Derived from code and description
A20: UPVD | B20: urban point for vendom 100% | D20: Urban Point | E20: Aggregator BOGO | F20: C&B Vendome | G20: 2026-04 | H20: 140 | I20: Derived from code and description
A21: UHBP100 | B21: KDS urban point 100% | D21: Urban Point | E21: Aggregator BOGO | F21: KDS | G21: 2026-04 | H21: 113 | I21: Derived from code and description
A22: CBOGOE | B22: Entertainer BOGO | D22: Entertainer | E22: Aggregator BOGO | F22: C&B (unspecified mall) | G22: 2026-09 | H22: 102 | I22: Derived from code and description
A23: USBP100 | B23: KDS urban point 100% | D23: Urban Point | E23: Aggregator BOGO | F23: KDS | G23: 2026-03 | H23: 99 | I23: Derived from code and description
A24: EBOGO | D24: Entertainer | E24: Aggregator BOGO | F24: Not specified | G24: 2026-04 | H24: 97 | I24: Derived from code and description
A25: MYBVD | D25: My Book | E25: Aggregator BOGO | F25: C&B Vendome | G25: 2026-09 | H25: 94 | I25: Confirmed by Operations, Sep 2026
A26: BHBP100 | B26: KDS mybook 100% | D26: My Book | E26: Aggregator BOGO | F26: KDS | G26: 2026-04 | H26: 85 | I26: Derived from code and description
A27: RENA | B27: Imtyazat 15% Discount | D27: Imtyazat | E27: Corporate discount | F27: Not specified | G27: 2026-09 | H27: 85 | I27: Derived from code and description
A28: pp20 | D28: Internal / promotion | E28: Internal / promotion | F28: Not specified | G28: 2025-12 | H28: 63 | I28: Derived from code and description
A29: KDSBOGOM | C29: E3 | D29: My Book | E29: Aggregator BOGO | F29: KDS | G29: 2026-09 | H29: 62 | I29: Confirmed by Operations, Sep 2026
A30: INFQFD | B30: Qatar Foundation 15% Discount | D30: Qatar Foundation | E30: Corporate discount | F30: InflataPark | G30: 2026-09 | H30: 54 | I30: Derived from code and description
A31: loyaltykds | B31: loyalty pass free city pass | C31: E3 | D31: Internal / promotion | E31: Internal / promotion | F31: KDS | G31: 2026-09 | H31: 54 | I31: Derived from code and description
A32: KCDSURBOGO | B32: Urban Point BOGO | D32: Urban Point | E32: Aggregator BOGO | F32: KDS | G32: 2026-07 | H32: 53 | I32: Derived from code and description
A33: QAIP15 | B33: QATAR AIRWAYS INFLATAPARK 15% | D33: Qatar Airways | E33: Corporate discount | F33: InflataPark | G33: 2026-04 | H33: 45 | I33: Derived from code and description
A34: dmqnb15 | C34: QNB | D34: QNB Rewards | E34: Corporate discount | F34: Not specified | G34: 2026-09 | H34: 44 | I34: Confirmed by Operations, Sep 2026
A35: BSBP100 | B35: KDS mybook 100% | D35: My Book | E35: Aggregator BOGO | F35: KDS | G35: 2025-12 | H35: 42 | I35: Derived from code and description
A36: ESBP100 | B36: KDS entertainer 100% | D36: Entertainer | E36: Aggregator BOGO | F36: KDS | G36: 2026-03 | H36: 42 | I36: Derived from code and description
A37: ARNA | B37: Aspire 15% Discount | D37: Aspire | E37: Corporate discount | F37: Not specified | G37: 2026-09 | H37: 41 | I37: Derived from code and description
A38: zub50 | B38: Aspire Zubara 50% | D38: Internal / promotion | E38: Internal / promotion | F38: Aspire Carousel | G38: 2026-01 | H38: 40 | I38: Derived from code and description
A39: DL30 | B39: Driving License 30% | D39: Internal / promotion | E39: Internal / promotion | F39: Not specified | G39: 2026-04 | H39: 36 | I39: Derived from code and description
A40: INFUPBOGO2 | C40: E3 | D40: Urban Point | E40: Aggregator BOGO | F40: InflataPark | G40: 2026-09 | H40: 35 | I40: Confirmed by Operations, Sep 2026
A41: INFUPBOGO | B41: Urban Point BOGO | D41: Urban Point | E41: Aggregator BOGO | F41: InflataPark | G41: 2026-07 | H41: 33 | I41: Derived from code and description
A42: URBN | B42: Al Jazeera Imityazat 15% Discount | D42: Al Jazeera Imtiyazat | E42: Corporate discount | F42: Not specified | G42: 2026-09 | H42: 31 | I42: Derived from code and description
A43: MEDIA50 | B43: Media Experience Pass 50% | D43: Internal / promotion | E43: Internal / promotion | F43: Not specified | G43: 2026-01 | H43: 29 | I43: Derived from code and description
A44: UGOBOE | B44: Entertainer BOGO | D44: Entertainer | E44: Aggregator BOGO | F44: Not specified | G44: 2026-08 | H44: 26 | I44: Derived from code and description
A45: cmin10 | B45: 10% classmate inflatarun | D45: Internal / promotion | E45: Internal / promotion | F45: InflataPark | G45: 2025-12 | H45: 26 | I45: Derived from code and description
A46: KCDSAJID | B46: Al Jazeera Imityazat 15% Discount | D46: Al Jazeera Imtiyazat | E46: Corporate discount | F46: KDS | G46: 2026-07 | H46: 24 | I46: Derived from code and description
A47: BRNA | B47: QIB 15% Discount | D47: QIB | E47: Corporate discount | F47: Not specified | G47: 2026-09 | H47: 23 | I47: Derived from code and description
A48: INFAJID | B48: Al Jazeera Imityazat 15% Discount | D48: Al Jazeera Imtiyazat | E48: Corporate discount | F48: InflataPark | G48: 2026-09 | H48: 22 | I48: Derived from code and description
A49: UAQMC | B49: Qatar Media Corporation 15% Discount | D49: Qatar Media Corporation | E49: Corporate discount | F49: Urban Arena | G49: 2026-08 | H49: 22 | I49: Derived from code and description
A50: SCKDS | B50: Snoou City | D50: Snoonu Employees | E50: Corporate discount | F50: KDS | G50: 2026-04 | H50: 21 | I50: Derived from code and description
A51: HMCIP15 | B51: HMC Inflatapark 15% | D51: HMC (not on master) | E51: Not on master | F51: InflataPark | G51: 2026-04 | H51: 19 | I51: Derived from code and description
A52: INFENTBOGO2 | C52: E3 | D52: Entertainer | E52: Aggregator BOGO | F52: InflataPark | G52: 2026-09 | H52: 19 | I52: Confirmed by Operations, Sep 2026
A53: KCDSMYBOGO | B53: My Book BOGO | D53: My Book | E53: Aggregator BOGO | F53: KDS | G53: 2026-07 | H53: 19 | I53: Derived from code and description
A54: UARE | B54: Bein 15% Discount | D54: Bein | E54: Corporate discount | F54: Urban Arena | G54: 2026-08 | H54: 19 | I54: Derived from code and description
A55: EHBP100 | B55: KDS entertainer 100% | D55: Entertainer | E55: Aggregator BOGO | F55: KDS | G55: 2026-04 | H55: 18 | I55: Derived from code and description
A56: QA15 | B56: QATAR AIRWAYS KDS 15% | D56: Qatar Airways | E56: Corporate discount | F56: KDS | G56: 2026-04 | H56: 18 | I56: Derived from code and description
A57: IRDS | B57: buy one get one free driving school, inflatarun | D57: Internal / promotion | E57: Internal / promotion | F57: InflataPark | G57: 2025-12 | H57: 17 | I57: Derived from code and description
A58: IRIP | B58: Buy one get one free inflatapark , inflatarun | D58: Internal / promotion | E58: Internal / promotion | F58: InflataPark | G58: 2025-12 | H58: 17 | I58: Derived from code and description
A59: KCDQIA15 | B59: Qatar Investment Authority 15% Discount | C59: E3 | D59: Qatar Investment Authority | E59: Corporate discount | F59: KDS | G59: 2026-09 | H59: 16 | I59: Derived from code and description
A60: JR15 | B60: 15% off for juiors in inflatapark | D60: Internal / promotion | E60: Internal / promotion | F60: InflataPark | G60: 2026-04 | H60: 15 | I60: Derived from code and description
A61: TGI15 | B61: TGI 15% | D61: TGI (not on master) | E61: Not on master | F61: Not specified | G61: 2025-12 | H61: 15 | I61: Derived from code and description
A62: UBOGOC | B62: Classmate BOGO | D62: Classmate | E62: Aggregator BOGO | F62: C&B (unspecified mall) | G62: 2026-07 | H62: 15 | I62: Derived from code and description
A63: INFAMBBOGO | B63: My Book BOGO | D63: My Book | E63: Aggregator BOGO | F63: InflataPark | G63: 2026-07 | H63: 13 | I63: Confirmed by Operations, Sep 2026
A64: AJIP15 | B64: AL Jazeera inflatapark 15% | D64: Al Jazeera Imtiyazat | E64: Corporate discount | F64: InflataPark | G64: 2026-03 | H64: 12 | I64: Derived from code and description
A65: QIBIP15 | B65: QIB INFLATAPRK 15% | D65: QIB | E65: Corporate discount | F65: InflataPark | G65: 2025-12 | H65: 12 | I65: Derived from code and description
A66: uacm50 | D66: Internal / promotion | E66: Internal / promotion | F66: Urban Arena | G66: 2026-05 | H66: 11 | I66: Derived from code and description
A67: K9P3X | B67: Qatar Airways 15% Discount | D67: Qatar Airways | E67: Corporate discount | F67: Not specified | G67: 2026-09 | H67: 9 | I67: Derived from code and description
A68: rb20 | C68: E3 | D68: Internal / promotion | E68: Internal / promotion | F68: Not specified | G68: 2026-07 | H68: 9 | I68: Derived from code and description
A69: 15off | D69: Internal / promotion | E69: Internal / promotion | F69: Not specified | G69: 2026-05 | H69: 8 | I69: Derived from code and description
A70: KCDENTEBOGO | B70: Entertainer BOGO | D70: Entertainer | E70: Aggregator BOGO | F70: KDS | G70: 2026-07 | H70: 8 | I70: Derived from code and description
A71: KCDQAIRWAYS15 | B71: Qatar Airways 15% Discount | C71: E3 | D71: Qatar Airways | E71: Corporate discount | F71: KDS | G71: 2026-09 | H71: 8 | I71: Derived from code and description
A72: M2W7D | B72: Imtyazat 15% Discount | D72: Imtyazat | E72: Corporate discount | F72: Not specified | G72: 2026-08 | H72: 8 | I72: Derived from code and description
A73: UARB | B73: Qatar Investment Authority 15% Discount | D73: Qatar Investment Authority | E73: Corporate discount | F73: Urban Arena | G73: 2026-08 | H73: 8 | I73: Derived from code and description
A74: INFASPID | B74: Aspire 15% Discount | D74: Aspire | E74: Corporate discount | F74: InflataPark | G74: 2026-09 | H74: 7 | I74: Derived from code and description
A75: INFENTBOGO | B75: Entertainer BOGO | D75: Entertainer | E75: Aggregator BOGO | F75: InflataPark | G75: 2026-07 | H75: 7 | I75: Derived from code and description
A76: HMC15 | B76: HMC KDS 15% | D76: HMC (not on master) | E76: Not on master | F76: KDS | G76: 2026-03 | H76: 6 | I76: Derived from code and description
A77: INFAMBBOGO2 | C77: E3 | D77: My Book | E77: Aggregator BOGO | F77: InflataPark | G77: 2026-09 | H77: 6 | I77: Confirmed by Operations, Sep 2026
A78: loyalty | B78: Loyalty customer free rookie pass | C78: E3 | D78: Internal / promotion | E78: Internal / promotion | F78: Not specified | G78: 2026-09 | H78: 6 | I78: Derived from code and description
A79: INFQIAD | B79: Qatar Investment Authority 15% Discount | D79: Qatar Investment Authority | E79: Corporate discount | F79: InflataPark | G79: 2026-09 | H79: 5 | I79: Derived from code and description
A80: SCINF | B80: Snoou City | D80: Snoonu Employees | E80: Corporate discount | F80: InflataPark | G80: 2026-03 | H80: 5 | I80: Derived from code and description
A81: loyaltyinf | C81: E3 | D81: Internal / promotion | E81: Internal / promotion | F81: InflataPark | G81: 2026-09 | H81: 5 | I81: Confirmed by Operations, Sep 2026
A82: INFBEIND | B82: Bein 15% Discount | D82: Bein | E82: Corporate discount | F82: InflataPark | G82: 2026-09 | H82: 4 | I82: Derived from code and description
A83: INFQIBD | B83: QIB 15% Discount | D83: QIB | E83: Corporate discount | F83: InflataPark | G83: 2026-06 | H83: 4 | I83: Derived from code and description
A84: KCDSBEIND | B84: Bein 15% Discount | D84: Bein | E84: Corporate discount | F84: KDS | G84: 2026-07 | H84: 4 | I84: Derived from code and description
A85: R1Z6L | B85: Qatar Foundation 15% Discount | D85: Qatar Foundation | E85: Corporate discount | F85: Not specified | G85: 2026-09 | H85: 4 | I85: Derived from code and description
A86: karak100 | C86: E3 | D86: Internal / promotion | E86: Internal / promotion | F86: Urban Arena | G86: 2026-09 | H86: 4 | I86: Confirmed by Operations, Sep 2026
A87: CGOBOQ | B87: Qatar Living BOGO | D87: Qatar Living Deals | E87: Aggregator BOGO | F87: C&B (unspecified mall) | G87: 2026-09 | H87: 3 | I87: Derived from code and description
A88: FRND20 | D88: Unmapped | E88: Unmapped | F88: Not specified | G88: 2025-10 | H88: 3 | I88: Derived from code and description
A89: KD30 | B89: Kids driving school 30% | D89: Unmapped | E89: Unmapped | F89: KDS | G89: 2025-11 | H89: 3 | I89: Derived from code and description
A90: RONALD15 | D90: Unmapped | E90: Unmapped | F90: Not specified | G90: 2025-10 | H90: 3 | I90: Derived from code and description
A91: VIP200 | B91: 100% off for couples ticket comedy show | D91: Unmapped | E91: Unmapped | F91: Not specified | G91: 2025-10 | H91: 3 | I91: Derived from code and description
A92: dg100 | C92: E3 | D92: Unmapped | E92: Unmapped | F92: Not specified | G92: 2026-08 | H92: 3 | I92: Derived from code and description
A93: subr50 | B93: Ahmad Client 50% | C93: E3 | D93: Unmapped | E93: Unmapped | F93: Not specified | G93: 2026-07 | H93: 3 | I93: Derived from code and description
A94: AJ15 | B94: AL JAZEERA KDS 15% | D94: Al Jazeera Imtiyazat | E94: Corporate discount | F94: KDS | G94: 2026-02 | H94: 2 | I94: Derived from code and description
A95: GH25 | B95: Gulf hotel staff 25% off on single ticket | D95: Unmapped | E95: Unmapped | F95: Not specified | G95: 2025-12 | H95: 2 | I95: Derived from code and description
A96: ST15 | B96: school trip 15% off | C96: E3 | D96: Unmapped | E96: Unmapped | F96: Not specified | G96: 2026-07 | H96: 2 | I96: Derived from code and description
A97: UAM7K2WR | B97: Education Above all 100% | D97: Unmapped | E97: Unmapped | F97: Urban Arena | G97: 2026-05 | H97: 2 | I97: Derived from code and description
A98: infqnb15 | C98: QNB | D98: QNB Rewards | E98: Corporate discount | F98: InflataPark | G98: 2026-08 | H98: 2 | I98: Derived from code and description
A99: irebogo | D99: Unmapped | E99: Unmapped | F99: Not specified | G99: 2025-12 | H99: 2 | I99: Derived from code and description
A100: A7K2P | B100: Al Jazeera Imityazat 15% Discount | D100: Al Jazeera Imtiyazat | E100: Corporate discount | F100: Not specified | G100: 2026-06 | H100: 1 | I100: Derived from code and description
A101: AREN | B101: Dar App by fadaat media 15% Discount | D101: Dar App | E101: Corporate discount | F101: Not specified | G101: 2026-07 | H101: 1 | I101: Derived from code and description
...

Sheet Partner Master
A1: Partner master (from the Corporate Deals Google Sheet)
A2: Source: Corporate Deals sheet, both tabs. Add new partners here and in Code Mapping.
A4: Partner | B4: Category | C4: Redemption mechanism
A5: Al Jazeera Imtiyazat | B5: Corporate discount | C5: Staff ID
A6: My Book | B6: Aggregator BOGO | C6: App PIN 9247
A7: QIB | B7: Corporate discount | C7: QIB cardholders
A8: Dar App | B8: Corporate discount | C8: Dar community app
A9: Qatar Airways | B9: Corporate discount | C9: Staff ID
A10: Entertainer | B10: Aggregator BOGO | C10: App 9581
A11: Public Health Sector (Sogha) | B11: Corporate discount | C11: Sogha card ID
A12: Urban Point | B12: Aggregator BOGO | C12: App 7654
A13: Qatar Living Deals | B13: Aggregator BOGO | C13: Qatar Living Deals app
A14: Imtyazat | B14: Corporate discount | C14: Imtyazat ID card
A15: Classmate | B15: Aggregator BOGO | C15: App 9171
... A25: Snoonu Employees | B25: Corporate discount | C25: Scity app

Sheet Weekly Log
A1: Weekly Log: raw export from BookingQube plus lookup columns
A2: Weekly log: paste each new weekly export below the last filled row (columns A to I). Formulas cover 600 spare rows. The Dashboard reads the week named in Dashboard!C4.
A4: promocode_id | B4: promocode | C4: description | D4: company_name | E4: event_id | F4: event_title | G4: period_week | H4: times_used | I4: booking_lines | J4: tickets | K4: total_discount | L4: Partner | M4: Category | N4: Venue
A5: 8070 | B5: ARNA | C5: Aspire 15% Discount | E5: 133 | F5: Urban Arena | G5: 2026-W37 | H5: 3 | I5: 17 | J5: 17 | K5: 126.75 | L5: =IF($B5="","",IFERROR(INDEX('Code Mapping'!$D$5:$D$1753,MATCH($B5,'Code Mapping'!$A$5:$A$1753,0)),"Unmapped")) -> Aspire | M5: =IF($B5="","",IFERROR(INDEX('Code Mapping'!$E$5:$E$1753,MATCH($B5,'Code Mapping'!$A$5:$A$1753,0)),"Unmapped")) -> Corporate discount | N5: =IF($F5="","",$F5) -> Urban Arena
A6: 8079 | B6: ARNB | C6: Qatar Foundation 15% Discount | D6: E3 | E6: 133 | F6: Urban Arena | G6: 2026-W37 | H6: 10 | I6: 54 | J6: 54 | K6: 464.25 | L6: =IF($B6="","",IFERROR(INDEX('Code Mapping'!$D$5:$D$1753,MATCH($B6,'Code Mapping'!$A$5:$A$1753,0)),"Unmapped")) -> Qatar Foundation | M6: =IF($B6="","",IFERROR(INDEX('Code Mapping'!$E$5:$E$1753,MATCH($B6,'Code Mapping'!$A$5:$A$1753,0)),"Unmapped")) -> Corporate discount | N6: =IF($F6="","",$F6) -> Urban Arena
A7: 8077 | B7: BRNA | C7: QIB 15% Discount | E7: 133 | F7: Urban Arena | G7: 2026-W37 | H7: 2 | I7: 11 | J7: 11 | K7: 106.5 | L7: =IF($B7="","",IFERROR(INDEX('Code Mapping'!$D$5:$D$1753,MATCH($B7,'Code Mapping'!$A$5:$A$1753,0)),"Unmapped")) -> QIB | M7: =IF($B7="","",IFERROR(INDEX('Code Mapping'!$E$5:$E$1753,MATCH($B7,'Code Mapping'!$A$5:$A$1753,0)),"Unmapped")) -> Corporate discount | N7: =IF($F7="","",$F7) -> Urban Arena
A8: 8038 | B8: cafe50 | C8: 50% off on cafe | E8: 133 | F8: Urban Arena | G8: 2026-W37 | H8: 31 | I8: 36 | J8: 36 | K8: 247.5 | L8: =IF($B8="","",IFERROR(INDEX('Code Mapping'!$D$5:$D$1753,MATCH($B8,'Code Mapping'!$A$5:$A$1753,0)),"Unmapped")) -> Internal / promotion | M8: =IF($B8="","",IFERROR(INDEX('Code Mapping'!$E$5:$E$1753,MATCH($B8,'Code Mapping'!$A$5:$A$1753,0)),"Unmapped")) -> Internal / promotion | N8: =IF($F8="","",$F8) -> Urban Arena
A9: 8095 | B9: CBOGOE | C9: Entertainer BOGO | E9: 61 | F9: Crayons & Bricks Vendome | G9: 2026-W37 | H9: 9 | I9: 9 | J9: 9 | K9: 900 | L9: =IF($B9="","",IFERROR(INDEX('Code Mapping'!$D$5:$D$1753,MATCH($B9,'Code Mapping'!$A$5:$A$1753,0)),"Unmapped")) -> Entertainer | M9: =IF($B9="","",IFERROR(INDEX('Code Mapping'!$E$5:$E$1753,MATCH($B9,'Code Mapping'!$A$5:$A$1753,0)),"Unmapped")) -> Aggregator BOGO | N9: =IF($F9="","",$F9) -> Crayons & Bricks Vendome
A10: 8097 | B10: CGBOGU | C10: Urban Point BOGO | E10: 61 | F10: Crayons & Bricks Vendome | G10: 2026-W37 | H10: 12 | I10: 12 | J10: 12 | K10: 1200 | L10: =IF($B10="","",IFERROR(INDEX('Code Mapping'!$D$5:$D$1753,MATCH($B10,'Code Mapping'!$A$5:$A$1753,0)),"Unmapped")) -> Urban Point | M10: =IF($B10="","",IFERROR(INDEX('Code Mapping'!$E$5:$E$1753,MATCH($B10,'Code Mapping'!$A$5:$A$1753,0)),"Unmapped")) -> Aggregator BOGO | N10: =IF($F10="","",$F10) -> Crayons & Bricks Vendome
A11: 8318 | B11: dmqnb15 | D11: QNB | E11: 133 | F11: Urban Arena | G11: 2026-W37 | H11: 3 | I11: 10 | J11: 10 | K11: 93 | L11: =IF($B11="","",IFERROR(INDEX('Code Mapping'!$D$5:$D$1753,MATCH($B11,'Code Mapping'!$A$5:$A$1753,0)),"Unmapped")) -> QNB Rewards | M11: =IF($B11="","",IFERROR(INDEX('Code Mapping'!$E$5:$E$1753,MATCH($B11,'Code Mapping'!$A$5:$A$1753,0)),"Unmapped")) -> Corporate discount | N11: =IF($F11="","",$F11) -> Urban Arena
A12: 8047 | B12: INFASPID | C12: Aspire 15% Discount | E12: 91 | F12: InflataPark | G12: 2026-W37 | H12: 1 | I12: 2 | J12: 2 | K12: 15 | L12: =IF($B12="","",IFERROR(INDEX('Code Mapping'!$D$5:$D$1753,MATCH($B12,'Code Mapping'!$A$5:$A$1753,0)),"Unmapped")) -> Aspire | M12: =IF($B12="","",IFERROR(INDEX('Code Mapping'!$E$5:$E$1753,MATCH($B12,'Code Mapping'!$A$5:$A$1753,0)),"Unmapped")) -> Corporate discount | N12: =IF($F12="","",$F12) -> InflataPark
A13: 8324 | B13: INFENTBOGO2 | D13: E3 | E13: 91 | F13: InflataPark | G13: 2026-W37 | H13: 4 | I13: 4 | J13: 4 | K13: 796 | L13: =IF($B13="","",IFERROR(INDEX('Code Mapping'!$D$5:$D$1753,MATCH($B13,'Code Mapping'!$A$5:$A$1753,0)),"Unmapped")) -> Entertainer | M13: =IF($B13="","",IFERROR(INDEX('Code Mapping'!$E$5:$E$1753,MATCH($B13,'Code Mapping'!$A$5:$A$1753,0)),"Unmapped")) -> Aggregator BOGO | N13: =IF($F13="","",$F13) -> InflataPark
A14: 8052 | B14: INFIMTYD | C14: Imtyazat 15% Discount | D14: E3 | E14: 91 | F14: InflataPark | G14: 2026-W37 | H14: 13 | I14: 55 | J14: 55 | K14: 465.75 | L14: =IF($B14="","",IFERROR(INDEX('Code Mapping'!$D$5:$D$1753,MATCH($B14,'Code Mapping'!$A$5:$A$1753,0)),"Unmapped")) -> Imtyazat | M14: =IF($B14="","",IFERROR(INDEX('Code Mapping'!$E$5:$E$1753,MATCH($B14,'Code Mapping'!$A$5:$A$1753,0)),"Unmapped")) -> Corporate discount | N14: =IF($F14="","",$F14) -> InflataPark
A15: 8053 | B15: INFPHSED | C15: Public Health Sector Employees 20% Discount | E15: 91 | F15: InflataPark | G15: 2026-W37 | H15: 13 | I15: 33 | J15: 33 | K15: 315 | L15: =IF($B15="","",IFERROR(INDEX('Code Mapping'!$D$5:$D$1753,MATCH($B15,'Code Mapping'!$A$5:$A$1753,0)),"Unmapped")) -> Public Health Sector (Sogha) | M15: =IF($B15="","",IFERROR(INDEX('Code Mapping'!$E$5:$E$1753,MATCH($B15,'Code Mapping'!$A$5:$A$1753,0)),"Unmapped")) -> Corporate discount | N15: =IF($F15="","",$F15) -> InflataPark
A16: 8055 | B16: INFQAD | C16: Qatar Airways 15% Discount | E16: 91 | F16: InflataPark | G16: 2026-W37 | H16: 16 | I16: 35 | J16: 35 | K16: 204.75 | L16: =IF($B16="","",IFERROR(INDEX('Code Mapping'!$D$5:$D$1753,MATCH($B16,'Code Mapping'!$A$5:$A$1753,0)),"Unmapped")) -> Qatar Airways | M16: =IF($B16="","",IFERROR(INDEX('Code Mapping'!$E$5:$E$1753,MATCH($B16,'Code Mapping'!$A$5:$A$1753,0)),"Unmapped")) -> Corporate discount | N16: =IF($F16="","",$F16) -> InflataPark
A17: 8056 | B17: INFQFD | C17: Qatar Foundation 15% Discount | E17: 91 | F17: InflataPark | G17: 2026-W37 | H17: 2 | I17: 5 | J17: 5 | K17: 36.75 | L17: =IF($B17="","",IFERROR(INDEX('Code Mapping'!$D$5:$D$1753,MATCH($B17,'Code Mapping'!$A$5:$A$1753,0)),"Unmapped")) -> Qatar Foundation | M17: =IF($B17="","",IFERROR(INDEX('Code Mapping'!$E$5:$E$1753,MATCH($B17,'Code Mapping'!$A$5:$A$1753,0)),"Unmapped")) -> Corporate discount | N17: =IF($F17="","",$F17) -> InflataPark
A18: 8057 | B18: INFQIAD | C18: Qatar Investment Authority 15% Discount | E18: 91 | F18: InflataPark | G18: 2026-W37 | H18: 2 | I18: 7 | J18: 7 | K18: 47.25 | L18: =IF($B18="","",IFERROR(INDEX('Code Mapping'!$D$5:$D$1753,MATCH($B18,'Code Mapping'!$A$5:$A$1753,0)),"Unmapped")) -> Qatar Investment Authority | M18: =IF($B18="","",IFERROR(INDEX('Code Mapping'!$E$5:$E$1753,MATCH($B18,'Code Mapping'!$A$5:$A$1753,0)),"Unmapped")) -> Corporate discount | N18: =IF($F18="","",$F18) -> InflataPark
A19: 8326 | B19: INFUPBOGO2 | D19: E3 | E19: 91 | F19: InflataPark | G19: 2026-W37 | H19: 7 | I19: 7 | J19: 7 | K19: 1393 | L19: =IF($B19="","",IFERROR(INDEX('Code Mapping'!$D$5:$D$1753,MATCH($B19,'Code Mapping'!$A$5:$A$1753,0)),"Unmapped")) -> Urban Point | M19: =IF($B19="","",IFERROR(INDEX('Code Mapping'!$E$5:$E$1753,MATCH($B19,'Code Mapping'!$A$5:$A$1753,0)),"Unmapped")) -> Aggregator BOGO | N19: =IF($F19="","",$F19) -> InflataPark
A20: 8255 | B20: karak100 | D20: E3 | E20: 133 | F20: Urban Arena | G20: 2026-W37 | H20: 1 | I20: 3 | J20: 3 | K20: 15 | L20: =IF($B20="","",IFERROR(INDEX('Code Mapping'!$D$5:$D$1753,MATCH($B20,'Code Mapping'!$A$5:$A$1753,0)),"Unmapped")) -> Internal / promotion | M20: =IF($B20="","",IFERROR(INDEX('Code Mapping'!$E$5:$E$1753,MATCH($B20,'Code Mapping'!$A$5:$A$1753,0)),"Unmapped")) -> Internal / promotion | N20: =IF($F20="","",$F20) -> Urban Arena
A21: 8335 | B21: KCDIMTIYAZAT15 | C21: Imtiyazat 15% Discount | D21: E3 | E21: 94 | F21: Kids City Driving School | G21: 2026-W37 | H21: 22 | I21: 96 | J21: 96 | K21: 660.75 | L21: =IF($B21="","",IFERROR(INDEX('Code Mapping'!$D$5:$D$1753,MATCH($B21,'Code Mapping'!$A$5:$A$1753,0)),"Unmapped")) -> Imtyazat | M21: =IF($B21="","",IFERROR(INDEX('Code Mapping'!$E$5:$E$1753,MATCH($B21,'Code Mapping'!$A$5:$A$1753,0)),"Unmapped")) -> Corporate discount | N21: =IF($F21="","",$F21) -> Kids City Driving School
A22: 8338 | B22: KCDQAIRWAYS15 | C22: Qatar Airways 15% Discount | D22: E3 | E22: 94 | F22: Kids City Driving School | G22: 2026-W37 | H22: 2 | I22: 9 | J22: 9 | K22: 69.75 | L22: =IF($B22="","",IFERROR(INDEX('Code Mapping'!$D$5:$D$1753,MATCH($B22,'Code Mapping'!$A$5:$A$1753,0)),"Unmapped")) -> Qatar Airways | M22: =IF($B22="","",IFERROR(INDEX('Code Mapping'!$E$5:$E$1753,MATCH($B22,'Code Mapping'!$A$5:$A$1753,0)),"Unmapped")) -> Corporate discount | N22: =IF($F22="","",$F22) -> Kids City Driving School
A23: 8340 | B23: KCDQIA15 | C23: Qatar Investment Authority 15% Discount | D23: E3 | E23: 94 | F23: Kids City Driving School | G23: 2026-W37 | H23: 10 | I23: 42 | J23: 42 | K23: 311.25 | L23: =IF($B23="","",IFERROR(INDEX('Code Mapping'!$D$5:$D$1753,MATCH($B23,'Code Mapping'!$A$5:$A$1753,0)),"Unmapped")) -> Qatar Investment Authority | M23: =IF($B23="","",IFERROR(INDEX('Code Mapping'!$E$5:$E$1753,MATCH($B23,'Code Mapping'!$A$5:$A$1753,0)),"Unmapped")) -> Corporate discount | N23: =IF($F23="","",$F23) -> Kids City Driving School
A24: 8345 | B24: KDSBOGOE | D24: E3 | E24: 94 | F24: Kids City Driving School | G24: 2026-W37 | H24: 1 | I24: 1 | J24: 1 | K24: 199 | L24: =IF($B24="","",IFERROR(INDEX('Code Mapping'!$D$5:$D$1753,MATCH($B24,'Code Mapping'!$A$5:$A$1753,0)),"Unmapped")) -> Entertainer | M24: =IF($B24="","",IFERROR(INDEX('Code Mapping'!$E$5:$E$1753,MATCH($B24,'Code Mapping'!$A$5:$A$1753,0)),"Unmapped")) -> Aggregator BOGO | N24: =IF($F24="","",$F24) -> Kids City Driving School
A25: 8347 | B25: KDSBOGOM | D25: E3 | E25: 94 | F25: Kids City Driving School | G25: 2026-W37 | H25: 9 | I25: 9 | J25: 9 | K25: 1791 | L25: =IF($B25="","",IFERROR(INDEX('Code Mapping'!$D$5:$D$1753,MATCH($B25,'Code Mapping'!$A$5:$A$1753,0)),"Unmapped")) -> My Book | M25: =IF($B25="","",IFERROR(INDEX('Code Mapping'!$E$5:$E$1753,MATCH($B25,'Code Mapping'!$A$5:$A$1753,0)),"Unmapped")) -> Aggregator BOGO | N25: =IF($F25="","",$F25) -> Kids City Driving School
A26: 8346 | B26: KDSBOGOU | D26: E3 | E26: 94 | F26: Kids City Driving School | G26: 2026-W37 | H26: 1 | I26: 1 | J26: 1 | K26: 199 | L26: =IF($B26="","",IFERROR(INDEX('Code Mapping'!$D$5:$D$1753,MATCH($B26,'Code Mapping'!$A$5:$A$1753,0)),"Unmapped")) -> Urban Point | M26: =IF($B26="","",IFERROR(INDEX('Code Mapping'!$E$5:$E$1753,MATCH($B26,'Code Mapping'!$A$5:$A$1753,0)),"Unmapped")) -> Aggregator BOGO | N26: =IF($F26="","",$F26) -> Kids City Driving School
A27: 8314 | B27: loyaltyinf | D27: E3 | E27: 91 | F27: InflataPark | G27: 2026-W37 | H27: 1 | I27: 1 | J27: 1 | K27: 45 | L27: =IF($B27="","",IFERROR(INDEX('Code Mapping'!$D$5:$D$1753,MATCH($B27,'Code Mapping'!$A$5:$A$1753,0)),"Unmapped")) -> Internal / promotion | M27: =IF($B27="","",IFERROR(INDEX('Code Mapping'!$E$5:$E$1753,MATCH($B27,'Code Mapping'!$A$5:$A$1753,0)),"Unmapped")) -> Internal / promotion | N27: =IF($F27="","",$F27) -> InflataPark
A28: 8322 | B28: loyaltykds | C28: loyalty pass free city pass | D28: E3 | E28: 94 | F28: Kids City Driving School | G28: 2026-W37 | H28: 7 | I28: 7 | J28: 7 | K28: 315 | L28: =IF($B28="","",IFERROR(INDEX('Code Mapping'!$D$5:$D$1753,MATCH($B28,'Code Mapping'!$A$5:$A$1753,0)),"Unmapped")) -> Internal / promotion | M28: =IF($B28="","",IFERROR(INDEX('Code Mapping'!$E$5:$E$1753,MATCH($B28,'Code Mapping'!$A$5:$A$1753,0)),"Unmapped")) -> Internal / promotion | N28: =IF($F28="","",$F28) -> Kids City Driving School
A29: 6827 | B29: MYBVD | E29: 61 | F29: Crayons & Bricks Vendome | G29: 2026-W37 | H29: 2 | I29: 2 | J29: 2 | K29: 200 | L29: =IF($B29="","",IFERROR(INDEX('Code Mapping'!$D$5:$D$1753,MATCH($B29,'Code Mapping'!$A$5:$A$1753,0)),"Unmapped")) -> My Book | M29: =IF($B29="","",IFERROR(INDEX('Code Mapping'!$E$5:$E$1753,MATCH($B29,'Code Mapping'!$A$5:$A$1753,0)),"Unmapped")) -> Aggregator BOGO | N29: =IF($F29="","",$F29) -> Crayons & Bricks Vendome
A30: 8106 | B30: R1Z6L | C30: Qatar Foundation 15% Discount | E30: 61 | F30: Crayons & Bricks Vendome | G30: 2026-W37 | H30: 1 | I30: 6 | J30: 6 | K30: 31.5 | L30: =IF($B30="","",IFERROR(INDEX('Code Mapping'!$D$5:$D$1753,MATCH($B30,'Code Mapping'!$A$5:$A$1753,0)),"Unmapped")) -> Qatar Foundation | M30: =IF($B30="","",IFERROR(INDEX('Code Mapping'!$E$5:$E$1753,MATCH($B30,'Code Mapping'!$A$5:$A$1753,0)),"Unmapped")) -> Corporate discount | N30: =IF($F30="","",$F30) -> Crayons & Bricks Vendome
A31: 8075 | B31: RENA | C31: Imtyazat 15% Discount | E31: 133 | F31: Urban Arena | G31: 2026-W37 | H31: 5 | I31: 25 | J31: 25 | K31: 162.75 | L31: =IF($B31="","",IFERROR(INDEX('Code Mapping'!$D$5:$D$1753,MATCH($B31,'Code Mapping'!$A$5:$A$1753,0)),"Unmapped")) -> Imtyazat | M31: =IF($B31="","",IFERROR(INDEX('Code Mapping'!$E$5:$E$1753,MATCH($B31,'Code Mapping'!$A$5:$A$1753,0)),"Unmapped")) -> Corporate discount | N31: =IF($F31="","",$F31) -> Urban Arena
A32: 8093 | B32: UBOFFM | C32: My Book BOGO | E32: 133 | F32: Urban Arena | G32: 2026-W37 | H32: 3 | I32: 3 | J32: 3 | K32: 597 | L32: =IF($B32="","",IFERROR(INDEX('Code Mapping'!$D$5:$D$1753,MATCH($B32,'Code Mapping'!$A$5:$A$1753,0)),"Unmapped")) -> My Book | M32: =IF($B32="","",IFERROR(INDEX('Code Mapping'!$E$5:$E$1753,MATCH($B32,'Code Mapping'!$A$5:$A$1753,0)),"Unmapped")) -> Aggregator BOGO | N32: =IF($F32="","",$F32) -> Urban Arena
A33: 8078 | B33: UENA | C33: Qatar Airways 15% Discount | E33: 133 | F33: Urban Arena | G33: 2026-W37 | H33: 19 | I33: 58 | J33: 58 | K33: 397.5 | L33: =IF($B33="","",IFERROR(INDEX('Code Mapping'!$D$5:$D$1753,MATCH($B33,'Code Mapping'!$A$5:$A$1753,0)),"Unmapped")) -> Qatar Airways | M33: =IF($B33="","",IFERROR(INDEX('Code Mapping'!$E$5:$E$1753,MATCH($B33,'Code Mapping'!$A$5:$A$1753,0)),"Unmapped")) -> Corporate discount | N33: =IF($F33="","",$F33) -> Urban Arena
A34: 8094 | B34: UGBOGU | C34: Urban Point BOGO | E34: 133 | F34: Urban Arena | G34: 2026-W37 | H34: 7 | I34: 7 | J34: 7 | K34: 1393 | L34: =IF($B34="","",IFERROR(INDEX('Code Mapping'!$D$5:$D$1753,MATCH($B34,'Code Mapping'!$A$5:$A$1753,0)),"Unmapped")) -> Urban Point | M34: =IF($B34="","",IFERROR(INDEX('Code Mapping'!$E$5:$E$1753,MATCH($B34,'Code Mapping'!$A$5:$A$1753,0)),"Unmapped")) -> Aggregator BOGO | N34: =IF($F34="","",$F34) -> Urban Arena
A35: 8076 | B35: UNAR | C35: Public Health Sector Employees 20% Discount | E35: 133 | F35: Urban Arena | G35: 2026-W37 | H35: 12 | I35: 48 | J35: 48 | K35: 478 | L35: =IF($B35="","",IFERROR(INDEX('Code Mapping'!$D$5:$D$1753,MATCH($B35,'Code Mapping'!$A$5:$A$1753,0)),"Unmapped")) -> Public Health Sector (Sogha) | M35: =IF($B35="","",IFERROR(INDEX('Code Mapping'!$E$5:$E$1753,MATCH($B35,'Code Mapping'!$A$5:$A$1753,0)),"Unmapped")) -> Corporate discount | N35: =IF($F35="","",$F35) -> Urban Arena
A36: 8069 | B36: URBN | C36: Al Jazeera Imityazat 15% Discount | E36: 133 | F36: Urban Arena | G36: 2026-W37 | H36: 3 | I36: 8 | J36: 8 | K36: 96 | L36: =IF($B36="","",IFERROR(INDEX('Code Mapping'!$D$5:$D$1753,MATCH($B36,'Code Mapping'!$A$5:$A$1753,0)),"Unmapped")) -> Al Jazeera Imtiyazat | M36: =IF($B36="","",IFERROR(INDEX('Code Mapping'!$E$5:$E$1753,MATCH($B36,'Code Mapping'!$A$5:$A$1753,0)),"Unmapped")) -> Corporate discount | N36: =IF($F36="","",$F36) -> Urban Arena
L37: =IF($B37="","",IFERROR(INDEX('Code Mapping'!$D$5:$D$1753,MATCH($B37,'Code Mapping'!$A$5:$A$1753,0)),"Unmapped")) | M37: =IF($B37="","",IFERROR(INDEX('Code Mapping'!$E$5:$E$1753,MATCH($B37,'Code Mapping'!$A$5:$A$1753,0)),"Unmapped")) | N37: =IF($F37="","",$F37)
L38: =IF($B38="","",IFERROR(INDEX('Code Mapping'!$D$5:$D$1753,MATCH($B38,'Code Mapping'!$A$5:$A$1753,0)),"Unmapped")) | M38: =IF($B38="","",IFERROR(INDEX('Code Mapping'!$E$5:$E$1753,MATCH($B38,'Code Mapping'!$A$5:$A$1753,0)),"Unmapped")) | N38: =IF($F38="","",$F38)
L39: =IF($B39="","",IFERROR(INDEX('Code Mapping'!$D$5:$D$1753,MATCH($B39,'Code Mapping'!$A$5:$A$1753,0)),"Unmapped")) | M39: =IF($B39="","",IFERROR(INDEX('Code Mapping'!$E$5:$E$1753,MATCH($B39,'Code Mapping'!$A$5:$A$1753,0)),"Unmapped")) | N39: =IF($F39="","",$F39)
L40: =IF($B40="","",IFERROR(INDEX('Code Mapping'!$D$5:$D$1753,MATCH($B40,'Code Mapping'!$A$5:$A$1753,0)),"Unmapped")) | M40: =IF($B40="","",IFERROR(INDEX('Code Mapping'!$E$5:$E$1753,MATCH($B40,'Code Mapping'!$A$5:$A$1753,0)),"Unmapped")) | N40: =IF($F40="","",$F40)
L41: =IF($B41="","",IFERROR(INDEX('Code Mapping'!$D$5:$D$1753,MATCH($B41,'Code Mapping'!$A$5:$A$1753,0)),"Unmapped")) | M41: =IF($B41="","",IFERROR(INDEX('Code Mapping'!$E$5:$E$1753,MATCH($B41,'Code Mapping'!$A$5:$A$1753,0)),"Unmapped")) | N41: =IF($F41="","",$F41)
L42: =IF($B42="","",IFERROR(INDEX('Code Mapping'!$D$5:$D$1753,MATCH($B42,'Code Mapping'!$A$5:$A$1753,0)),"Unmapped")) | M42: =IF($B42="","",IFERROR(INDEX('Code Mapping'!$E$5:$E$1753,MATCH($B42,'Code Mapping'!$A$5:$A$1753,0)),"Unmapped")) | N42: =IF($F42="","",$F42)
L43: =IF($B43="","",IFERROR(INDEX('Code Mapping'!$D$5:$D$1753,MATCH($B43,'Code Mapping'!$A$5:$A$1753,0)),"Unmapped")) | M43: =IF($B43="","",IFERROR(INDEX('Code Mapping'!$E$5:$E$1753,MATCH($B43,'Code Mapping'!$A$5:$A$1753,0)),"Unmapped")) | N43: =IF($F43="","",$F43)
L44: =IF($B44="","",IFERROR(INDEX('Code Mapping'!$D$5:$D$1753,MATCH($B44,'Code Mapping'!$A$5:$A$1753,0)),"Unmapped")) | M44: =IF($B44="","",IFERROR(INDEX('Code Mapping'!$E$5:$E$1753,MATCH($B44,'Code Mapping'!$A$5:$A$1753,0)),"Unmapped")) | N44: =IF($F44="","",$F44)
L45: =IF($B45="","",IFERROR(INDEX('Code Mapping'!$D$5:$D$1753,MATCH($B45,'Code Mapping'!$A$5:$A$1753,0)),"Unmapped")) | M45: =IF($B45="","",IFERROR(INDEX('Code Mapping'!$E$5:$E$1753,MATCH($B45,'Code Mapping'!$A$5:$A$1753,0)),"Unmapped")) | N45: =IF($F45="","",$F45)
L46: =IF($B46="","",IFERROR(INDEX('Code Mapping'!$D$5:$D$1753,MATCH($B46,'Code Mapping'!$A$5:$A$1753,0)),"Unmapped")) | M46: =IF($B46="","",IFERROR(INDEX('Code Mapping'!$E$5:$E$1753,MATCH($B46,'Code Mapping'!$A$5:$A$1753,0)),"Unmapped")) | N46: =IF($F46="","",$F46)
L47: =IF($B47="","",IFERROR(INDEX('Code Mapping'!$D$5:$D$1753,MATCH($B47,'Code Mapping'!$A$5:$A$1753,0)),"Unmapped")) | M47: =IF($B47="","",IFERROR(INDEX('Code Mapping'!$E$5:$E$1753,MATCH($B47,'Code Mapping'!$A$5:$A$1753,0)),"Unmapped")) | N47: =IF($F47="","",$F47)
L48: =IF($B48="","",IFERROR(INDEX('Code Mapping'!$D$5:$D$1753,MATCH($B48,'Code Mapping'!$A$5:$A$1753,0)),"Unmapped")) | M48: =IF($B48="","",IFERROR(INDEX('Code Mapping'!$E$5:$E$1753,MATCH($B48,'Code Mapping'!$A$5:$A$1753,0)),"Unmapped")) | N48: =IF($F48="","",$F48)
... L636: =IF($B636="","",IFERROR(INDEX('Code Mapping'!$D$5:$D$1753,MATCH($B636,'Code Mapping'!$A$5:$A$1753,0)),"Unmapped")) | M636: =IF($B636="","",IFERROR(INDEX('Code Mapping'!$E$5:$E$1753,MATCH($B636,'Code Mapping'!$A$5:$A$1753,0)),"Unmapped")) | N636: =IF($F636="","",$F636)

Sheet Month Data
A1: Month Data: raw export from BookingQube plus lookup columns
A2: Columns A to K are pasted from the system export (event-wise). L and M look up Code Mapping; N repeats the venue from the export. To refresh, paste the new export over A5 downward.
A4: promocode_id | B4: promocode | C4: description | D4: company_name | E4: event_id | F4: event_title | G4: period_month | H4: times_used | I4: booking_lines | J4: tickets | K4: total_discount | L4: Partner | M4: Category | N4: Venue
A5: 8070 | B5: ARNA | C5: Aspire 15% Discount | E5: 133 | F5: Urban Arena | G5: 2026-09 | H5: 4 | I5: 21 | J5: 21 | K5: 147.75 | L5: =IF($B5="","",IFERROR(INDEX('Code Mapping'!$D$5:$D$1753,MATCH($B5,'Code Mapping'!$A$5:$A$1753,0)),"Unmapped")) -> Aspire | M5: =IF($B5="","",IFERROR(INDEX('Code Mapping'!$E$5:$E$1753,MATCH($B5,'Code Mapping'!$A$5:$A$1753,0)),"Unmapped")) -> Corporate discount | N5: =IF($F5="","",$F5) -> Urban Arena
A6: 8079 | B6: ARNB | C6: Qatar Foundation 15% Discount | D6: E3 | E6: 133 | F6: Urban Arena | G6: 2026-09 | H6: 27 | I6: 113 | J6: 113 | K6: 947.7 | L6: =IF($B6="","",IFERROR(INDEX('Code Mapping'!$D$5:$D$1753,MATCH($B6,'Code Mapping'!$A$5:$A$1753,0)),"Unmapped")) -> Qatar Foundation | M6: =IF($B6="","",IFERROR(INDEX('Code Mapping'!$E$5:$E$1753,MATCH($B6,'Code Mapping'!$A$5:$A$1753,0)),"Unmapped")) -> Corporate discount | N6: =IF($F6="","",$F6) -> Urban Arena
A7: 8077 | B7: BRNA | C7: QIB 15% Discount | E7: 133 | F7: Urban Arena | G7: 2026-09 | H7: 5 | I7: 21 | J7: 21 | K7: 174 | L7: =IF($B7="","",IFERROR(INDEX('Code Mapping'!$D$5:$D$1753,MATCH($B7,'Code Mapping'!$A$5:$A$1753,0)),"Unmapped")) -> QIB | M7: =IF($B7="","",IFERROR(INDEX('Code Mapping'!$E$5:$E$1753,MATCH($B7,'Code Mapping'!$A$5:$A$1753,0)),"Unmapped")) -> Corporate discount | N7: =IF($F7="","",$F7) -> Urban Arena
A8: 8038 | B8: cafe50 | C8: 50% off on cafe | E8: 133 | F8: Urban Arena | G8: 2026-09 | H8: 63 | I8: 78 | J8: 78 | K8: 443.5 | L8: =IF($B8="","",IFERROR(INDEX('Code Mapping'!$D$5:$D$1753,MATCH($B8,'Code Mapping'!$A$5:$A$1753,0)),"Unmapped")) -> Internal / promotion | M8: =IF($B8="","",IFERROR(INDEX('Code Mapping'!$E$5:$E$1753,MATCH($B8,'Code Mapping'!$A$5:$A$1753,0)),"Unmapped")) -> Internal / promotion | N8: =IF($F8="","",$F8) -> Urban Arena
A9: 8095 | B9: CBOGOE | C9: Entertainer BOGO | E9: 61 | F9: Crayons & Bricks Vendome | G9: 2026-09 | H9: 12 | I9: 12 | J9: 12 | K9: 1200 | L9: =IF($B9="","",IFERROR(INDEX('Code Mapping'!$D$5:$D$1753,MATCH($B9,'Code Mapping'!$A$5:$A$1753,0)),"Unmapped")) -> Entertainer | M9: =IF($B9="","",IFERROR(INDEX('Code Mapping'!$E$5:$E$1753,MATCH($B9,'Code Mapping'!$A$5:$A$1753,0)),"Unmapped")) -> Aggregator BOGO | N9: =IF($F9="","",$F9) -> Crayons & Bricks Vendome
A10: 8097 | B10: CGBOGU | C10: Urban Point BOGO | E10: 61 | F10: Crayons & Bricks Vendome | G10: 2026-09 | H10: 17 | I10: 17 | J10: 17 | K10: 1700 | L10: =IF($B10="","",IFERROR(INDEX('Code Mapping'!$D$5:$D$1753,MATCH($B10,'Code Mapping'!$A$5:$A$1753,0)),"Unmapped")) -> Urban Point | M10: =IF($B10="","",IFERROR(INDEX('Code Mapping'!$E$5:$E$1753,MATCH($B10,'Code Mapping'!$A$5:$A$1753,0)),"Unmapped")) -> Aggregator BOGO | N10: =IF($F10="","",$F10) -> Crayons & Bricks Vendome
A11: 8096 | B11: CGOBOQ | C11: Qatar Living BOGO | E11: 61 | F11: Crayons & Bricks Vendome | G11: 2026-09 | H11: 1 | I11: 1 | J11: 1 | K11: 100 | L11: =IF($B11="","",IFERROR(INDEX('Code Mapping'!$D$5:$D$1753,MATCH($B11,'Code Mapping'!$A$5:$A$1753,0)),"Unmapped")) -> Qatar Living Deals | M11: =IF($B11="","",IFERROR(INDEX('Code Mapping'!$E$5:$E$1753,MATCH($B11,'Code Mapping'!$A$5:$A$1753,0)),"Unmapped")) -> Aggregator BOGO | N11: =IF($F11="","",$F11) -> Crayons & Bricks Vendome
A12: 8318 | B12: dmqnb15 | D12: QNB | E12: 133 | F12: Urban Arena | G12: 2026-09 | H12: 6 | I12: 18 | J12: 18 | K12: 151.5 | L12: =IF($B12="","",IFERROR(INDEX('Code Mapping'!$D$5:$D$1753,MATCH($B12,'Code Mapping'!$A$5:$A$1753,0)),"Unmapped")) -> QNB Rewards | M12: =IF($B12="","",IFERROR(INDEX('Code Mapping'!$E$5:$E$1753,MATCH($B12,'Code Mapping'!$A$5:$A$1753,0)),"Unmapped")) -> Corporate discount | N12: =IF($F12="","",$F12) -> Urban Arena
A13: 8046 | B13: INFAJID | C13: Al Jazeera Imityazat 15% Discount | E13: 91 | F13: InflataPark | G13: 2026-09 | H13: 2 | I13: 2 | J13: 2 | K13: 22.5 | L13: =IF($B13="","",IFERROR(INDEX('Code Mapping'!$D$5:$D$1753,MATCH($B13,'Code Mapping'!$A$5:$A$1753,0)),"Unmapped")) -> Al Jazeera Imtiyazat | M13: =IF($B13="","",IFERROR(INDEX('Code Mapping'!$E$5:$E$1753,MATCH($B13,'Code Mapping'!$A$5:$A$1753,0)),"Unmapped")) -> Corporate discount | N13: =IF($F13="","",$F13) -> InflataPark
A14: 8325 | B14: INFAMBBOGO2 | D14: E3 | E14: 91 | F14: InflataPark | G14: 2026-09 | H14: 1 | I14: 1 | J14: 1 | K14: 199 | L14: =IF($B14="","",IFERROR(INDEX('Code Mapping'!$D$5:$D$1753,MATCH($B14,'Code Mapping'!$A$5:$A$1753,0)),"Unmapped")) -> My Book | M14: =IF($B14="","",IFERROR(INDEX('Code Mapping'!$E$5:$E$1753,MATCH($B14,'Code Mapping'!$A$5:$A$1753,0)),"Unmapped")) -> Aggregator BOGO | N14: =IF($F14="","",$F14) -> InflataPark
A15: 8047 | B15: INFASPID | C15: Aspire 15% Discount | E15: 91 | F15: InflataPark | G15: 2026-09 | H15: 1 | I15: 2 | J15: 2 | K15: 15 | L15: =IF($B15="","",IFERROR(INDEX('Code Mapping'!$D$5:$D$1753,MATCH($B15,'Code Mapping'!$A$5:$A$1753,0)),"Unmapped")) -> Aspire | M15: =IF($B15="","",IFERROR(INDEX('Code Mapping'!$E$5:$E$1753,MATCH($B15,'Code Mapping'!$A$5:$A$1753,0)),"Unmapped")) -> Corporate discount | N15: =IF($F15="","",$F15) -> InflataPark
A16: 8048 | B16: INFBEIND | C16: Bein 15% Discount | E16: 91 | F16: InflataPark | G16: 2026-09 | H16: 1 | I16: 6 | J16: 6 | K16: 52.5 | L16: =IF($B16="","",IFERROR(INDEX('Code Mapping'!$D$5:$D$1753,MATCH($B16,'Code Mapping'!$A$5:$A$1753,0)),"Unmapped")) -> Bein | M16: =IF($B16="","",IFERROR(INDEX('Code Mapping'!$E$5:$E$1753,MATCH($B16,'Code Mapping'!$A$5:$A$1753,0)),"Unmapped")) -> Corporate discount | N16: =IF($F16="","",$F16) -> InflataPark
A17: 8324 | B17: INFENTBOGO2 | D17: E3 | E17: 91 | F17: InflataPark | G17: 2026-09 | H17: 6 | I17: 6 | J17: 6 | K17: 1194 | L17: =IF($B17="","",IFERROR(INDEX('Code Mapping'!$D$5:$D$1753,MATCH($B17,'Code Mapping'!$A$5:$A$1753,0)),"Unmapped")) -> Entertainer | M17: =IF($B17="","",IFERROR(INDEX('Code Mapping'!$E$5:$E$1753,MATCH($B17,'Code Mapping'!$A$5:$A$1753,0)),"Unmapped")) -> Aggregator BOGO | N17: =IF($F17="","",$F17) -> InflataPark
A18: 8052 | B18: INFIMTYD | C18: Imtyazat 15% Discount | D18: E3 | E18: 91 | F18: InflataPark | G18: 2026-09 | H18: 27 | I18: 110 | J18: 110 | K18: 859.5 | L18: =IF($B18="","",IFERROR(INDEX('Code Mapping'!$D$5:$D$1753,MATCH($B18,'Code Mapping'!$A$5:$A$1753,0)),"Unmapped")) -> Imtyazat | M18: =IF($B18="","",IFERROR(INDEX('Code Mapping'!$E$5:$E$1753,MATCH($B18,'Code Mapping'!$A$5:$A$1753,0)),"Unmapped")) -> Corporate discount | N18: =IF($F18="","",$F18) -> InflataPark
A19: 8053 | B19: INFPHSED | C19: Public Health Sector Employees 20% Discount | E19: 91 | F19: InflataPark | G19: 2026-09 | H19: 21 | I19: 50 | J19: 50 | K19: 466 | L19: =IF($B19="","",IFERROR(INDEX('Code Mapping'!$D$5:$D$1753,MATCH($B19,'Code Mapping'!$A$5:$A$1753,0)),"Unmapped")) -> Public Health Sector (Sogha) | M19: =IF($B19="","",IFERROR(INDEX('Code Mapping'!$E$5:$E$1753,MATCH($B19,'Code Mapping'!$A$5:$A$1753,0)),"Unmapped")) -> Corporate discount | N19: =IF($F19="","",$F19) -> InflataPark
A20: 8055 | B20: INFQAD | C20: Qatar Airways 15% Discount | E20: 91 | F20: InflataPark | G20: 2026-09 | H20: 32 | I20: 82 | J20: 82 | K20: 523.5 | L20: =IF($B20="","",IFERROR(INDEX('Code Mapping'!$D$5:$D$1753,MATCH($B20,'Code Mapping'!$A$5:$A$1753,0)),"Unmapped")) -> Qatar Airways | M20: =IF($B20="","",IFERROR(INDEX('Code Mapping'!$E$5:$E$1753,MATCH($B20,'Code Mapping'!$A$5:$A$1753,0)),"Unmapped")) -> Corporate discount | N20: =IF($F20="","",$F20) -> InflataPark
A21: 8056 | B21: INFQFD | C21: Qatar Foundation 15% Discount | E21: 91 | F21: InflataPark | G21: 2026-09 | H21: 5 | I21: 11 | J21: 11 | K21: 71.25 | L21: =IF($B21="","",IFERROR(INDEX('Code Mapping'!$D$5:$D$1753,MATCH($B21,'Code Mapping'!$A$5:$A$1753,0)),"Unmapped")) -> Qatar Foundation | M21: =IF($B21="","",IFERROR(INDEX('Code Mapping'!$E$5:$E$1753,MATCH($B21,'Code Mapping'!$A$5:$A$1753,0)),"Unmapped")) -> Corporate discount | N21: =IF($F21="","",$F21) -> InflataPark
A22: 8057 | B22: INFQIAD | C22: Qatar Investment Authority 15% Discount | E22: 91 | F22: InflataPark | G22: 2026-09 | H22: 4 | I22: 12 | J22: 12 | K22: 88.5 | L22: =IF($B22="","",IFERROR(INDEX('Code Mapping'!$D$5:$D$1753,MATCH($B22,'Code Mapping'!$A$5:$A$1753,0)),"Unmapped")) -> Qatar Investment Authority | M22: =IF($B22="","",IFERROR(INDEX('Code Mapping'!$E$5:$E$1753,MATCH($B22,'Code Mapping'!$A$5:$A$1753,0)),"Unmapped")) -> Corporate discount | N22: =IF($F22="","",$F22) -> InflataPark
A23: 8326 | B23: INFUPBOGO2 | D23: E3 | E23: 91 | F23: InflataPark | G23: 2026-09 | H23: 12 | I23: 12 | J23: 12 | K23: 2388 | L23: =IF($B23="","",IFERROR(INDEX('Code Mapping'!$D$5:$D$1753,MATCH($B23,'Code Mapping'!$A$5:$A$1753,0)),"Unmapped")) -> Urban Point | M23: =IF($B23="","",IFERROR(INDEX('Code Mapping'!$E$5:$E$1753,MATCH($B23,'Code Mapping'!$A$5:$A$1753,0)),"Unmapped")) -> Aggregator BOGO | N23: =IF($F23="","",$F23) -> InflataPark
A24: 8105 | B24: K9P3X | C24: Qatar Airways 15% Discount | E24: 61 | F24: Crayons & Bricks Vendome | G24: 2026-09 | H24: 1 | I24: 1 | J24: 1 | K24: 5.25 | L24: =IF($B24="","",IFERROR(INDEX('Code Mapping'!$D$5:$D$1753,MATCH($B24,'Code Mapping'!$A$5:$A$1753,0)),"Unmapped")) -> Qatar Airways | M24: =IF($B24="","",IFERROR(INDEX('Code Mapping'!$E$5:$E$1753,MATCH($B24,'Code Mapping'!$A$5:$A$1753,0)),"Unmapped")) -> Corporate discount | N24: =IF($F24="","",$F24) -> Crayons & Bricks Vendome
A25: 8255 | B25: karak100 | D25: E3 | E25: 133 | F25: Urban Arena | G25: 2026-09 | H25: 1 | I25: 3 | J25: 3 | K25: 15 | L25: =IF($B25="","",IFERROR(INDEX('Code Mapping'!$D$5:$D$1753,MATCH($B25,'Code Mapping'!$A$5:$A$1753,0)),"Unmapped")) -> Internal / promotion | M25: =IF($B25="","",IFERROR(INDEX('Code Mapping'!$E$5:$E$1753,MATCH($B25,'Code Mapping'!$A$5:$A$1753,0)),"Unmapped")) -> Internal / promotion | N25: =IF($F25="","",$F25) -> Urban Arena
A26: 8335 | B26: KCDIMTIYAZAT15 | C26: Imtiyazat 15% Discount | D26: E3 | E26: 94 | F26: Kids City Driving School | G26: 2026-09 | H26: 37 | I26: 160 | J26: 160 | K26: 1137.75 | L26: =IF($B26="","",IFERROR(INDEX('Code Mapping'!$D$5:$D$1753,MATCH($B26,'Code Mapping'!$A$5:$A$1753,0)),"Unmapped")) -> Imtyazat | M26: =IF($B26="","",IFERROR(INDEX('Code Mapping'!$E$5:$E$1753,MATCH($B26,'Code Mapping'!$A$5:$A$1753,0)),"Unmapped")) -> Corporate discount | N26: =IF($F26="","",$F26) -> Kids City Driving School
A27: 8338 | B27: KCDQAIRWAYS15 | C27: Qatar Airways 15% Discount | D27: E3 | E27: 94 | F27: Kids City Driving School | G27: 2026-09 | H27: 2 | I27: 9 | J27: 9 | K27: 69.75 | L27: =IF($B27="","",IFERROR(INDEX('Code Mapping'!$D$5:$D$1753,MATCH($B27,'Code Mapping'!$A$5:$A$1753,0)),"Unmapped")) -> Qatar Airways | M27: =IF($B27="","",IFERROR(INDEX('Code Mapping'!$E$5:$E$1753,MATCH($B27,'Code Mapping'!$A$5:$A$1753,0)),"Unmapped")) -> Corporate discount | N27: =IF($F27="","",$F27) -> Kids City Driving School
A28: 8340 | B28: KCDQIA15 | C28: Qatar Investment Authority 15% Discount | D28: E3 | E28: 94 | F28: Kids City Driving School | G28: 2026-09 | H28: 16 | I28: 65 | J28: 65 | K28: 453 | L28: =IF($B28="","",IFERROR(INDEX('Code Mapping'!$D$5:$D$1753,MATCH($B28,'Code Mapping'!$A$5:$A$1753,0)),"Unmapped")) -> Qatar Investment Authority | M28: =IF($B28="","",IFERROR(INDEX('Code Mapping'!$E$5:$E$1753,MATCH($B28,'Code Mapping'!$A$5:$A$1753,0)),"Unmapped")) -> Corporate discount | N28: =IF($F28="","",$F28) -> Kids City Driving School
A29: 8345 | B29: KDSBOGOE | D29: E3 | E29: 94 | F29: Kids City Driving School | G29: 2026-09 | H29: 1 | I29: 1 | J29: 1 | K29: 199 | L29: =IF($B29="","",IFERROR(INDEX('Code Mapping'!$D$5:$D$1753,MATCH($B29,'Code Mapping'!$A$5:$A$1753,0)),"Unmapped")) -> Entertainer | M29: =IF($B29="","",IFERROR(INDEX('Code Mapping'!$E$5:$E$1753,MATCH($B29,'Code Mapping'!$A$5:$A$1753,0)),"Unmapped")) -> Aggregator BOGO | N29: =IF($F29="","",$F29) -> Kids City Driving School
A30: 8347 | B30: KDSBOGOM | D30: E3 | E30: 94 | F30: Kids City Driving School | G30: 2026-09 | H30: 11 | I30: 11 | J30: 11 | K30: 2189 | L30: =IF($B30="","",IFERROR(INDEX('Code Mapping'!$D$5:$D$1753,MATCH($B30,'Code Mapping'!$A$5:$A$1753,0)),"Unmapped")) -> My Book | M30: =IF($B30="","",IFERROR(INDEX('Code Mapping'!$E$5:$E$1753,MATCH($B30,'Code Mapping'!$A$5:$A$1753,0)),"Unmapped")) -> Aggregator BOGO | N30: =IF($F30="","",$F30) -> Kids City Driving School
A31: 8346 | B31: KDSBOGOU | D31: E3 | E31: 94 | F31: Kids City Driving School | G31: 2026-09 | H31: 1 | I31: 1 | J31: 1 | K31: 199 | L31: =IF($B31="","",IFERROR(INDEX('Code Mapping'!$D$5:$D$1753,MATCH($B31,'Code Mapping'!$A$5:$A$1753,0)),"Unmapped")) -> Urban Point | M31: =IF($B31="","",IFERROR(INDEX('Code Mapping'!$E$5:$E$1753,MATCH($B31,'Code Mapping'!$A$5:$A$1753,0)),"Unmapped")) -> Aggregator BOGO | N31: =IF($F31="","",$F31) -> Kids City Driving School
A32: 8313 | B32: loyalty | C32: Loyalty customer free rookie pass | D32: E3 | E32: 133 | F32: Urban Arena | G32: 2026-09 | H32: 1 | I32: 1 | J32: 1 | K32: 45 | L32: =IF($B32="","",IFERROR(INDEX('Code Mapping'!$D$5:$D$1753,MATCH($B32,'Code Mapping'!$A$5:$A$1753,0)),"Unmapped")) -> Internal / promotion | M32: =IF($B32="","",IFERROR(INDEX('Code Mapping'!$E$5:$E$1753,MATCH($B32,'Code Mapping'!$A$5:$A$1753,0)),"Unmapped")) -> Internal / promotion | N32: =IF($F32="","",$F32) -> Urban Arena
A33: 8314 | B33: loyaltyinf | D33: E3 | E33: 91 | F33: InflataPark | G33: 2026-09 | H33: 1 | I33: 1 | J33: 1 | K33: 45 | L33: =IF($B33="","",IFERROR(INDEX('Code Mapping'!$D$5:$D$1753,MATCH($B33,'Code Mapping'!$A$5:$A$1753,0)),"Unmapped")) -> Internal / promotion | M33: =IF($B33="","",IFERROR(INDEX('Code Mapping'!$E$5:$E$1753,MATCH($B33,'Code Mapping'!$A$5:$A$1753,0)),"Unmapped")) -> Internal / promotion | N33: =IF($F33="","",$F33) -> InflataPark
A34: 8322 | B34: loyaltykds | C34: loyalty pass free city pass | D34: E3 | E34: 94 | F34: Kids City Driving School | G34: 2026-09 | H34: 13 | I34: 13 | J34: 13 | K34: 585 | L34: =IF($B34="","",IFERROR(INDEX('Code Mapping'!$D$5:$D$1753,MATCH($B34,'Code Mapping'!$A$5:$A$1753,0)),"Unmapped")) -> Internal / promotion | M34: =IF($B34="","",IFERROR(INDEX('Code Mapping'!$E$5:$E$1753,MATCH($B34,'Code Mapping'!$A$5:$A$1753,0)),"Unmapped")) -> Internal / promotion | N34: =IF($F34="","",$F34) -> Kids City Driving School
A35: 6827 | B35: MYBVD | E35: 61 | F35: Crayons & Bricks Vendome | G35: 2026-09 | H35: 4 | I35: 4 | J35: 4 | K35: 400 | L35: =IF($B35="","",IFERROR(INDEX('Code Mapping'!$D$5:$D$1753,MATCH($B35,'Code Mapping'!$A$5:$A$1753,0)),"Unmapped")) -> My Book | M35: =IF($B35="","",IFERROR(INDEX('Code Mapping'!$E$5:$E$1753,MATCH($B35,'Code Mapping'!$A$5:$A$1753,0)),"Unmapped")) -> Aggregator BOGO | N35: =IF($F35="","",$F35) -> Crayons & Bricks Vendome
A36: 8106 | B36: R1Z6L | C36: Qatar Foundation 15% Discount | E36: 61 | F36: Crayons & Bricks Vendome | G36: 2026-09 | H36: 2 | I36: 10 | J36: 10 | K36: 52.5 | L36: =IF($B36="","",IFERROR(INDEX('Code Mapping'!$D$5:$D$1753,MATCH($B36,'Code Mapping'!$A$5:$A$1753,0)),"Unmapped")) -> Qatar Foundation | M36: =IF($B36="","",IFERROR(INDEX('Code Mapping'!$E$5:$E$1753,MATCH($B36,'Code Mapping'!$A$5:$A$1753,0)),"Unmapped")) -> Corporate discount | N36: =IF($F36="","",$F36) -> Crayons & Bricks Vendome
A37: 8075 | B37: RENA | C37: Imtyazat 15% Discount | E37: 133 | F37: Urban Arena | G37: 2026-09 | H37: 8 | I37: 35 | J37: 35 | K37: 224.25 | L37: =IF($B37="","",IFERROR(INDEX('Code Mapping'!$D$5:$D$1753,MATCH($B37,'Code Mapping'!$A$5:$A$1753,0)),"Unmapped")) -> Imtyazat | M37: =IF($B37="","",IFERROR(INDEX('Code Mapping'!$E$5:$E$1753,MATCH($B37,'Code Mapping'!$A$5:$A$1753,0)),"Unmapped")) -> Corporate discount | N37: =IF($F37="","",$F37) -> Urban Arena
A38: 8093 | B38: UBOFFM | C38: My Book BOGO | E38: 133 | F38: Urban Arena | G38: 2026-09 | H38: 9 | I38: 9 | J38: 9 | K38: 1791 | L38: =IF($B38="","",IFERROR(INDEX('Code Mapping'!$D$5:$D$1753,MATCH($B38,'Code Mapping'!$A$5:$A$1753,0)),"Unmapped")) -> My Book | M38: =IF($B38="","",IFERROR(INDEX('Code Mapping'!$E$5:$E$1753,MATCH($B38,'Code Mapping'!$A$5:$A$1753,0)),"Unmapped")) -> Aggregator BOGO | N38: =IF($F38="","",$F38) -> Urban Arena
A39: 8078 | B39: UENA | C39: Qatar Airways 15% Discount | E39: 133 | F39: Urban Arena | G39: 2026-09 | H39: 31 | I39: 113 | J39: 113 | K39: 856.5 | L39: =IF($B39="","",IFERROR(INDEX('Code Mapping'!$D$5:$D$1753,MATCH($B39,'Code Mapping'!$A$5:$A$1753,0)),"Unmapped")) -> Qatar Airways | M39: =IF($B39="","",IFERROR(INDEX('Code Mapping'!$E$5:$E$1753,MATCH($B39,'Code Mapping'!$A$5:$A$1753,0)),"Unmapped")) -> Corporate discount | N39: =IF($F39="","",$F39) -> Urban Arena
A40: 8094 | B40: UGBOGU | C40: Urban Point BOGO | E40: 133 | F40: Urban Arena | G40: 2026-09 | H40: 10 | I40: 10 | J40: 10 | K40: 1990 | L40: =IF($B40="","",IFERROR(INDEX('Code Mapping'!$D$5:$D$1753,MATCH($B40,'Code Mapping'!$A$5:$A$1753,0)),"Unmapped")) -> Urban Point | M40: =IF($B40="","",IFERROR(INDEX('Code Mapping'!$E$5:$E$1753,MATCH($B40,'Code Mapping'!$A$5:$A$1753,0)),"Unmapped")) -> Aggregator BOGO | N40: =IF($F40="","",$F40) -> Urban Arena
A41: 8076 | B41: UNAR | C41: Public Health Sector Employees 20% Discount | E41: 133 | F41: Urban Arena | G41: 2026-09 | H41: 30 | I41: 107 | J41: 107 | K41: 1068 | L41: =IF($B41="","",IFERROR(INDEX('Code Mapping'!$D$5:$D$1753,MATCH($B41,'Code Mapping'!$A$5:$A$1753,0)),"Unmapped")) -> Public Health Sector (Sogha) | M41: =IF($B41="","",IFERROR(INDEX('Code Mapping'!$E$5:$E$1753,MATCH($B41,'Code Mapping'!$A$5:$A$1753,0)),"Unmapped")) -> Corporate discount | N41: =IF($F41="","",$F41) -> Urban Arena
A42: 8069 | B42: URBN | C42: Al Jazeera Imityazat 15% Discount | E42: 133 | F42: Urban Arena | G42: 2026-09 | H42: 4 | I42: 9 | J42: 9 | K42: 197.25 | L42: =IF($B42="","",IFERROR(INDEX('Code Mapping'!$D$5:$D$1753,MATCH($B42,'Code Mapping'!$A$5:$A$1753,0)),"Unmapped")) -> Al Jazeera Imtiyazat | M42: =IF($B42="","",IFERROR(INDEX('Code Mapping'!$E$5:$E$1753,MATCH($B42,'Code Mapping'!$A$5:$A$1753,0)),"Unmapped")) -> Corporate discount | N42: =IF($F42="","",$F42) -> Urban Arena

Sheet Trend Data
A1: Trend Data: raw export from BookingQube plus lookup columns
A2: Columns A to K are pasted from the system export (event-wise). L and M look up Code Mapping; N repeats the venue from the export. To refresh, paste the new export over A5 downward.
A4: promocode_id | B4: promocode | C4: description | D4: company_name | E4: event_id | F4: event_title | G4: period_month | H4: times_used | I4: booking_lines | J4: tickets | K4: total_discount | L4: Partner | M4: Category | N4: Venue
A5: 8070 | B5: ARNA | C5: Aspire 15% Discount | E5: 133 | F5: Urban Arena | G5: 2026-09 | H5: 4 | I5: 21 | J5: 21 | K5: 147.75 | L5: =IF($B5="","",IFERROR(INDEX('Code Mapping'!$D$5:$D$1753,MATCH($B5,'Code Mapping'!$A$5:$A$1753,0)),"Unmapped")) -> Aspire | M5: =IF($B5="","",IFERROR(INDEX('Code Mapping'!$E$5:$E$1753,MATCH($B5,'Code Mapping'!$A$5:$A$1753,0)),"Unmapped")) -> Corporate discount | N5: =IF($F5="","",$F5) -> Urban Arena
A6: 8322 | B6: loyaltykds | C6: loyalty pass free city pass | D6: E3 | E6: 94 | F6: Kids City Driving School | G6: 2026-09 | H6: 13 | I6: 13 | J6: 13 | K6: 585 | L6: =IF($B6="","",IFERROR(INDEX('Code Mapping'!$D$5:$D$1753,MATCH($B6,'Code Mapping'!$A$5:$A$1753,0)),"Unmapped")) -> Internal / promotion | M6: =IF($B6="","",IFERROR(INDEX('Code Mapping'!$E$5:$E$1753,MATCH($B6,'Code Mapping'!$A$5:$A$1753,0)),"Unmapped")) -> Internal / promotion | N6: =IF($F6="","",$F6) -> Kids City Driving School
A7: 8338 | B7: KCDQAIRWAYS15 | C7: Qatar Airways 15% Discount | D7: E3 | E7: 94 | F7: Kids City Driving School | G7: 2026-09 | H7: 2 | I7: 9 | J7: 9 | K7: 69.75 | L7: =IF($B7="","",IFERROR(INDEX('Code Mapping'!$D$5:$D$1753,MATCH($B7,'Code Mapping'!$A$5:$A$1753,0)),"Unmapped")) -> Qatar Airways | M7: =IF($B7="","",IFERROR(INDEX('Code Mapping'!$E$5:$E$1753,MATCH($B7,'Code Mapping'!$A$5:$A$1753,0)),"Unmapped")) -> Corporate discount | N7: =IF($F7="","",$F7) -> Kids City Driving School
A8: 8340 | B8: KCDQIA15 | C8: Qatar Investment Authority 15% Discount | D8: E3 | E8: 94 | F8: Kids City Driving School | G8: 2026-09 | H8: 16 | I8: 65 | J8: 65 | K8: 453 | L8: =IF($B8="","",IFERROR(INDEX('Code Mapping'!$D$5:$D$1753,MATCH($B8,'Code Mapping'!$A$5:$A$1753,0)),"Unmapped")) -> Qatar Investment Authority | M8: =IF($B8="","",IFERROR(INDEX('Code Mapping'!$E$5:$E$1753,MATCH($B8,'Code Mapping'!$A$5:$A$1753,0)),"Unmapped")) -> Corporate discount | N8: =IF($F8="","",$F8) -> Kids City Driving School
A9: 8345 | B9: KDSBOGOE | D9: E3 | E9: 94 | F9: Kids City Driving School | G9: 2026-09 | H9: 1 | I9: 1 | J9: 1 | K9: 199 | L9: =IF($B9="","",IFERROR(INDEX('Code Mapping'!$D$5:$D$1753,MATCH($B9,'Code Mapping'!$A$5:$A$1753,0)),"Unmapped")) -> Entertainer | M9: =IF($B9="","",IFERROR(INDEX('Code Mapping'!$E$5:$E$1753,MATCH($B9,'Code Mapping'!$A$5:$A$1753,0)),"Unmapped")) -> Aggregator BOGO | N9: =IF($F9="","",$F9) -> Kids City Driving School
A10: 8347 | B10: KDSBOGOM | D10: E3 | E10: 94 | F10: Kids City Driving School | G10: 2026-09 | H10: 11 | I10: 11 | J10: 11 | K10: 2189 | L10: =IF($B10="","",IFERROR(INDEX('Code Mapping'!$D$5:$D$1753,MATCH($B10,'Code Mapping'!$A$5:$A$1753,0)),"Unmapped")) -> My Book | M10: =IF($B10="","",IFERROR(INDEX('Code Mapping'!$E$5:$E$1753,MATCH($B10,'Code Mapping'!$A$5:$A$1753,0)),"Unmapped")) -> Aggregator BOGO | N10: =IF($F10="","",$F10) -> Kids City Driving School
A11: 8346 | B11: KDSBOGOU | D11: E3 | E11: 94 | F11: Kids City Driving School | G11: 2026-09 | H11: 1 | I11: 1 | J11: 1 | K11: 199 | L11: =IF($B11="","",IFERROR(INDEX('Code Mapping'!$D$5:$D$1753,MATCH($B11,'Code Mapping'!$A$5:$A$1753,0)),"Unmapped")) -> Urban Point | M11: =IF($B11="","",IFERROR(INDEX('Code Mapping'!$E$5:$E$1753,MATCH($B11,'Code Mapping'!$A$5:$A$1753,0)),"Unmapped")) -> Aggregator BOGO | N11: =IF($F11="","",$F11) -> Kids City Driving School
A12: 8313 | B12: loyalty | C12: Loyalty customer free rookie pass | D12: E3 | E12: 133 | F12: Urban Arena | G12: 2026-09 | H12: 1 | I12: 1 | J12: 1 | K12: 45 | L12: =IF($B12="","",IFERROR(INDEX('Code Mapping'!$D$5:$D$1753,MATCH($B12,'Code Mapping'!$A$5:$A$1753,0)),"Unmapped")) -> Internal / promotion | M12: =IF($B12="","",IFERROR(INDEX('Code Mapping'!$E$5:$E$1753,MATCH($B12,'Code Mapping'!$A$5:$A$1753,0)),"Unmapped")) -> Internal / promotion | N12: =IF($F12="","",$F12) -> Urban Arena
A13: 8314 | B13: loyaltyinf | D13: E3 | E13: 91 | F13: InflataPark | G13: 2026-09 | H13: 1 | I13: 1 | J13: 1 | K13: 45 | L13: =IF($B13="","",IFERROR(INDEX('Code Mapping'!$D$5:$D$1753,MATCH($B13,'Code Mapping'!$A$5:$A$1753,0)),"Unmapped")) -> Internal / promotion | M13: =IF($B13="","",IFERROR(INDEX('Code Mapping'!$E$5:$E$1753,MATCH($B13,'Code Mapping'!$A$5:$A$1753,0)),"Unmapped")) -> Internal / promotion | N13: =IF($F13="","",$F13) -> InflataPark
A14: 6827 | B14: MYBVD | E14: 61 | F14: Crayons & Bricks Vendome | G14: 2026-09 | H14: 4 | I14: 4 | J14: 4 | K14: 400 | L14: =IF($B14="","",IFERROR(INDEX('Code Mapping'!$D$5:$D$1753,MATCH($B14,'Code Mapping'!$A$5:$A$1753,0)),"Unmapped")) -> My Book | M14: =IF($B14="","",IFERROR(INDEX('Code Mapping'!$E$5:$E$1753,MATCH($B14,'Code Mapping'!$A$5:$A$1753,0)),"Unmapped")) -> Aggregator BOGO | N14: =IF($F14="","",$F14) -> Crayons & Bricks Vendome
A15: 8255 | B15: karak100 | D15: E3 | E15: 133 | F15: Urban Arena | G15: 2026-09 | H15: 1 | I15: 3 | J15: 3 | K15: 15 | L15: =IF($B15="","",IFERROR(INDEX('Code Mapping'!$D$5:$D$1753,MATCH($B15,'Code Mapping'!$A$5:$A$1753,0)),"Unmapped")) -> Internal / promotion | M15: =IF($B15="","",IFERROR(INDEX('Code Mapping'!$E$5:$E$1753,MATCH($B15,'Code Mapping'!$A$5:$A$1753,0)),"Unmapped")) -> Internal / promotion | N15: =IF($F15="","",$F15) -> Urban Arena
A16: 8106 | B16: R1Z6L | C16: Qatar Foundation 15% Discount | E16: 61 | F16: Crayons & Bricks Vendome | G16: 2026-09 | H16: 2 | I16: 10 | J16: 10 | K16: 52.5 | L16: =IF($B16="","",IFERROR(INDEX('Code Mapping'!$D$5:$D$1753,MATCH($B16,'Code Mapping'!$A$5:$A$1753,0)),"Unmapped")) -> Qatar Foundation | M16: =IF($B16="","",IFERROR(INDEX('Code Mapping'!$E$5:$E$1753,MATCH($B16,'Code Mapping'!$A$5:$A$1753,0)),"Unmapped")) -> Corporate discount | N16: =IF($F16="","",$F16) -> Crayons & Bricks Vendome
A17: 8075 | B17: RENA | C17: Imtyazat 15% Discount | E17: 133 | F17: Urban Arena | G17: 2026-09 | H17: 8 | I17: 35 | J17: 35 | K17: 224.25 | L17: =IF($B17="","",IFERROR(INDEX('Code Mapping'!$D$5:$D$1753,MATCH($B17,'Code Mapping'!$A$5:$A$1753,0)),"Unmapped")) -> Imtyazat | M17: =IF($B17="","",IFERROR(INDEX('Code Mapping'!$E$5:$E$1753,MATCH($B17,'Code Mapping'!$A$5:$A$1753,0)),"Unmapped")) -> Corporate discount | N17: =IF($F17="","",$F17) -> Urban Arena
A18: 8093 | B18: UBOFFM | C18: My Book BOGO | E18: 133 | F18: Urban Arena | G18: 2026-09 | H18: 9 | I18: 9 | J18: 9 | K18: 1791 | L18: =IF($B18="","",IFERROR(INDEX('Code Mapping'!$D$5:$D$1753,MATCH($B18,'Code Mapping'!$A$5:$A$1753,0)),"Unmapped")) -> My Book | M18: =IF($B18="","",IFERROR(INDEX('Code Mapping'!$E$5:$E$1753,MATCH($B18,'Code Mapping'!$A$5:$A$1753,0)),"Unmapped")) -> Aggregator BOGO | N18: =IF($F18="","",$F18) -> Urban Arena
A19: 8078 | B19: UENA | C19: Qatar Airways 15% Discount | E19: 133 | F19: Urban Arena | G19: 2026-09 | H19: 31 | I19: 113 | J19: 113 | K19: 856.5 | L19: =IF($B19="","",IFERROR(INDEX('Code Mapping'!$D$5:$D$1753,MATCH($B19,'Code Mapping'!$A$5:$A$1753,0)),"Unmapped")) -> Qatar Airways | M19: =IF($B19="","",IFERROR(INDEX('Code Mapping'!$E$5:$E$1753,MATCH($B19,'Code Mapping'!$A$5:$A$1753,0)),"Unmapped")) -> Corporate discount | N19: =IF($F19="","",$F19) -> Urban Arena
A20: 8094 | B20: UGBOGU | C20: Urban Point BOGO | E20: 133 | F20: Urban Arena | G20: 2026-09 | H20: 10 | I20: 10 | J20: 10 | K20: 1990 | L20: =IF($B20="","",IFERROR(INDEX('Code Mapping'!$D$5:$D$1753,MATCH($B20,'Code Mapping'!$A$5:$A$1753,0)),"Unmapped")) -> Urban Point | M20: =IF($B20="","",IFERROR(INDEX('Code Mapping'!$E$5:$E$1753,MATCH($B20,'Code Mapping'!$A$5:$A$1753,0)),"Unmapped")) -> Aggregator BOGO | N20: =IF($F20="","",$F20) -> Urban Arena
A21: 8076 | B21: UNAR | C21: Public Health Sector Employees 20% Discount | E21: 133 | F21: Urban Arena | G21: 2026-09 | H21: 30 | I21: 107 | J21: 107 | K21: 1068 | L21: =IF($B21="","",IFERROR(INDEX('Code Mapping'!$D$5:$D$1753,MATCH($B21,'Code Mapping'!$A$5:$A$1753,0)),"Unmapped")) -> Public Health Sector (Sogha) | M21: =IF($B21="","",IFERROR(INDEX('Code Mapping'!$E$5:$E$1753,MATCH($B21,'Code Mapping'!$A$5:$A$1753,0)),"Unmapped")) -> Corporate discount | N21: =IF($F21="","",$F21) -> Urban Arena
A22: 8069 | B22: URBN | C22: Al Jazeera Imityazat 15% Discount | E22: 133 | F22: Urban Arena | G22: 2026-09 | H22: 4 | I22: 9 | J22: 9 | K22: 197.25 | L22: =IF($B22="","",IFERROR(INDEX('Code Mapping'!$D$5:$D$1753,MATCH($B22,'Code Mapping'!$A$5:$A$1753,0)),"Unmapped")) -> Al Jazeera Imtiyazat | M22: =IF($B22="","",IFERROR(INDEX('Code Mapping'!$E$5:$E$1753,MATCH($B22,'Code Mapping'!$A$5:$A$1753,0)),"Unmapped")) -> Corporate discount | N22: =IF($F22="","",$F22) -> Urban Arena
A23: 8335 | B23: KCDIMTIYAZAT15 | C23: Imtiyazat 15% Discount | D23: E3 | E23: 94 | F23: Kids City Driving School | G23: 2026-09 | H23: 37 | I23: 160 | J23: 160 | K23: 1137.75 | L23: =IF($B23="","",IFERROR(INDEX('Code Mapping'!$D$5:$D$1753,MATCH($B23,'Code Mapping'!$A$5:$A$1753,0)),"Unmapped")) -> Imtyazat | M23: =IF($B23="","",IFERROR(INDEX('Code Mapping'!$E$5:$E$1753,MATCH($B23,'Code Mapping'!$A$5:$A$1753,0)),"Unmapped")) -> Corporate discount | N23: =IF($F23="","",$F23) -> Kids City Driving School
A24: 8079 | B24: ARNB | C24: Qatar Foundation 15% Discount | D24: E3 | E24: 133 | F24: Urban Arena | G24: 2026-09 | H24: 27 | I24: 113 | J24: 113 | K24: 947.7 | L24: =IF($B24="","",IFERROR(INDEX('Code Mapping'!$D$5:$D$1753,MATCH($B24,'Code Mapping'!$A$5:$A$1753,0)),"Unmapped")) -> Qatar Foundation | M24: =IF($B24="","",IFERROR(INDEX('Code Mapping'!$E$5:$E$1753,MATCH($B24,'Code Mapping'!$A$5:$A$1753,0)),"Unmapped")) -> Corporate discount | N24: =IF($F24="","",$F24) -> Urban Arena
A25: 8105 | B25: K9P3X | C25: Qatar Airways 15% Discount | E25: 61 | F25: Crayons & Bricks Vendome | G25: 2026-09 | H25: 1 | I25: 1 | J25: 1 | K25: 5.25 | L25: =IF($B25="","",IFERROR(INDEX('Code Mapping'!$D$5:$D$1753,MATCH($B25,'Code Mapping'!$A$5:$A$1753,0)),"Unmapped")) -> Qatar Airways | M25: =IF($B25="","",IFERROR(INDEX('Code Mapping'!$E$5:$E$1753,MATCH($B25,'Code Mapping'!$A$5:$A$1753,0)),"Unmapped")) -> Corporate discount | N25: =IF($F25="","",$F25) -> Crayons & Bricks Vendome
A26: 8325 | B26: INFAMBBOGO2 | D26: E3 | E26: 91 | F26: InflataPark | G26: 2026-09 | H26: 1 | I26: 1 | J26: 1 | K26: 199 | L26: =IF($B26="","",IFERROR(INDEX('Code Mapping'!$D$5:$D$1753,MATCH($B26,'Code Mapping'!$A$5:$A$1753,0)),"Unmapped")) -> My Book | M26: =IF($B26="","",IFERROR(INDEX('Code Mapping'!$E$5:$E$1753,MATCH($B26,'Code Mapping'!$A$5:$A$1753,0)),"Unmapped")) -> Aggregator BOGO | N26: =IF($F26="","",$F26) -> InflataPark
A27: 8077 | B27: BRNA | C27: QIB 15% Discount | E27: 133 | F27: Urban Arena | G27: 2026-09 | H27: 5 | I27: 21 | J27: 21 | K27: 174 | L27: =IF($B27="","",IFERROR(INDEX('Code Mapping'!$D$5:$D$1753,MATCH($B27,'Code Mapping'!$A$5:$A$1753,0)),"Unmapped")) -> QIB | M27: =IF($B27="","",IFERROR(INDEX('Code Mapping'!$E$5:$E$1753,MATCH($B27,'Code Mapping'!$A$5:$A$1753,0)),"Unmapped")) -> Corporate discount | N27: =IF($F27="","",$F27) -> Urban Arena
A28: 8038 | B28: cafe50 | C28: 50% off on cafe | E28: 133 | F28: Urban Arena | G28: 2026-09 | H28: 63 | I28: 78 | J28: 78 | K28: 443.5 | L28: =IF($B28="","",IFERROR(INDEX('Code Mapping'!$D$5:$D$1753,MATCH($B28,'Code Mapping'!$A$5:$A$1753,0)),"Unmapped")) -> Internal / promotion | M28: =IF($B28="","",IFERROR(INDEX('Code Mapping'!$E$5:$E$1753,MATCH($B28,'Code Mapping'!$A$5:$A$1753,0)),"Unmapped")) -> Internal / promotion | N28: =IF($F28="","",$F28) -> Urban Arena
A29: 8095 | B29: CBOGOE | C29: Entertainer BOGO | E29: 61 | F29: Crayons & Bricks Vendome | G29: 2026-09 | H29: 12 | I29: 12 | J29: 12 | K29: 1200 | L29: =IF($B29="","",IFERROR(INDEX('Code Mapping'!$D$5:$D$1753,MATCH($B29,'Code Mapping'!$A$5:$A$1753,0)),"Unmapped")) -> Entertainer | M29: =IF($B29="","",IFERROR(INDEX('Code Mapping'!$E$5:$E$1753,MATCH($B29,'Code Mapping'!$A$5:$A$1753,0)),"Unmapped")) -> Aggregator BOGO | N29: =IF($F29="","",$F29) -> Crayons & Bricks Vendome
A30: 8097 | B30: CGBOGU | C30: Urban Point BOGO | E30: 61 | F30: Crayons & Bricks Vendome | G30: 2026-09 | H30: 17 | I30: 17 | J30: 17 | K30: 1700 | L30: =IF($B30="","",IFERROR(INDEX('Code Mapping'!$D$5:$D$1753,MATCH($B30,'Code Mapping'!$A$5:$A$1753,0)),"Unmapped")) -> Urban Point | M30: =IF($B30="","",IFERROR(INDEX('Code Mapping'!$E$5:$E$1753,MATCH($B30,'Code Mapping'!$A$5:$A$1753,0)),"Unmapped")) -> Aggregator BOGO | N30: =IF($F30="","",$F30) -> Crayons & Bricks Vendome
A31: 8096 | B31: CGOBOQ | C31: Qatar Living BOGO | E31: 61 | F31: Crayons & Bricks Vendome | G31: 2026-09 | H31: 1 | I31: 1 | J31: 1 | K31: 100 | L31: =IF($B31="","",IFERROR(INDEX('Code Mapping'!$D$5:$D$1753,MATCH($B31,'Code Mapping'!$A$5:$A$1753,0)),"Unmapped")) -> Qatar Living Deals | M31: =IF($B31="","",IFERROR(INDEX('Code Mapping'!$E$5:$E$1753,MATCH($B31,'Code Mapping'!$A$5:$A$1753,0)),"Unmapped")) -> Aggregator BOGO | N31: =IF($F31="","",$F31) -> Crayons & Bricks Vendome
A32: 8318 | B32: dmqnb15 | D32: QNB | E32: 133 | F32: Urban Arena | G32: 2026-09 | H32: 6 | I32: 18 | J32: 18 | K32: 151.5 | L32: =IF($B32="","",IFERROR(INDEX('Code Mapping'!$D$5:$D$1753,MATCH($B32,'Code Mapping'!$A$5:$A$1753,0)),"Unmapped")) -> QNB Rewards | M32: =IF($B32="","",IFERROR(INDEX('Code Mapping'!$E$5:$E$1753,MATCH($B32,'Code Mapping'!$A$5:$A$1753,0)),"Unmapped")) -> Corporate discount | N32: =IF($F32="","",$F32) -> Urban Arena
A33: 8046 | B33: INFAJID | C33: Al Jazeera Imityazat 15% Discount | E33: 91 | F33: InflataPark | G33: 2026-09 | H33: 2 | I33: 2 | J33: 2 | K33: 22.5 | L33: =IF($B33="","",IFERROR(INDEX('Code Mapping'!$D$5:$D$1753,MATCH($B33,'Code Mapping'!$A$5:$A$1753,0)),"Unmapped")) -> Al Jazeera Imtiyazat | M33: =IF($B33="","",IFERROR(INDEX('Code Mapping'!$E$5:$E$1753,MATCH($B33,'Code Mapping'!$A$5:$A$1753,0)),"Unmapped")) -> Corporate discount | N33: =IF($F33="","",$F33) -> InflataPark
A34: 8326 | B34: INFUPBOGO2 | D34: E3 | E34: 91 | F34: InflataPark | G34: 2026-09 | H34: 12 | I34: 12 | J34: 12 | K34: 2388 | L34: =IF($B34="","",IFERROR(INDEX('Code Mapping'!$D$5:$D$1753,MATCH($B34,'Code Mapping'!$A$5:$A$1753,0)),"Unmapped")) -> Urban Point | M34: =IF($B34="","",IFERROR(INDEX('Code Mapping'!$E$5:$E$1753,MATCH($B34,'Code Mapping'!$A$5:$A$1753,0)),"Unmapped")) -> Aggregator BOGO | N34: =IF($F34="","",$F34) -> InflataPark
A35: 8047 | B35: INFASPID | C35: Aspire 15% Discount | E35: 91 | F35: InflataPark | G35: 2026-09 | H35: 1 | I35: 2 | J35: 2 | K35: 15 | L35: =IF($B35="","",IFERROR(INDEX('Code Mapping'!$D$5:$D$1753,MATCH($B35,'Code Mapping'!$A$5:$A$1753,0)),"Unmapped")) -> Aspire | M35: =IF($B35="","",IFERROR(INDEX('Code Mapping'!$E$5:$E$1753,MATCH($B35,'Code Mapping'!$A$5:$A$1753,0)),"Unmapped")) -> Corporate discount | N35: =IF($F35="","",$F35) -> InflataPark
A36: 8324 | B36: INFENTBOGO2 | D36: E3 | E36: 91 | F36: InflataPark | G36: 2026-09 | H36: 6 | I36: 6 | J36: 6 | K36: 1194 | L36: =IF($B36="","",IFERROR(INDEX('Code Mapping'!$D$5:$D$1753,MATCH($B36,'Code Mapping'!$A$5:$A$1753,0)),"Unmapped")) -> Entertainer | M36: =IF($B36="","",IFERROR(INDEX('Code Mapping'!$E$5:$E$1753,MATCH($B36,'Code Mapping'!$A$5:$A$1753,0)),"Unmapped")) -> Aggregator BOGO | N36: =IF($F36="","",$F36) -> InflataPark
A37: 8052 | B37: INFIMTYD | C37: Imtyazat 15% Discount | D37: E3 | E37: 91 | F37: InflataPark | G37: 2026-09 | H37: 27 | I37: 110 | J37: 110 | K37: 859.5 | L37: =IF($B37="","",IFERROR(INDEX('Code Mapping'!$D$5:$D$1753,MATCH($B37,'Code Mapping'!$A$5:$A$1753,0)),"Unmapped")) -> Imtyazat | M37: =IF($B37="","",IFERROR(INDEX('Code Mapping'!$E$5:$E$1753,MATCH($B37,'Code Mapping'!$A$5:$A$1753,0)),"Unmapped")) -> Corporate discount | N37: =IF($F37="","",$F37) -> InflataPark
A38: 8053 | B38: INFPHSED | C38: Public Health Sector Employees 20% Discount | E38: 91 | F38: InflataPark | G38: 2026-09 | H38: 21 | I38: 50 | J38: 50 | K38: 466 | L38: =IF($B38="","",IFERROR(INDEX('Code Mapping'!$D$5:$D$1753,MATCH($B38,'Code Mapping'!$A$5:$A$1753,0)),"Unmapped")) -> Public Health Sector (Sogha) | M38: =IF($B38="","",IFERROR(INDEX('Code Mapping'!$E$5:$E$1753,MATCH($B38,'Code Mapping'!$A$5:$A$1753,0)),"Unmapped")) -> Corporate discount | N38: =IF($F38="","",$F38) -> InflataPark
A39: 8055 | B39: INFQAD | C39: Qatar Airways 15% Discount | E39: 91 | F39: InflataPark | G39: 2026-09 | H39: 32 | I39: 82 | J39: 82 | K39: 523.5 | L39: =IF($B39="","",IFERROR(INDEX('Code Mapping'!$D$5:$D$1753,MATCH($B39,'Code Mapping'!$A$5:$A$1753,0)),"Unmapped")) -> Qatar Airways | M39: =IF($B39="","",IFERROR(INDEX('Code Mapping'!$E$5:$E$1753,MATCH($B39,'Code Mapping'!$A$5:$A$1753,0)),"Unmapped")) -> Corporate discount | N39: =IF($F39="","",$F39) -> InflataPark
A40: 8056 | B40: INFQFD | C40: Qatar Foundation 15% Discount | E40: 91 | F40: InflataPark | G40: 2026-09 | H40: 5 | I40: 11 | J40: 11 | K40: 71.25 | L40: =IF($B40="","",IFERROR(INDEX('Code Mapping'!$D$5:$D$1753,MATCH($B40,'Code Mapping'!$A$5:$A$1753,0)),"Unmapped")) -> Qatar Foundation | M40: =IF($B40="","",IFERROR(INDEX('Code Mapping'!$E$5:$E$1753,MATCH($B40,'Code Mapping'!$A$5:$A$1753,0)),"Unmapped")) -> Corporate discount | N40: =IF($F40="","",$F40) -> InflataPark
A41: 8057 | B41: INFQIAD | C41: Qatar Investment Authority 15% Discount | E41: 91 | F41: InflataPark | G41: 2026-09 | H41: 4 | I41: 12 | J41: 12 | K41: 88.5 | L41: =IF($B41="","",IFERROR(INDEX('Code Mapping'!$D$5:$D$1753,MATCH($B41,'Code Mapping'!$A$5:$A$1753,0)),"Unmapped")) -> Qatar Investment Authority | M41: =IF($B41="","",IFERROR(INDEX('Code Mapping'!$E$5:$E$1753,MATCH($B41,'Code Mapping'!$A$5:$A$1753,0)),"Unmapped")) -> Corporate discount | N41: =IF($F41="","",$F41) -> InflataPark
A42: 8048 | B42: INFBEIND | C42: Bein 15% Discount | E42: 91 | F42: InflataPark | G42: 2026-09 | H42: 1 | I42: 6 | J42: 6 | K42: 52.5 | L42: =IF($B42="","",IFERROR(INDEX('Code Mapping'!$D$5:$D$1753,MATCH($B42,'Code Mapping'!$A$5:$A$1753,0)),"Unmapped")) -> Bein | M42: =IF($B42="","",IFERROR(INDEX('Code Mapping'!$E$5:$E$1753,MATCH($B42,'Code Mapping'!$A$5:$A$1753,0)),"Unmapped")) -> Corporate discount | N42: =IF($F42="","",$F42) -> InflataPark
A43: 8103 | B43: M2W7D | C43: Imtyazat 15% Discount | E43: 61 | F43: Crayons & Bricks Vendome | G43: 2026-08 | H43: 3 | I43: 12 | J43: 12 | K43: 44.25 | L43: =IF($B43="","",IFERROR(INDEX('Code Mapping'!$D$5:$D$1753,MATCH($B43,'Code Mapping'!$A$5:$A$1753,0)),"Unmapped")) -> Imtyazat | M43: =IF($B43="","",IFERROR(INDEX('Code Mapping'!$E$5:$E$1753,MATCH($B43,'Code Mapping'!$A$5:$A$1753,0)),"Unmapped")) -> Corporate discount | N43: =IF($F43="","",$F43) -> Crayons & Bricks Vendome
A44: 8106 | B44: R1Z6L | C44: Qatar Foundation 15% Discount | E44: 61 | F44: Crayons & Bricks Vendome | G44: 2026-08 | H44: 2 | I44: 9 | J44: 9 | K44: 42.3 | L44: =IF($B44="","",IFERROR(INDEX('Code Mapping'!$D$5:$D$1753,MATCH($B44,'Code Mapping'!$A$5:$A$1753,0)),"Unmapped")) -> Qatar Foundation | M44: =IF($B44="","",IFERROR(INDEX('Code Mapping'!$E$5:$E$1753,MATCH($B44,'Code Mapping'!$A$5:$A$1753,0)),"Unmapped")) -> Corporate discount | N44: =IF($F44="","",$F44) -> Crayons & Bricks Vendome
A45: 6827 | B45: MYBVD | E45: 61 | F45: Crayons & Bricks Vendome | G45: 2026-08 | H45: 8 | I45: 8 | J45: 8 | K45: 800 | L45: =IF($B45="","",IFERROR(INDEX('Code Mapping'!$D$5:$D$1753,MATCH($B45,'Code Mapping'!$A$5:$A$1753,0)),"Unmapped")) -> My Book | M45: =IF($B45="","",IFERROR(INDEX('Code Mapping'!$E$5:$E$1753,MATCH($B45,'Code Mapping'!$A$5:$A$1753,0)),"Unmapped")) -> Aggregator BOGO | N45: =IF($F45="","",$F45) -> Crayons & Bricks Vendome
A46: 8065 | B46: KCDSIMTYD | C46: Imtyazat 15% Discount | D46: E3 | E46: 94 | F46: Kids City Driving School | G46: 2026-08 | H46: 2 | I46: 4 | J46: 4 | K46: 21 | L46: =IF($B46="","",IFERROR(INDEX('Code Mapping'!$D$5:$D$1753,MATCH($B46,'Code Mapping'!$A$5:$A$1753,0)),"Unmapped")) -> Imtyazat | M46: =IF($B46="","",IFERROR(INDEX('Code Mapping'!$E$5:$E$1753,MATCH($B46,'Code Mapping'!$A$5:$A$1753,0)),"Unmapped")) -> Corporate discount | N46: =IF($F46="","",$F46) -> Kids City Driving School
A47: 8322 | B47: loyaltykds | C47: loyalty pass free city pass | D47: E3 | E47: 94 | F47: Kids City Driving School | G47: 2026-08 | H47: 33 | I47: 33 | J47: 33 | K47: 1485 | L47: =IF($B47="","",IFERROR(INDEX('Code Mapping'!$D$5:$D$1753,MATCH($B47,'Code Mapping'!$A$5:$A$1753,0)),"Unmapped")) -> Internal / promotion | M47: =IF($B47="","",IFERROR(INDEX('Code Mapping'!$E$5:$E$1753,MATCH($B47,'Code Mapping'!$A$5:$A$1753,0)),"Unmapped")) -> Internal / promotion | N47: =IF($F47="","",$F47) -> Kids City Driving School
A48: 8314 | B48: loyaltyinf | D48: E3 | E48: 91 | F48: InflataPark | G48: 2026-08 | H48: 2 | I48: 2 | J48: 2 | K48: 90 | L48: =IF($B48="","",IFERROR(INDEX('Code Mapping'!$D$5:$D$1753,MATCH($B48,'Code Mapping'!$A$5:$A$1753,0)),"Unmapped")) -> Internal / promotion | M48: =IF($B48="","",IFERROR(INDEX('Code Mapping'!$E$5:$E$1753,MATCH($B48,'Code Mapping'!$A$5:$A$1753,0)),"Unmapped")) -> Internal / promotion | N48: =IF($F48="","",$F48) -> InflataPark
A49: 8313 | B49: loyalty | C49: Loyalty customer free rookie pass | D49: E3 | E49: 133 | F49: Urban Arena | G49: 2026-08 | H49: 2 | I49: 2 | J49: 2 | K49: 90 | L49: =IF($B49="","",IFERROR(INDEX('Code Mapping'!$D$5:$D$1753,MATCH($B49,'Code Mapping'!$A$5:$A$1753,0)),"Unmapped")) -> Internal / promotion | M49: =IF($B49="","",IFERROR(INDEX('Code Mapping'!$E$5:$E$1753,MATCH($B49,'Code Mapping'!$A$5:$A$1753,0)),"Unmapped")) -> Internal / promotion | N49: =IF($F49="","",$F49) -> Urban Arena
A50: 8081 | B50: UAQMC | C50: Qatar Media Corporation 15% Discount | E50: 133 | F50: Urban Arena | G50: 2026-08 | H50: 6 | I50: 24 | J50: 24 | K50: 161.25 | L50: =IF($B50="","",IFERROR(INDEX('Code Mapping'!$D$5:$D$1753,MATCH($B50,'Code Mapping'!$A$5:$A$1753,0)),"Unmapped")) -> Qatar Media Corporation | M50: =IF($B50="","",IFERROR(INDEX('Code Mapping'!$E$5:$E$1753,MATCH($B50,'Code Mapping'!$A$5:$A$1753,0)),"Unmapped")) -> Corporate discount | N50: =IF($F50="","",$F50) -> Urban Arena
A51: 8075 | B51: RENA | C51: Imtyazat 15% Discount | E51: 133 | F51: Urban Arena | G51: 2026-08 | H51: 12 | I51: 31 | J51: 31 | K51: 239.25 | L51: =IF($B51="","",IFERROR(INDEX('Code Mapping'!$D$5:$D$1753,MATCH($B51,'Code Mapping'!$A$5:$A$1753,0)),"Unmapped")) -> Imtyazat | M51: =IF($B51="","",IFERROR(INDEX('Code Mapping'!$E$5:$E$1753,MATCH($B51,'Code Mapping'!$A$5:$A$1753,0)),"Unmapped")) -> Corporate discount | N51: =IF($F51="","",$F51) -> Urban Arena
A52: 8078 | B52: UENA | C52: Qatar Airways 15% Discount | E52: 133 | F52: Urban Arena | G52: 2026-08 | H52: 65 | I52: 190 | J52: 190 | K52: 1387.35 | L52: =IF($B52="","",IFERROR(INDEX('Code Mapping'!$D$5:$D$1753,MATCH($B52,'Code Mapping'!$A$5:$A$1753,0)),"Unmapped")) -> Qatar Airways | M52: =IF($B52="","",IFERROR(INDEX('Code Mapping'!$E$5:$E$1753,MATCH($B52,'Code Mapping'!$A$5:$A$1753,0)),"Unmapped")) -> Corporate discount | N52: =IF($F52="","",$F52) -> Urban Arena
A53: 8080 | B53: UARB | C53: Qatar Investment Authority 15% Discount | E53: 133 | F53: Urban Arena | G53: 2026-08 | H53: 2 | I53: 13 | J53: 13 | K53: 108.75 | L53: =IF($B53="","",IFERROR(INDEX('Code Mapping'!$D$5:$D$1753,MATCH($B53,'Code Mapping'!$A$5:$A$1753,0)),"Unmapped")) -> Qatar Investment Authority | M53: =IF($B53="","",IFERROR(INDEX('Code Mapping'!$E$5:$E$1753,MATCH($B53,'Code Mapping'!$A$5:$A$1753,0)),"Unmapped")) -> Corporate discount | N53: =IF($F53="","",$F53) -> Urban Arena
A54: 8071 | B54: UARE | C54: Bein 15% Discount | E54: 133 | F54: Urban Arena | G54: 2026-08 | H54: 4 | I54: 25 | J54: 25 | K54: 171.75 | L54: =IF($B54="","",IFERROR(INDEX('Code Mapping'!$D$5:$D$1753,MATCH($B54,'Code Mapping'!$A$5:$A$1753,0)),"Unmapped")) -> Bein | M54: =IF($B54="","",IFERROR(INDEX('Code Mapping'!$E$5:$E$1753,MATCH($B54,'Code Mapping'!$A$5:$A$1753,0)),"Unmapped")) -> Corporate discount | N54: =IF($F54="","",$F54) -> Urban Arena
A55: 8093 | B55: UBOFFM | C55: My Book BOGO | E55: 133 | F55: Urban Arena | G55: 2026-08 | H55: 65 | I55: 65 | J55: 65 | K55: 12935 | L55: =IF($B55="","",IFERROR(INDEX('Code Mapping'!$D$5:$D$1753,MATCH($B55,'Code Mapping'!$A$5:$A$1753,0)),"Unmapped")) -> My Book | M55: =IF($B55="","",IFERROR(INDEX('Code Mapping'!$E$5:$E$1753,MATCH($B55,'Code Mapping'!$A$5:$A$1753,0)),"Unmapped")) -> Aggregator BOGO | N55: =IF($F55="","",$F55) -> Urban Arena
A56: 8094 | B56: UGBOGU | C56: Urban Point BOGO | E56: 133 | F56: Urban Arena | G56: 2026-08 | H56: 20 | I56: 20 | J56: 20 | K56: 3980 | L56: =IF($B56="","",IFERROR(INDEX('Code Mapping'!$D$5:$D$1753,MATCH($B56,'Code Mapping'!$A$5:$A$1753,0)),"Unmapped")) -> Urban Point | M56: =IF($B56="","",IFERROR(INDEX('Code Mapping'!$E$5:$E$1753,MATCH($B56,'Code Mapping'!$A$5:$A$1753,0)),"Unmapped")) -> Aggregator BOGO | N56: =IF($F56="","",$F56) -> Urban Arena
A57: 8092 | B57: UGOBOE | C57: Entertainer BOGO | E57: 133 | F57: Urban Arena | G57: 2026-08 | H57: 3 | I57: 3 | J57: 3 | K57: 597 | L57: =IF($B57="","",IFERROR(INDEX('Code Mapping'!$D$5:$D$1753,MATCH($B57,'Code Mapping'!$A$5:$A$1753,0)),"Unmapped")) -> Entertainer | M57: =IF($B57="","",IFERROR(INDEX('Code Mapping'!$E$5:$E$1753,MATCH($B57,'Code Mapping'!$A$5:$A$1753,0)),"Unmapped")) -> Aggregator BOGO | N57: =IF($F57="","",$F57) -> Urban Arena
A58: 8076 | B58: UNAR | C58: Public Health Sector Employees 20% Discount | E58: 133 | F58: Urban Arena | G58: 2026-08 | H58: 53 | I58: 224 | J58: 224 | K58: 2543.4 | L58: =IF($B58="","",IFERROR(INDEX('Code Mapping'!$D$5:$D$1753,MATCH($B58,'Code Mapping'!$A$5:$A$1753,0)),"Unmapped")) -> Public Health Sector (Sogha) | M58: =IF($B58="","",IFERROR(INDEX('Code Mapping'!$E$5:$E$1753,MATCH($B58,'Code Mapping'!$A$5:$A$1753,0)),"Unmapped")) -> Corporate discount | N58: =IF($F58="","",$F58) -> Urban Arena
A59: 8069 | B59: URBN | C59: Al Jazeera Imityazat 15% Discount | E59: 133 | F59: Urban Arena | G59: 2026-08 | H59: 6 | I59: 32 | J59: 32 | K59: 274.5 | L59: =IF($B59="","",IFERROR(INDEX('Code Mapping'!$D$5:$D$1753,MATCH($B59,'Code Mapping'!$A$5:$A$1753,0)),"Unmapped")) -> Al Jazeera Imtiyazat | M59: =IF($B59="","",IFERROR(INDEX('Code Mapping'!$E$5:$E$1753,MATCH($B59,'Code Mapping'!$A$5:$A$1753,0)),"Unmapped")) -> Corporate discount | N59: =IF($F59="","",$F59) -> Urban Arena
A60: 8335 | B60: KCDIMTIYAZAT15 | C60: Imtiyazat 15% Discount | D60: E3 | E60: 94 | F60: Kids City Driving School | G60: 2026-08 | H60: 136 | I60: 544 | J60: 544 | K60: 4178.25 | L60: =IF($B60="","",IFERROR(INDEX('Code Mapping'!$D$5:$D$1753,MATCH($B60,'Code Mapping'!$A$5:$A$1753,0)),"Unmapped")) -> Imtyazat | M60: =IF($B60="","",IFERROR(INDEX('Code Mapping'!$E$5:$E$1753,MATCH($B60,'Code Mapping'!$A$5:$A$1753,0)),"Unmapped")) -> Corporate discount | N60: =IF($F60="","",$F60) -> Kids City Driving School
A61: 8338 | B61: KCDQAIRWAYS15 | C61: Qatar Airways 15% Discount | D61: E3 | E61: 94 | F61: Kids City Driving School | G61: 2026-08 | H61: 4 | I61: 14 | J61: 14 | K61: 102 | L61: =IF($B61="","",IFERROR(INDEX('Code Mapping'!$D$5:$D$1753,MATCH($B61,'Code Mapping'!$A$5:$A$1753,0)),"Unmapped")) -> Qatar Airways | M61: =IF($B61="","",IFERROR(INDEX('Code Mapping'!$E$5:$E$1753,MATCH($B61,'Code Mapping'!$A$5:$A$1753,0)),"Unmapped")) -> Corporate discount | N61: =IF($F61="","",$F61) -> Kids City Driving School
A62: 8347 | B62: KDSBOGOM | D62: E3 | E62: 94 | F62: Kids City Driving School | G62: 2026-08 | H62: 40 | I62: 40 | J62: 40 | K62: 7960 | L62: =IF($B62="","",IFERROR(INDEX('Code Mapping'!$D$5:$D$1753,MATCH($B62,'Code Mapping'!$A$5:$A$1753,0)),"Unmapped")) -> My Book | M62: =IF($B62="","",IFERROR(INDEX('Code Mapping'!$E$5:$E$1753,MATCH($B62,'Code Mapping'!$A$5:$A$1753,0)),"Unmapped")) -> Aggregator BOGO | N62: =IF($F62="","",$F62) -> Kids City Driving School
A63: 8105 | B63: K9P3X | C63: Qatar Airways 15% Discount | E63: 61 | F63: Crayons & Bricks Vendome | G63: 2026-08 | H63: 3 | I63: 6 | J63: 6 | K63: 21.75 | L63: =IF($B63="","",IFERROR(INDEX('Code Mapping'!$D$5:$D$1753,MATCH($B63,'Code Mapping'!$A$5:$A$1753,0)),"Unmapped")) -> Qatar Airways | M63: =IF($B63="","",IFERROR(INDEX('Code Mapping'!$E$5:$E$1753,MATCH($B63,'Code Mapping'!$A$5:$A$1753,0)),"Unmapped")) -> Corporate discount | N63: =IF($F63="","",$F63) -> Crayons & Bricks Vendome
A64: 8046 | B64: INFAJID | C64: Al Jazeera Imityazat 15% Discount | E64: 91 | F64: InflataPark | G64: 2026-08 | H64: 10 | I64: 23 | J64: 23 | K64: 170.25 | L64: =IF($B64="","",IFERROR(INDEX('Code Mapping'!$D$5:$D$1753,MATCH($B64,'Code Mapping'!$A$5:$A$1753,0)),"Unmapped")) -> Al Jazeera Imtiyazat | M64: =IF($B64="","",IFERROR(INDEX('Code Mapping'!$E$5:$E$1753,MATCH($B64,'Code Mapping'!$A$5:$A$1753,0)),"Unmapped")) -> Corporate discount | N64: =IF($F64="","",$F64) -> InflataPark
A65: 8326 | B65: INFUPBOGO2 | D65: E3 | E65: 91 | F65: InflataPark | G65: 2026-08 | H65: 20 | I65: 20 | J65: 20 | K65: 3980 | L65: =IF($B65="","",IFERROR(INDEX('Code Mapping'!$D$5:$D$1753,MATCH($B65,'Code Mapping'!$A$5:$A$1753,0)),"Unmapped")) -> Urban Point | M65: =IF($B65="","",IFERROR(INDEX('Code Mapping'!$E$5:$E$1753,MATCH($B65,'Code Mapping'!$A$5:$A$1753,0)),"Unmapped")) -> Aggregator BOGO | N65: =IF($F65="","",$F65) -> InflataPark
A66: 8070 | B66: ARNA | C66: Aspire 15% Discount | E66: 133 | F66: Urban Arena | G66: 2026-08 | H66: 9 | I66: 25 | J66: 25 | K66: 262.05 | L66: =IF($B66="","",IFERROR(INDEX('Code Mapping'!$D$5:$D$1753,MATCH($B66,'Code Mapping'!$A$5:$A$1753,0)),"Unmapped")) -> Aspire | M66: =IF($B66="","",IFERROR(INDEX('Code Mapping'!$E$5:$E$1753,MATCH($B66,'Code Mapping'!$A$5:$A$1753,0)),"Unmapped")) -> Corporate discount | N66: =IF($F66="","",$F66) -> Urban Arena
A67: 8079 | B67: ARNB | C67: Qatar Foundation 15% Discount | D67: E3 | E67: 133 | F67: Urban Arena | G67: 2026-08 | H67: 61 | I67: 242 | J67: 242 | K67: 2058.6 | L67: =IF($B67="","",IFERROR(INDEX('Code Mapping'!$D$5:$D$1753,MATCH($B67,'Code Mapping'!$A$5:$A$1753,0)),"Unmapped")) -> Qatar Foundation | M67: =IF($B67="","",IFERROR(INDEX('Code Mapping'!$E$5:$E$1753,MATCH($B67,'Code Mapping'!$A$5:$A$1753,0)),"Unmapped")) -> Corporate discount | N67: =IF($F67="","",$F67) -> Urban Arena
A68: 8077 | B68: BRNA | C68: QIB 15% Discount | E68: 133 | F68: Urban Arena | G68: 2026-08 | H68: 5 | I68: 19 | J68: 19 | K68: 120 | L68: =IF($B68="","",IFERROR(INDEX('Code Mapping'!$D$5:$D$1753,MATCH($B68,'Code Mapping'!$A$5:$A$1753,0)),"Unmapped")) -> QIB | M68: =IF($B68="","",IFERROR(INDEX('Code Mapping'!$E$5:$E$1753,MATCH($B68,'Code Mapping'!$A$5:$A$1753,0)),"Unmapped")) -> Corporate discount | N68: =IF($F68="","",$F68) -> Urban Arena
A69: 8038 | B69: cafe50 | C69: 50% off on cafe | E69: 133 | F69: Urban Arena | G69: 2026-08 | H69: 96 | I69: 124 | J69: 124 | K69: 604.5 | L69: =IF($B69="","",IFERROR(INDEX('Code Mapping'!$D$5:$D$1753,MATCH($B69,'Code Mapping'!$A$5:$A$1753,0)),"Unmapped")) -> Internal / promotion | M69: =IF($B69="","",IFERROR(INDEX('Code Mapping'!$E$5:$E$1753,MATCH($B69,'Code Mapping'!$A$5:$A$1753,0)),"Unmapped")) -> Internal / promotion | N69: =IF($F69="","",$F69) -> Urban Arena
A70: 8097 | B70: CGBOGU | C70: Urban Point BOGO | E70: 61 | F70: Crayons & Bricks Vendome | G70: 2026-08 | H70: 29 | I70: 29 | J70: 29 | K70: 2900 | L70: =IF($B70="","",IFERROR(INDEX('Code Mapping'!$D$5:$D$1753,MATCH($B70,'Code Mapping'!$A$5:$A$1753,0)),"Unmapped")) -> Urban Point | M70: =IF($B70="","",IFERROR(INDEX('Code Mapping'!$E$5:$E$1753,MATCH($B70,'Code Mapping'!$A$5:$A$1753,0)),"Unmapped")) -> Aggregator BOGO | N70: =IF($F70="","",$F70) -> Crayons & Bricks Vendome
A71: 8323 | B71: dg100 | D71: E3 | E71: 91 | F71: InflataPark | G71: 2026-08 | H71: 3 | I71: 3 | J71: 3 | K71: 597 | L71: =IF($B71="","",IFERROR(INDEX('Code Mapping'!$D$5:$D$1753,MATCH($B71,'Code Mapping'!$A$5:$A$1753,0)),"Unmapped")) -> Unmapped | M71: =IF($B71="","",IFERROR(INDEX('Code Mapping'!$E$5:$E$1753,MATCH($B71,'Code Mapping'!$A$5:$A$1753,0)),"Unmapped")) -> Unmapped | N71: =IF($F71="","",$F71) -> InflataPark
A72: 8318 | B72: dmqnb15 | D72: QNB | E72: 133 | F72: Urban Arena | G72: 2026-08 | H72: 24 | I72: 83 | J72: 83 | K72: 675 | L72: =IF($B72="","",IFERROR(INDEX('Code Mapping'!$D$5:$D$1753,MATCH($B72,'Code Mapping'!$A$5:$A$1753,0)),"Unmapped")) -> QNB Rewards | M72: =IF($B72="","",IFERROR(INDEX('Code Mapping'!$E$5:$E$1753,MATCH($B72,'Code Mapping'!$A$5:$A$1753,0)),"Unmapped")) -> Corporate discount | N72: =IF($F72="","",$F72) -> Urban Arena
A73: 8095 | B73: CBOGOE | C73: Entertainer BOGO | E73: 61 | F73: Crayons & Bricks Vendome | G73: 2026-08 | H73: 12 | I73: 12 | J73: 12 | K73: 1200 | L73: =IF($B73="","",IFERROR(INDEX('Code Mapping'!$D$5:$D$1753,MATCH($B73,'Code Mapping'!$A$5:$A$1753,0)),"Unmapped")) -> Entertainer | M73: =IF($B73="","",IFERROR(INDEX('Code Mapping'!$E$5:$E$1753,MATCH($B73,'Code Mapping'!$A$5:$A$1753,0)),"Unmapped")) -> Aggregator BOGO | N73: =IF($F73="","",$F73) -> Crayons & Bricks Vendome
A74: 8325 | B74: INFAMBBOGO2 | D74: E3 | E74: 91 | F74: InflataPark | G74: 2026-08 | H74: 3 | I74: 3 | J74: 3 | K74: 597 | L74: =IF($B74="","",IFERROR(INDEX('Code Mapping'!$D$5:$D$1753,MATCH($B74,'Code Mapping'!$A$5:$A$1753,0)),"Unmapped")) -> My Book | M74: =IF($B74="","",IFERROR(INDEX('Code Mapping'!$E$5:$E$1753,MATCH($B74,'Code Mapping'!$A$5:$A$1753,0)),"Unmapped")) -> Aggregator BOGO | N74: =IF($F74="","",$F74) -> InflataPark
A75: 8324 | B75: INFENTBOGO2 | D75: E3 | E75: 91 | F75: InflataPark | G75: 2026-08 | H75: 4 | I75: 4 | J75: 4 | K75: 796 | L75: =IF($B75="","",IFERROR(INDEX('Code Mapping'!$D$5:$D$1753,MATCH($B75,'Code Mapping'!$A$5:$A$1753,0)),"Unmapped")) -> Entertainer | M75: =IF($B75="","",IFERROR(INDEX('Code Mapping'!$E$5:$E$1753,MATCH($B75,'Code Mapping'!$A$5:$A$1753,0)),"Unmapped")) -> Aggregator BOGO | N75: =IF($F75="","",$F75) -> InflataPark
A76: 8052 | B76: INFIMTYD | C76: Imtyazat 15% Discount | D76: E3 | E76: 91 | F76: InflataPark | G76: 2026-08 | H76: 108 | I76: 447 | J76: 447 | K76: 3444 | L76: =IF($B76="","",IFERROR(INDEX('Code Mapping'!$D$5:$D$1753,MATCH($B76,'Code Mapping'!$A$5:$A$1753,0)),"Unmapped")) -> Imtyazat | M76: =IF($B76="","",IFERROR(INDEX('Code Mapping'!$E$5:$E$1753,MATCH($B76,'Code Mapping'!$A$5:$A$1753,0)),"Unmapped")) -> Corporate discount | N76: =IF($F76="","",$F76) -> InflataPark
A77: 8053 | B77: INFPHSED | C77: Public Health Sector Employees 20% Discount | E77: 91 | F77: InflataPark | G77: 2026-08 | H77: 66 | I77: 210 | J77: 210 | K77: 2064 | L77: =IF($B77="","",IFERROR(INDEX('Code Mapping'!$D$5:$D$1753,MATCH($B77,'Code Mapping'!$A$5:$A$1753,0)),"Unmapped")) -> Public Health Sector (Sogha) | M77: =IF($B77="","",IFERROR(INDEX('Code Mapping'!$E$5:$E$1753,MATCH($B77,'Code Mapping'!$A$5:$A$1753,0)),"Unmapped")) -> Corporate discount | N77: =IF($F77="","",$F77) -> InflataPark
A78: 8055 | B78: INFQAD | C78: Qatar Airways 15% Discount | E78: 91 | F78: InflataPark | G78: 2026-08 | H78: 68 | I78: 177 | J78: 177 | K78: 1223.25 | L78: =IF($B78="","",IFERROR(INDEX('Code Mapping'!$D$5:$D$1753,MATCH($B78,'Code Mapping'!$A$5:$A$1753,0)),"Unmapped")) -> Qatar Airways | M78: =IF($B78="","",IFERROR(INDEX('Code Mapping'!$E$5:$E$1753,MATCH($B78,'Code Mapping'!$A$5:$A$1753,0)),"Unmapped")) -> Corporate discount | N78: =IF($F78="","",$F78) -> InflataPark
A79: 8056 | B79: INFQFD | C79: Qatar Foundation 15% Discount | E79: 91 | F79: InflataPark | G79: 2026-08 | H79: 17 | I79: 76 | J79: 76 | K79: 643.5 | L79: =IF($B79="","",IFERROR(INDEX('Code Mapping'!$D$5:$D$1753,MATCH($B79,'Code Mapping'!$A$5:$A$1753,0)),"Unmapped")) -> Qatar Foundation | M79: =IF($B79="","",IFERROR(INDEX('Code Mapping'!$E$5:$E$1753,MATCH($B79,'Code Mapping'!$A$5:$A$1753,0)),"Unmapped")) -> Corporate discount | N79: =IF($F79="","",$F79) -> InflataPark
A80: 8316 | B80: infqnb15 | D80: QNB | E80: 91 | F80: InflataPark | G80: 2026-08 | H80: 2 | I80: 9 | J80: 9 | K80: 57.75 | L80: =IF($B80="","",IFERROR(INDEX('Code Mapping'!$D$5:$D$1753,MATCH($B80,'Code Mapping'!$A$5:$A$1753,0)),"Unmapped")) -> QNB Rewards | M80: =IF($B80="","",IFERROR(INDEX('Code Mapping'!$E$5:$E$1753,MATCH($B80,'Code Mapping'!$A$5:$A$1753,0)),"Unmapped")) -> Corporate discount | N80: =IF($F80="","",$F80) -> InflataPark
A81: 8048 | B81: INFBEIND | C81: Bein 15% Discount | E81: 91 | F81: InflataPark | G81: 2026-08 | H81: 1 | I81: 2 | J81: 2 | K81: 10.5 | L81: =IF($B81="","",IFERROR(INDEX('Code Mapping'!$D$5:$D$1753,MATCH($B81,'Code Mapping'!$A$5:$A$1753,0)),"Unmapped")) -> Bein | M81: =IF($B81="","",IFERROR(INDEX('Code Mapping'!$E$5:$E$1753,MATCH($B81,'Code Mapping'!$A$5:$A$1753,0)),"Unmapped")) -> Corporate discount | N81: =IF($F81="","",$F81) -> InflataPark
A82: 8322 | B82: loyaltykds | C82: loyalty pass free city pass | D82: E3 | E82: 94 | F82: Kids City Driving School | G82: 2026-07 | H82: 8 | I82: 8 | J82: 8 | K82: 360 | L82: =IF($B82="","",IFERROR(INDEX('Code Mapping'!$D$5:$D$1753,MATCH($B82,'Code Mapping'!$A$5:$A$1753,0)),"Unmapped")) -> Internal / promotion | M82: =IF($B82="","",IFERROR(INDEX('Code Mapping'!$E$5:$E$1753,MATCH($B82,'Code Mapping'!$A$5:$A$1753,0)),"Unmapped")) -> Internal / promotion | N82: =IF($F82="","",$F82) -> Kids City Driving School
A83: 8114 | B83: rb20 | D83: E3 | E83: 133 | F83: Urban Arena | G83: 2026-07 | H83: 1 | I83: 1 | J83: 1 | K83: 3 | L83: =IF($B83="","",IFERROR(INDEX('Code Mapping'!$D$5:$D$1753,MATCH($B83,'Code Mapping'!$A$5:$A$1753,0)),"Unmapped")) -> Internal / promotion | M83: =IF($B83="","",IFERROR(INDEX('Code Mapping'!$E$5:$E$1753,MATCH($B83,'Code Mapping'!$A$5:$A$1753,0)),"Unmapped")) -> Internal / promotion | N83: =IF($F83="","",$F83) -> Urban Arena
A84: 6827 | B84: MYBVD | E84: 61 | F84: Crayons & Bricks Vendome | G84: 2026-07 | H84: 8 | I84: 8 | J84: 8 | K84: 800 | L84: =IF($B84="","",IFERROR(INDEX('Code Mapping'!$D$5:$D$1753,MATCH($B84,'Code Mapping'!$A$5:$A$1753,0)),"Unmapped")) -> My Book | M84: =IF($B84="","",IFERROR(INDEX('Code Mapping'!$E$5:$E$1753,MATCH($B84,'Code Mapping'!$A$5:$A$1753,0)),"Unmapped")) -> Aggregator BOGO | N84: =IF($F84="","",$F84) -> Crayons & Bricks Vendome
A85: 8159 | B85: MC91G3KD | C85: Flat 100 off on total order | D85: E3 | E85: 94 | F85: Kids City Driving School | G85: 2026-07 | H85: 1 | I85: 1 | J85: 1 | K85: 199 | L85: =IF($B85="","",IFERROR(INDEX('Code Mapping'!$D$5:$D$1753,MATCH($B85,'Code Mapping'!$A$5:$A$1753,0)),"Unmapped")) -> Unmapped | M85: =IF($B85="","",IFERROR(INDEX('Code Mapping'!$E$5:$E$1753,MATCH($B85,'Code Mapping'!$A$5:$A$1753,0)),"Unmapped")) -> Unmapped | N85: =IF($F85="","",$F85) -> Kids City Driving School
A86: 8158 | B86: MC11F2KD | C86: Flat 100 off on total order | D86: E3 | E86: 94 | F86: Kids City Driving School | G86: 2026-07 | H86: 1 | I86: 1 | J86: 1 | K86: 199 | L86: =IF($B86="","",IFERROR(INDEX('Code Mapping'!$D$5:$D$1753,MATCH($B86,'Code Mapping'!$A$5:$A$1753,0)),"Unmapped")) -> Unmapped | M86: =IF($B86="","",IFERROR(INDEX('Code Mapping'!$E$5:$E$1753,MATCH($B86,'Code Mapping'!$A$5:$A$1753,0)),"Unmapped")) -> Unmapped | N86: =IF($F86="","",$F86) -> Kids City Driving School
A87: 8347 | B87: KDSBOGOM | D87: E3 | E87: 94 | F87: Kids City Driving School | G87: 2026-07 | H87: 11 | I87: 11 | J87: 11 | K87: 2189 | L87: =IF($B87="","",IFERROR(INDEX('Code Mapping'!$D$5:$D$1753,MATCH($B87,'Code Mapping'!$A$5:$A$1753,0)),"Unmapped")) -> My Book | M87: =IF($B87="","",IFERROR(INDEX('Code Mapping'!$E$5:$E$1753,MATCH($B87,'Code Mapping'!$A$5:$A$1753,0)),"Unmapped")) -> Aggregator BOGO | N87: =IF($F87="","",$F87) -> Kids City Driving School
A88: 8314 | B88: loyaltyinf | D88: E3 | E88: 91 | F88: InflataPark | G88: 2026-07 | H88: 2 | I88: 2 | J88: 2 | K88: 90 | L88: =IF($B88="","",IFERROR(INDEX('Code Mapping'!$D$5:$D$1753,MATCH($B88,'Code Mapping'!$A$5:$A$1753,0)),"Unmapped")) -> Internal / promotion | M88: =IF($B88="","",IFERROR(INDEX('Code Mapping'!$E$5:$E$1753,MATCH($B88,'Code Mapping'!$A$5:$A$1753,0)),"Unmapped")) -> Internal / promotion | N88: =IF($F88="","",$F88) -> InflataPark
A89: 8313 | B89: loyalty | C89: Loyalty customer free rookie pass | D89: E3 | E89: 133 | F89: Urban Arena | G89: 2026-07 | H89: 2 | I89: 2 | J89: 2 | K89: 90 | L89: =IF($B89="","",IFERROR(INDEX('Code Mapping'!$D$5:$D$1753,MATCH($B89,'Code Mapping'!$A$5:$A$1753,0)),"Unmapped")) -> Internal / promotion | M89: =IF($B89="","",IFERROR(INDEX('Code Mapping'!$E$5:$E$1753,MATCH($B89,'Code Mapping'!$A$5:$A$1753,0)),"Unmapped")) -> Internal / promotion | N89: =IF($F89="","",$F89) -> Urban Arena
A90: 8068 | B90: KCDSURBOGO | C90: Urban Point BOGO | E90: 94 | F90: Kids City Driving School | G90: 2026-07 | H90: 18 | I90: 22 | J90: 22 | K90: 4378 | L90: =IF($B90="","",IFERROR(INDEX('Code Mapping'!$D$5:$D$1753,MATCH($B90,'Code Mapping'!$A$5:$A$1753,0)),"Unmapped")) -> Urban Point | M90: =IF($B90="","",IFERROR(INDEX('Code Mapping'!$E$5:$E$1753,MATCH($B90,'Code Mapping'!$A$5:$A$1753,0)),"Unmapped")) -> Aggregator BOGO | N90: =IF($F90="","",$F90) -> Kids City Driving School
A91: 8328 | B91: ST15 | C91: school trip 15% off | D91: E3 | E91: 91 | F91: InflataPark | G91: 2026-07 | H91: 2 | I91: 50 | J91: 50 | K91: 337.5 | L91: =IF($B91="","",IFERROR(INDEX('Code Mapping'!$D$5:$D$1753,MATCH($B91,'Code Mapping'!$A$5:$A$1753,0)),"Unmapped")) -> Unmapped | M91: =IF($B91="","",IFERROR(INDEX('Code Mapping'!$E$5:$E$1753,MATCH($B91,'Code Mapping'!$A$5:$A$1753,0)),"Unmapped")) -> Unmapped | N91: =IF($F91="","",$F91) -> InflataPark
A92: 8075 | B92: RENA | C92: Imtyazat 15% Discount | E92: 133 | F92: Urban Arena | G92: 2026-07 | H92: 27 | I92: 116 | J92: 116 | K92: 955.8 | L92: =IF($B92="","",IFERROR(INDEX('Code Mapping'!$D$5:$D$1753,MATCH($B92,'Code Mapping'!$A$5:$A$1753,0)),"Unmapped")) -> Imtyazat | M92: =IF($B92="","",IFERROR(INDEX('Code Mapping'!$E$5:$E$1753,MATCH($B92,'Code Mapping'!$A$5:$A$1753,0)),"Unmapped")) -> Corporate discount | N92: =IF($F92="","",$F92) -> Urban Arena
A93: 8076 | B93: UNAR | C93: Public Health Sector Employees 20% Discount | E93: 133 | F93: Urban Arena | G93: 2026-07 | H93: 70 | I93: 250 | J93: 250 | K93: 2576 | L93: =IF($B93="","",IFERROR(INDEX('Code Mapping'!$D$5:$D$1753,MATCH($B93,'Code Mapping'!$A$5:$A$1753,0)),"Unmapped")) -> Public Health Sector (Sogha) | M93: =IF($B93="","",IFERROR(INDEX('Code Mapping'!$E$5:$E$1753,MATCH($B93,'Code Mapping'!$A$5:$A$1753,0)),"Unmapped")) -> Corporate discount | N93: =IF($F93="","",$F93) -> Urban Arena
A94: 8312 | B94: subr50 | C94: Ahmad Client 50% | D94: E3 | E94: 133 | F94: Urban Arena | G94: 2026-07 | H94: 2 | I94: 7 | J94: 7 | K94: 237.5 | L94: =IF($B94="","",IFERROR(INDEX('Code Mapping'!$D$5:$D$1753,MATCH($B94,'Code Mapping'!$A$5:$A$1753,0)),"Unmapped")) -> Unmapped | M94: =IF($B94="","",IFERROR(INDEX('Code Mapping'!$E$5:$E$1753,MATCH($B94,'Code Mapping'!$A$5:$A$1753,0)),"Unmapped")) -> Unmapped | N94: =IF($F94="","",$F94) -> Urban Arena
A95: 8081 | B95: UAQMC | C95: Qatar Media Corporation 15% Discount | E95: 133 | F95: Urban Arena | G95: 2026-07 | H95: 8 | I95: 42 | J95: 42 | K95: 310.5 | L95: =IF($B95="","",IFERROR(INDEX('Code Mapping'!$D$5:$D$1753,MATCH($B95,'Code Mapping'!$A$5:$A$1753,0)),"Unmapped")) -> Qatar Media Corporation | M95: =IF($B95="","",IFERROR(INDEX('Code Mapping'!$E$5:$E$1753,MATCH($B95,'Code Mapping'!$A$5:$A$1753,0)),"Unmapped")) -> Corporate discount | N95: =IF($F95="","",$F95) -> Urban Arena
A96: 8080 | B96: UARB | C96: Qatar Investment Authority 15% Discount | E96: 133 | F96: Urban Arena | G96: 2026-07 | H96: 3 | I96: 10 | J96: 10 | K96: 84 | L96: =IF($B96="","",IFERROR(INDEX('Code Mapping'!$D$5:$D$1753,MATCH($B96,'Code Mapping'!$A$5:$A$1753,0)),"Unmapped")) -> Qatar Investment Authority | M96: =IF($B96="","",IFERROR(INDEX('Code Mapping'!$E$5:$E$1753,MATCH($B96,'Code Mapping'!$A$5:$A$1753,0)),"Unmapped")) -> Corporate discount | N96: =IF($F96="","",$F96) -> Urban Arena
A97: 8071 | B97: UARE | C97: Bein 15% Discount | E97: 133 | F97: Urban Arena | G97: 2026-07 | H97: 8 | I97: 46 | J97: 46 | K97: 414 | L97: =IF($B97="","",IFERROR(INDEX('Code Mapping'!$D$5:$D$1753,MATCH($B97,'Code Mapping'!$A$5:$A$1753,0)),"Unmapped")) -> Bein | M97: =IF($B97="","",IFERROR(INDEX('Code Mapping'!$E$5:$E$1753,MATCH($B97,'Code Mapping'!$A$5:$A$1753,0)),"Unmapped")) -> Corporate discount | N97: =IF($F97="","",$F97) -> Urban Arena
A98: 8093 | B98: UBOFFM | C98: My Book BOGO | E98: 133 | F98: Urban Arena | G98: 2026-07 | H98: 38 | I98: 38 | J98: 38 | K98: 7562 | L98: =IF($B98="","",IFERROR(INDEX('Code Mapping'!$D$5:$D$1753,MATCH($B98,'Code Mapping'!$A$5:$A$1753,0)),"Unmapped")) -> My Book | M98: =IF($B98="","",IFERROR(INDEX('Code Mapping'!$E$5:$E$1753,MATCH($B98,'Code Mapping'!$A$5:$A$1753,0)),"Unmapped")) -> Aggregator BOGO | N98: =IF($F98="","",$F98) -> Urban Arena
A99: 8091 | B99: UBOGOC | C99: Classmate BOGO | E99: 133 | F99: Urban Arena | G99: 2026-07 | H99: 6 | I99: 6 | J99: 6 | K99: 1194 | L99: =IF($B99="","",IFERROR(INDEX('Code Mapping'!$D$5:$D$1753,MATCH($B99,'Code Mapping'!$A$5:$A$1753,0)),"Unmapped")) -> Classmate | M99: =IF($B99="","",IFERROR(INDEX('Code Mapping'!$E$5:$E$1753,MATCH($B99,'Code Mapping'!$A$5:$A$1753,0)),"Unmapped")) -> Aggregator BOGO | N99: =IF($F99="","",$F99) -> Urban Arena
A100: 8078 | B100: UENA | C100: Qatar Airways 15% Discount | E100: 133 | F100: Urban Arena | G100: 2026-07 | H100: 56 | I100: 247 | J100: 247 | K100: 2101.2 | L100: =IF($B100="","",IFERROR(INDEX('Code Mapping'!$D$5:$D$1753,MATCH($B100,'Code Mapping'!$A$5:$A$1753,0)),"Unmapped")) -> Qatar Airways | M100: =IF($B100="","",IFERROR(INDEX('Code Mapping'!$E$5:$E$1753,MATCH($B100,'Code Mapping'!$A$5:$A$1753,0)),"Unmapped")) -> Corporate discount | N100: =IF($F100="","",$F100) -> Urban Arena
A101: 8094 | B101: UGBOGU | C101: Urban Point BOGO | E101: 133 | F101: Urban Arena | G101: 2026-07 | H101: 30 | I101: 30 | J101: 30 | K101: 5970 | L101: =IF($B101="","",IFERROR(INDEX('Code Mapping'!$D$5:$D$1753,MATCH($B101,'Code Mapping'!$A$5:$A$1753,0)),"Unmapped")) -> Urban Point | M101: =IF($B101="","",IFERROR(INDEX('Code Mapping'!$E$5:$E$1753,MATCH($B101,'Code Mapping'!$A$5:$A$1753,0)),"Unmapped")) -> Aggregator BOGO | N101: =IF($F101="","",$F101) -> Urban Arena
...

Sheet MoM Follow-up
A1: Follow-up on previous minutes: FEC Management and Operations Review, 8 September 2026
A2: Update the yellow cells before each Tuesday meeting. Status: Open / In progress / Closed.
A4: # | B4: Item | C4: Venue | D4: Decision on 8 Sep | E4: Owner | F4: Due | G4: Status | H4: Update this week
A5: 1 | B5: Q-Balloon backside safety grill (critical safety; incident reported) | C5: KDS | D5: Approved by higher management; final quotation to be submitted for budget release and installation | E5: Operations / Maintenance | F5: Immediate | G5: Open
A6: 2 | B6: Socks stock availability (escalated approx. 85 days) | C6: KDS / InflataPark / Urban Arena | D6: Immediate need from 20,000-pair shipment; Operations to submit quantity by venue and size; fixed reorder quantity and minimum level to follow; weekly stock monitoring | E6: Operations | F6: This week | G6: Open
A7: 3 | B7: InflataPark blowers (5 x 2500 W) and Inflata Kids white lighting | C7: InflataPark | D7: Maintenance to proceed with service and lighting; PR for final approval once quotations received | E7: Maintenance | F7: Immediate | G7: Open
A8: 4 | B8: Commercial Registration renewals (KDS and InflataPark expired 13 Sep) | C8: KDS / InflataPark | D8: To be signed off by 12 September | E8: Operations / Admin | F8: 12 Sep | G8: Open
A9: 5 | B9: Urban Arena Qatar Tourism licence (expires 15 Sep) | C9: Urban Arena | D9: To be processed before 15 September | E9: Operations / Admin | F9: 15 Sep | G9: Open
A10: 6 | B10: Mandatory safety training and Training Development Programme | C10: KDS / C&B DAS / C&B Vendome / Aspire Carousel | D10: Consolidated training plan (courses, staff, providers, schedule, cost) for approval; initial schedule mid-September | E10: Operations / HR | F10: Mid-Sep | G10: Open
A11: 7 | B11: CCTV UPS replacement | C11: KDS | D11: Approved subject to quotation and final approval | E11: Quasain / Operations | F11: This week | G11: Open
A12: 8 | B12: CCTV room rack design and budget | C12: KDS | D12: Quasain to confirm design, then quotation to higher management | E12: Quasain | F12: This week | G12: Open
A13: 9 | B13: Additional wristbands (approx. 150 for Urban Arena) and Yalla Wall protection material | C13: KDS / Urban Arena | D13: Wristbands required; Quasain to confirm alternative sourcing for Yalla Wall material | E13: Quasain | F13: TBC | G13: Open
A14: 10 | B14: Spare parts for attractions | C14: Urban Arena / KDS / InflataPark / C&B Vendome | D14: Russell to finalise consolidated sheet; identify items in current shipment; quotations for the rest | E14: Russell | F14: This week | G14: Open
A15: 11 | B15: Fixed monthly operational floats | C15: Multi-venue | D15: QAR 1,000 birthday events (Louie) and QAR 300 Urban Arena supervisor approved, to PR system; QAR 2,000 maintenance float not approved | E15: Operations | F15: This week | G15: Open
A16: 12 | B16: Team performance incentive and team building (August campaign: 1,393 reviews; KDS 280 to 740) | C16: All venues | D16: Formal plan to be prepared; higher management to set sales targets for next four months | E16: Operations / Management | F16: September | G16: Open
... A28: 24 | B28: C&B Vendome activity plan (slime, acrylic, figurine painting, small slides) with pricing | C28: C&B Vendome | D28: Prepare plan and pricing | E28: C&B Vendome Ops / Rajan Pathak | F28: TBC | G28: Open
